Workbook

Sheet Leia-me
B2: FAST Insights — modelo financeiro
B3: Suporte quantitativo ao business plan · Rodrigo Garcia, franqueado FAST Limão · 08/09/2026
A6: COMO USAR
B7: 1. Mude só o azul | C7: Toda célula com texto AZUL na aba Premissas é uma entrada que você pode editar. Células pretas são fórmulas — não digite por cima delas.
B8: 2. Fundo amarelo = decisivo | C8: As entradas com fundo amarelo são as que mais mexem no resultado. Comece por elas.
B9: 3. O resto se ajusta sozinho | C9: Modelo mensal, Resumo e Cenários recalculam a partir das Premissas. Nenhum número deste arquivo é digitado duas vezes.
B10: 4. Se abrir e vier vazio | C10: Alguns visualizadores não recalculam sozinhos. Abra no Excel, LibreOffice ou Google Sheets e mande recalcular (no Excel: Ctrl+Alt+F9).
A12: AS ABAS
B13: Premissas | C13: Todas as entradas do modelo, agrupadas por tema, com a fonte de cada número.
B14: Modelo mensal | C14: 36 meses, linha a linha: lojas, receita, custos, resultado e caixa acumulado.
B15: Resumo | C15: Os números de decisão — capital necessário, ponto de equilíbrio, economia unitária — e os dois gráficos.
B16: Cenários | C16: Nove cenários calculados ao vivo, inclusive os de participação da franqueadora na receita.
B17: Descoberta | C17: Os 34 itens que faltam validar. Marque o status e anote a resposta.
A19: LEGENDA DE CORES
B20: Azul | C20: Número digitado — é uma premissa, e você pode mudar.
B21: Preto | C21: Fórmula calculada dentro da própria aba.
B22: Verde | C22: Fórmula que busca valor em outra aba.
B23: Fundo amarelo | C23: Premissa decisiva, ou campo para você preencher.
A25: TRÊS AVISOS HONESTOS
B26: Projeção, não previsão | C26: Cada linha aqui é uma suposição explícita. As que ainda não foram verificadas estão na aba Descoberta — seis delas são bloqueantes.
B27: Antes de impostos, por padrão | C27: A alíquota sobre a receita da empresa de software vem zerada (item N3 da Descoberta). Preencha-a em Premissas assim que o contador responder: no Simples, algo entre 6% e 16%.
B28: Adoção já é líquida de churn | C28: A curva de adoção representa lojas ativas, já descontando quem sai. O churn das Premissas serve só para calcular o LTV.

Sheet Premissas
A1: Premissas
A2: Edite apenas as células azuis. A célula B7 escolhe o modelo comercial e reconfigura sete premissas de uma vez.
A4: Premissa | B4: Em uso | C4: Sem homologação | D4: Com homologação | E4: Origem / observação
A6: MODELO COMERCIAL — a chave que muda tudo
A7: Modelo em uso (1 = COM homologação · 0 = SEM homologação) | B7: 1 | E7: 1 = homologado obrigatório em toda a rede, com cobrança consolidada pela franqueadora. 0 = venda voluntária, loja a loja. Trocar aqui reconfigura as sete linhas abaixo de uma vez.
C8: Sem homologação | D8: Com homologação
A9: Preço por loja | B9: =IF($B$7=1,D9,C9) -> 299 | C9: =B24 -> 319 | D9: 299 | E9: Sem homologação vem do mix de planos; com homologação é preço único para a rede toda.
A10: Teto de adoção | B10: =IF($B$7=1,D10,C10) -> 0.95 | C10: 0.65 | D10: 0.95 | E10: Obrigatório não é venda: os 5% que faltam são lojas em implantação e em transição.
A11: Mês central da curva | B11: =IF($B$7=1,D11,C11) -> 12 | C11: 16 | D11: 12 | E11: A franqueadora marca prazo — não há convencimento loja a loja.
A12: Inclinação da curva | B12: =IF($B$7=1,D12,C12) -> 0.45 | C12: 0.32 | D12: 0.45 | E12: Implantação em bloco, não gota a gota.
A13: CAC por loja | B13: =IF($B$7=1,D13,C13) -> 50 | C13: 400 | D13: 50 | E13: Sem esforço de venda, sobra só o onboarding.
A14: Cobrança por loja | B14: =IF($B$7=1,D14,C14) -> 0 | C14: 3 | D14: 0 | E14: No consolidado é uma fatura só: a taxa por loja desaparece.
A15: Participação da franqueadora | B15: =IF($B$7=1,D15,C15) -> 0.25 | C15: 0 | D15: 0.25 | E15: O que a franqueadora cobra para tornar obrigatório e cobrar das lojas por você.
A17: PLANOS E MIX — usados apenas no modelo SEM homologação
A18: Plano | B18: Preço R$/mês | C18: Mix
A19: Essencial | B19: 199 | C19: 0.4
A20: Gestão | B20: 349 | C20: 0.45
A21: Crescimento | B21: 549 | C21: 0.15
A22: Soma do mix (precisa dar 100%) | C22: =SUM(C19:C21) -> 1
A24: Ticket médio do mix | B24: =SUMPRODUCT(B19:B21,C19:C21) -> 319 | E24: É este o preço usado quando B7 = 0.
A26: CUSTO POR LOJA
A27: Infraestrutura | B27: 8 | C27: R$/mês | E27: Servidor, banco e armazenamento rateados. A medir no piloto (item P1).
A28: Suporte | B28: 34 | C28: R$/mês | E28: 1 pessoa de CS para ~175 lojas. A medir no piloto (item N2).
A29: Cobrança | B29: =Premissas!$B$14 -> 0 | C29: R$/mês | E29: Vem do bloco Modelo comercial (linha 14).
A30: API / parceria de dados | B30: 0 | C30: R$/mês | E30: Zero enquanto a cota for do plano da loja. Itens T2 e T4 da Descoberta.
A31: Custo variável total | B31: =SUM(B27:B30) -> 42 | C31: R$/mês | E31: Soma das quatro linhas acima.
A32: Margem de contribuição | B32: =Premissas!$B$9-B31 -> 257 | C32: R$/mês | E32: Preço por loja menos custo variável.
A33: Margem de contribuição % | B33: =IF(Premissas!$B$9=0,0,B32/Premissas!$B$9) -> 0.85953177 | C33: %
A35: RETENÇÃO
A36: Churn mensal | B36: 0.015 | C36: %/mês | E36: Conservador; inclui fechamento de loja. Usado só no LTV — a curva de adoção já é líquida. No modelo obrigatório o churn real tende a ser menor ainda.
A38: REDE E CRONOGRAMA
A39: Lojas na rede hoje | B39: 431 | C39: lojas | E39: Fast Escova 401 + Fast Spa 30 em operação no fim de 2026. Fonte: Times Brasil / Mapa das Franquias, 09/2026.
A40: Lojas na rede no mês 36 | B40: 600 | C40: lojas | E40: Plano de expansão: +159 lojas em 2026. Fonte: mesma acima.
A41: Mês em que começam as vendas | B41: 7 | C41: mês | E41: Depois do acordo jurídico e do piloto.
A42: Atraso na homologação | B42: 0 | C42: meses | E42: Empurra todo o cronograma. Teste 6 para ver o efeito de a franqueadora demorar.
A44: PAINEL DA REDE (FRANQUEADORA)
A45: Mensalidade | B45: 10000 | C45: R$/mês | E45: Meio da faixa proposta de R$ 8 a 15 mil.
A46: Mês de início | B46: 9 | C46: mês | E46: Depois da Fase 2, quando o painel da rede existe.
A48: CUSTO FIXO POR FASE
A49: Fase 0 — até o mês 2 | B49: 5000 | C49: R$/mês | E49: Jurídico e negociação.
A50: Fase 1 — meses 3 a 5 | B50: 22000 | C50: R$/mês | E50: Dev sênior parceiro 16k + infra 3k + jurídico 3k.
A51: Fase 2 — meses 6 a 8 | B51: 28000 | C51: R$/mês | E51: Acrescenta CS meio período.
A52: Regime — mês 9 em diante | B52: 35000 | C52: R$/mês | E52: Dev 16k + CS 6k + infra e contabilidade 3k + pró-labore 10k. Sem pró-labore: 25.000.
A54: INVESTIMENTOS NÃO RECORRENTES
A55: Mês 1 | B55: 8000 | C55: R$ | E55: Fechar o acesso, contratos, jurídico inicial.
A56: Mês 3 | B56: 12000 | C56: R$ | E56: Setup do MVP: infraestrutura, ferramentas, marca.
A57: Mês 6 | B57: 10000 | C57: R$ | E57: Painel da rede e integração de cobrança.
A59: IMPOSTOS
A60: Impostos sobre a receita | B60: 0 | C60: % | E60: ITEM N3 EM ABERTO — no Simples anexo III, algo entre 6% e 16%. Preencher assim que o contador responder.
A62: Fontes de mercado: Times Brasil, Mapa das Franquias e Portal do Franchising (setembro de 2026).
A63: Cláusulas que sustentam a obrigatoriedade: 7.6, 12.8, 12.11, 2.3 e xlii do contrato de franquia assinado em 27/01/2026.
A65: AUXILIARES — usados pela aba Cenários
A66: Custo variável sem homologação | B66: =B27+B28+C14+B30 -> 45 | C66: R$/mês | E66: Infra + suporte + cobrança por loja + API.
A67: Custo variável com homologação | B67: =B27+B28+D14+B30 -> 42 | C67: R$/mês | E67: A cobrança por loja desaparece: é uma fatura só.

Sheet Modelo mensal
A1: Modelo mensal — 36 meses
A2: Todas as colunas são fórmulas que leem a aba Premissas. Custos aparecem como negativos.
A4: Mês | B4: Lojas na rede | C4: Lojas pagando | D4: Novas no mês | E4: Receita planos | F4: Painel da Rede | G4: Receita total | H4: Impostos | I4: Custo variável | J4: Custo fixo | K4: Investimento | L4: Resultado | M4: Caixa acumulado | N4: 1º mês positivo | O4: 1º mês caixa > 0
A5: 1 | B5: =Premissas!$B$39+(Premissas!$B$40-Premissas!$B$39)*A5/36 -> 435.69444 | C5: =IF(A5-Premissas!$B$42<Premissas!$B$41,0,Premissas!$B$10*B5/(1+EXP(-Premissas!$B$12*(A5-Premissas!$B$42-Premissas!$B$11)))) -> 0 | D5: =C5 -> 0 | E5: =C5*Premissas!$B$9*(1-Premissas!$B$15) -> 0 | F5: =IF(A5>=Premissas!$B$46+Premissas!$B$42,Premissas!$B$45*(1-Premissas!$B$15),0) -> 0 | G5: =E5+F5 -> 0 | H5: =-G5*Premissas!$B$60 -> 0 | I5: =-(C5*Premissas!$B$31+D5*Premissas!$B$13) -> 0 | J5: =-IF(A5-Premissas!$B$42<=2,Premissas!$B$49,IF(A5-Premissas!$B$42<=5,Premissas!$B$50,IF(A5-Premissas!$B$42<=8,Premissas!$B$51,Premissas!$B$52))) -> -5000 | K5: =-IF(A5=1+Premissas!$B$42,Premissas!$B$55,IF(A5=3+Premissas!$B$42,Premissas!$B$56,IF(A5=6+Premissas!$B$42,Premissas!$B$57,0))) -> -8000 | L5: =G5+H5+I5+J5+K5 -> -13000 | M5: =L5 -> -13000 | N5: =IF(L5>0,A5,9999) -> 9999 | O5: =IF(M5>0,A5,9999) -> 9999
A6: 2 | B6: =Premissas!$B$39+(Premissas!$B$40-Premissas!$B$39)*A6/36 -> 440.38889 | C6: =IF(A6-Premissas!$B$42<Premissas!$B$41,0,Premissas!$B$10*B6/(1+EXP(-Premissas!$B$12*(A6-Premissas!$B$42-Premissas!$B$11)))) -> 0 | D6: =MAX(0,C6-C5) -> 0 | E6: =C6*Premissas!$B$9*(1-Premissas!$B$15) -> 0 | F6: =IF(A6>=Premissas!$B$46+Premissas!$B$42,Premissas!$B$45*(1-Premissas!$B$15),0) -> 0 | G6: =E6+F6 -> 0 | H6: =-G6*Premissas!$B$60 -> 0 | I6: =-(C6*Premissas!$B$31+D6*Premissas!$B$13) -> 0 | J6: =-IF(A6-Premissas!$B$42<=2,Premissas!$B$49,IF(A6-Premissas!$B$42<=5,Premissas!$B$50,IF(A6-Premissas!$B$42<=8,Premissas!$B$51,Premissas!$B$52))) -> -5000 | K6: =-IF(A6=1+Premissas!$B$42,Premissas!$B$55,IF(A6=3+Premissas!$B$42,Premissas!$B$56,IF(A6=6+Premissas!$B$42,Premissas!$B$57,0))) -> 0 | L6: =G6+H6+I6+J6+K6 -> -5000 | M6: =M5+L6 -> -18000 | N6: =IF(L6>0,A6,9999) -> 9999 | O6: =IF(M6>0,A6,9999) -> 9999
A7: 3 | B7: =Premissas!$B$39+(Premissas!$B$40-Premissas!$B$39)*A7/36 -> 445.08333 | C7: =IF(A7-Premissas!$B$42<Premissas!$B$41,0,Premissas!$B$10*B7/(1+EXP(-Premissas!$B$12*(A7-Premissas!$B$42-Premissas!$B$11)))) -> 0 | D7: =MAX(0,C7-C6) -> 0 | E7: =C7*Premissas!$B$9*(1-Premissas!$B$15) -> 0 | F7: =IF(A7>=Premissas!$B$46+Premissas!$B$42,Premissas!$B$45*(1-Premissas!$B$15),0) -> 0 | G7: =E7+F7 -> 0 | H7: =-G7*Premissas!$B$60 -> 0 | I7: =-(C7*Premissas!$B$31+D7*Premissas!$B$13) -> 0 | J7: =-IF(A7-Premissas!$B$42<=2,Premissas!$B$49,IF(A7-Premissas!$B$42<=5,Premissas!$B$50,IF(A7-Premissas!$B$42<=8,Premissas!$B$51,Premissas!$B$52))) -> -22000 | K7: =-IF(A7=1+Premissas!$B$42,Premissas!$B$55,IF(A7=3+Premissas!$B$42,Premissas!$B$56,IF(A7=6+Premissas!$B$42,Premissas!$B$57,0))) -> -12000 | L7: =G7+H7+I7+J7+K7 -> -34000 | M7: =M6+L7 -> -52000 | N7: =IF(L7>0,A7,9999) -> 9999 | O7: =IF(M7>0,A7,9999) -> 9999
A8: 4 | B8: =Premissas!$B$39+(Premissas!$B$40-Premissas!$B$39)*A8/36 -> 449.77778 | C8: =IF(A8-Premissas!$B$42<Premissas!$B$41,0,Premissas!$B$10*B8/(1+EXP(-Premissas!$B$12*(A8-Premissas!$B$42-Premissas!$B$11)))) -> 0 | D8: =MAX(0,C8-C7) -> 0 | E8: =C8*Premissas!$B$9*(1-Premissas!$B$15) -> 0 | F8: =IF(A8>=Premissas!$B$46+Premissas!$B$42,Premissas!$B$45*(1-Premissas!$B$15),0) -> 0 | G8: =E8+F8 -> 0 | H8: =-G8*Premissas!$B$60 -> 0 | I8: =-(C8*Premissas!$B$31+D8*Premissas!$B$13) -> 0 | J8: =-IF(A8-Premissas!$B$42<=2,Premissas!$B$49,IF(A8-Premissas!$B$42<=5,Premissas!$B$50,IF(A8-Premissas!$B$42<=8,Premissas!$B$51,Premissas!$B$52))) -> -22000 | K8: =-IF(A8=1+Premissas!$B$42,Premissas!$B$55,IF(A8=3+Premissas!$B$42,Premissas!$B$56,IF(A8=6+Premissas!$B$42,Premissas!$B$57,0))) -> 0 | L8: =G8+H8+I8+J8+K8 -> -22000 | M8: =M7+L8 -> -74000 | N8: =IF(L8>0,A8,9999) -> 9999 | O8: =IF(M8>0,A8,9999) -> 9999
A9: 5 | B9: =Premissas!$B$39+(Premissas!$B$40-Premissas!$B$39)*A9/36 -> 454.47222 | C9: =IF(A9-Premissas!$B$42<Premissas!$B$41,0,Premissas!$B$10*B9/(1+EXP(-Premissas!$B$12*(A9-Premissas!$B$42-Premissas!$B$11)))) -> 0 | D9: =MAX(0,C9-C8) -> 0 | E9: =C9*Premissas!$B$9*(1-Premissas!$B$15) -> 0 | F9: =IF(A9>=Premissas!$B$46+Premissas!$B$42,Premissas!$B$45*(1-Premissas!$B$15),0) -> 0 | G9: =E9+F9 -> 0 | H9: =-G9*Premissas!$B$60 -> 0 | I9: =-(C9*Premissas!$B$31+D9*Premissas!$B$13) -> 0 | J9: =-IF(A9-Premissas!$B$42<=2,Premissas!$B$49,IF(A9-Premissas!$B$42<=5,Premissas!$B$50,IF(A9-Premissas!$B$42<=8,Premissas!$B$51,Premissas!$B$52))) -> -22000 | K9: =-IF(A9=1+Premissas!$B$42,Premissas!$B$55,IF(A9=3+Premissas!$B$42,Premissas!$B$56,IF(A9=6+Premissas!$B$42,Premissas!$B$57,0))) -> 0 | L9: =G9+H9+I9+J9+K9 -> -22000 | M9: =M8+L9 -> -96000 | N9: =IF(L9>0,A9,9999) -> 9999 | O9: =IF(M9>0,A9,9999) -> 9999
A10: 6 | B10: =Premissas!$B$39+(Premissas!$B$40-Premissas!$B$39)*A10/36 -> 459.16667 | C10: =IF(A10-Premissas!$B$42<Premissas!$B$41,0,Premissas!$B$10*B10/(1+EXP(-Premissas!$B$12*(A10-Premissas!$B$42-Premissas!$B$11)))) -> 0 | D10: =MAX(0,C10-C9) -> 0 | E10: =C10*Premissas!$B$9*(1-Premissas!$B$15) -> 0 | F10: =IF(A10>=Premissas!$B$46+Premissas!$B$42,Premissas!$B$45*(1-Premissas!$B$15),0) -> 0 | G10: =E10+F10 -> 0 | H10: =-G10*Premissas!$B$60 -> 0 | I10: =-(C10*Premissas!$B$31+D10*Premissas!$B$13) -> 0 | J10: =-IF(A10-Premissas!$B$42<=2,Premissas!$B$49,IF(A10-Premissas!$B$42<=5,Premissas!$B$50,IF(A10-Premissas!$B$42<=8,Premissas!$B$51,Premissas!$B$52))) -> -28000 | K10: =-IF(A10=1+Premissas!$B$42,Premissas!$B$55,IF(A10=3+Premissas!$B$42,Premissas!$B$56,IF(A10=6+Premissas!$B$42,Premissas!$B$57,0))) -> -10000 | L10: =G10+H10+I10+J10+K10 -> -38000 | M10: =M9+L10 -> -134000 | N10: =IF(L10>0,A10,9999) -> 9999 | O10: =IF(M10>0,A10,9999) -> 9999
A11: 7 | B11: =Premissas!$B$39+(Premissas!$B$40-Premissas!$B$39)*A11/36 -> 463.86111 | C11: =IF(A11-Premissas!$B$42<Premissas!$B$41,0,Premissas!$B$10*B11/(1+EXP(-Premissas!$B$12*(A11-Premissas!$B$42-Premissas!$B$11)))) -> 42.017463 | D11: =MAX(0,C11-C10) -> 42.017463 | E11: =C11*Premissas!$B$9*(1-Premissas!$B$15) -> 9422.4161 | F11: =IF(A11>=Premissas!$B$46+Premissas!$B$42,Premissas!$B$45*(1-Premissas!$B$15),0) -> 0 | G11: =E11+F11 -> 9422.4161 | H11: =-G11*Premissas!$B$60 -> 0 | I11: =-(C11*Premissas!$B$31+D11*Premissas!$B$13) -> -3865.6066 | J11: =-IF(A11-Premissas!$B$42<=2,Premissas!$B$49,IF(A11-Premissas!$B$42<=5,Premissas!$B$50,IF(A11-Premissas!$B$42<=8,Premissas!$B$51,Premissas!$B$52))) -> -28000 | K11: =-IF(A11=1+Premissas!$B$42,Premissas!$B$55,IF(A11=3+Premissas!$B$42,Premissas!$B$56,IF(A11=6+Premissas!$B$42,Premissas!$B$57,0))) -> 0 | L11: =G11+H11+I11+J11+K11 -> -22443.19 | M11: =M10+L11 -> -156443.19 | N11: =IF(L11>0,A11,9999) -> 9999 | O11: =IF(M11>0,A11,9999) -> 9999
A12: 8 | B12: =Premissas!$B$39+(Premissas!$B$40-Premissas!$B$39)*A12/36 -> 468.55556 | C12: =IF(A12-Premissas!$B$42<Premissas!$B$41,0,Premissas!$B$10*B12/(1+EXP(-Premissas!$B$12*(A12-Premissas!$B$42-Premissas!$B$11)))) -> 63.141849 | D12: =MAX(0,C12-C11) -> 21.124386 | E12: =C12*Premissas!$B$9*(1-Premissas!$B$15) -> 14159.56 | F12: =IF(A12>=Premissas!$B$46+Premissas!$B$42,Premissas!$B$45*(1-Premissas!$B$15),0) -> 0 | G12: =E12+F12 -> 14159.56 | H12: =-G12*Premissas!$B$60 -> 0 | I12: =-(C12*Premissas!$B$31+D12*Premissas!$B$13) -> -3708.177 | J12: =-IF(A12-Premissas!$B$42<=2,Premissas!$B$49,IF(A12-Premissas!$B$42<=5,Premissas!$B$50,IF(A12-Premissas!$B$42<=8,Premissas!$B$51,Premissas!$B$52))) -> -28000 | K12: =-IF(A12=1+Premissas!$B$42,Premissas!$B$55,IF(A12=3+Premissas!$B$42,Premissas!$B$56,IF(A12=6+Premissas!$B$42,Premissas!$B$57,0))) -> 0 | L12: =G12+H12+I12+J12+K12 -> -17548.617 | M12: =M11+L12 -> -173991.81 | N12: =IF(L12>0,A12,9999) -> 9999 | O12: =IF(M12>0,A12,9999) -> 9999
A13: 9 | B13: =Premissas!$B$39+(Premissas!$B$40-Premissas!$B$39)*A13/36 -> 473.25 | C13: =IF(A13-Premissas!$B$42<Premissas!$B$41,0,Premissas!$B$10*B13/(1+EXP(-Premissas!$B$12*(A13-Premissas!$B$42-Premissas!$B$11)))) -> 92.556746 | D13: =MAX(0,C13-C12) -> 29.414896 | E13: =C13*Premissas!$B$9*(1-Premissas!$B$15) -> 20755.85 | F13: =IF(A13>=Premissas!$B$46+Premissas!$B$42,Premissas!$B$45*(1-Premissas!$B$15),0) -> 7500 | G13: =E13+F13 -> 28255.85 | H13: =-G13*Premissas!$B$60 -> 0 | I13: =-(C13*Premissas!$B$31+D13*Premissas!$B$13) -> -5358.1281 | J13: =-IF(A13-Premissas!$B$42<=2,Premissas!$B$49,IF(A13-Premissas!$B$42<=5,Premissas!$B$50,IF(A13-Premissas!$B$42<=8,Premissas!$B$51,Premissas!$B$52))) -> -35000 | K13: =-IF(A13=1+Premissas!$B$42,Premissas!$B$55,IF(A13=3+Premissas!$B$42,Premissas!$B$56,IF(A13=6+Premissas!$B$42,Premissas!$B$57,0))) -> 0 | L13: =G13+H13+I13+J13+K13 -> -12102.278 | M13: =M12+L13 -> -186094.09 | N13: =IF(L13>0,A13,9999) -> 9999 | O13: =IF(M13>0,A13,9999) -> 9999
A14: 10 | B14: =Premissas!$B$39+(Premissas!$B$40-Premissas!$B$39)*A14/36 -> 477.94444 | C14: =IF(A14-Premissas!$B$42<Premissas!$B$41,0,Premissas!$B$10*B14/(1+EXP(-Premissas!$B$12*(A14-Premissas!$B$42-Premissas!$B$11)))) -> 131.24258 | D14: =MAX(0,C14-C13) -> 38.68583 | E14: =C14*Premissas!$B$9*(1-Premissas!$B$15) -> 29431.148 | F14: =IF(A14>=Premissas!$B$46+Premissas!$B$42,Premissas!$B$45*(1-Premissas!$B$15),0) -> 7500 | G14: =E14+F14 -> 36931.148 | H14: =-G14*Premissas!$B$60 -> 0 | I14: =-(C14*Premissas!$B$31+D14*Premissas!$B$13) -> -7446.4796 | J14: =-IF(A14-Premissas!$B$42<=2,Premissas!$B$49,IF(A14-Premissas!$B$42<=5,Premissas!$B$50,IF(A14-Premissas!$B$42<=8,Premissas!$B$51,Premissas!$B$52))) -> -35000 | K14: =-IF(A14=1+Premissas!$B$42,Premissas!$B$55,IF(A14=3+Premissas!$B$42,Premissas!$B$56,IF(A14=6+Premissas!$B$42,Premissas!$B$57,0))) -> 0 | L14: =G14+H14+I14+J14+K14 -> -5515.3321 | M14: =M13+L14 -> -191609.42 | N14: =IF(L14>0,A14,9999) -> 9999 | O14: =IF(M14>0,A14,9999) -> 9999
A15: 11 | B15: =Premissas!$B$39+(Premissas!$B$40-Premissas!$B$39)*A15/36 -> 482.63889 | C15: =IF(A15-Premissas!$B$42<Premissas!$B$41,0,Premissas!$B$10*B15/(1+EXP(-Premissas!$B$12*(A15-Premissas!$B$42-Premissas!$B$11)))) -> 178.52462 | D15: =MAX(0,C15-C14) -> 47.28204 | E15: =C15*Premissas!$B$9*(1-Premissas!$B$15) -> 40034.145 | F15: =IF(A15>=Premissas!$B$46+Premissas!$B$42,Premissas!$B$45*(1-Premissas!$B$15),0) -> 7500 | G15: =E15+F15 -> 47534.145 | H15: =-G15*Premissas!$B$60 -> 0 | I15: =-(C15*Premissas!$B$31+D15*Premissas!$B$13) -> -9862.1358 | J15: =-IF(A15-Premissas!$B$42<=2,Premissas!$B$49,IF(A15-Premissas!$B$42<=5,Premissas!$B$50,IF(A15-Premissas!$B$42<=8,Premissas!$B$51,Premissas!$B$52))) -> -35000 | K15: =-IF(A15=1+Premissas!$B$42,Premissas!$B$55,IF(A15=3+Premissas!$B$42,Premissas!$B$56,IF(A15=6+Premissas!$B$42,Premissas!$B$57,0))) -> 0 | L15: =G15+H15+I15+J15+K15 -> 2672.0091 | M15: =M14+L15 -> -188937.41 | N15: =IF(L15>0,A15,9999) -> 11 | O15: =IF(M15>0,A15,9999) -> 9999
A16: 12 | B16: =Premissas!$B$39+(Premissas!$B$40-Premissas!$B$39)*A16/36 -> 487.33333 | C16: =IF(A16-Premissas!$B$42<Premissas!$B$41,0,Premissas!$B$10*B16/(1+EXP(-Premissas!$B$12*(A16-Premissas!$B$42-Premissas!$B$11)))) -> 231.48333 | D16: =MAX(0,C16-C15) -> 52.958718 | E16: =C16*Premissas!$B$9*(1-Premissas!$B$15) -> 51910.137 | F16: =IF(A16>=Premissas!$B$46+Premissas!$B$42,Premissas!$B$45*(1-Premissas!$B$15),0) -> 7500 | G16: =E16+F16 -> 59410.137 | H16: =-G16*Premissas!$B$60 -> 0 | I16: =-(C16*Premissas!$B$31+D16*Premissas!$B$13) -> -12370.236 | J16: =-IF(A16-Premissas!$B$42<=2,Premissas!$B$49,IF(A16-Premissas!$B$42<=5,Premissas!$B$50,IF(A16-Premissas!$B$42<=8,Premissas!$B$51,Premissas!$B$52))) -> -35000 | K16: =-IF(A16=1+Premissas!$B$42,Premissas!$B$55,IF(A16=3+Premissas!$B$42,Premissas!$B$56,IF(A16=6+Premissas!$B$42,Premissas!$B$57,0))) -> 0 | L16: =G16+H16+I16+J16+K16 -> 12039.902 | M16: =M15+L16 -> -176897.51 | N16: =IF(L16>0,A16,9999) -> 12 | O16: =IF(M16>0,A16,9999) -> 9999
A17: 13 | B17: =Premissas!$B$39+(Premissas!$B$40-Premissas!$B$39)*A17/36 -> 492.02778 | C17: =IF(A17-Premissas!$B$42<Premissas!$B$41,0,Premissas!$B$10*B17/(1+EXP(-Premissas!$B$12*(A17-Premissas!$B$42-Premissas!$B$11)))) -> 285.42889 | D17: =MAX(0,C17-C16) -> 53.945559 | E17: =C17*Premissas!$B$9*(1-Premissas!$B$15) -> 64007.429 | F17: =IF(A17>=Premissas!$B$46+Premissas!$B$42,Premissas!$B$45*(1-Premissas!$B$15),0) -> 7500 | G17: =E17+F17 -> 71507.429 | H17: =-G17*Premissas!$B$60 -> 0 | I17: =-(C17*Premissas!$B$31+D17*Premissas!$B$13) -> -14685.291 | J17: =-IF(A17-Premissas!$B$42<=2,Premissas!$B$49,IF(A17-Premissas!$B$42<=5,Premissas!$B$50,IF(A17-Premissas!$B$42<=8,Premissas!$B$51,Premissas!$B$52))) -> -35000 | K17: =-IF(A17=1+Premissas!$B$42,Premissas!$B$55,IF(A17=3+Premissas!$B$42,Premissas!$B$56,IF(A17=6+Premissas!$B$42,Premissas!$B$57,0))) -> 0 | L17: =G17+H17+I17+J17+K17 -> 21822.138 | M17: =M16+L17 -> -155075.37 | N17: =IF(L17>0,A17,9999) -> 13 | O17: =IF(M17>0,A17,9999) -> 9999
... A40: 36 | B40: =Premissas!$B$39+(Premissas!$B$40-Premissas!$B$39)*A40/36 -> 600 | C40: =IF(A40-Premissas!$B$42<Premissas!$B$41,0,Premissas!$B$10*B40/(1+EXP(-Premissas!$B$12*(A40-Premissas!$B$42-Premissas!$B$11)))) -> 569.98837 | D40: =MAX(0,C40-C39) -> 4.4661874 | E40: =C40*Premissas!$B$9*(1-Premissas!$B$15) -> 127819.89 | F40: =IF(A40>=Premissas!$B$46+Premissas!$B$42,Premissas!$B$45*(1-Premissas!$B$15),0) -> 7500 | G40: =E40+F40 -> 135319.89 | H40: =-G40*Premissas!$B$60 -> 0 | I40: =-(C40*Premissas!$B$31+D40*Premissas!$B$13) -> -24162.821 | J40: =-IF(A40-Premissas!$B$42<=2,Premissas!$B$49,IF(A40-Premissas!$B$42<=5,Premissas!$B$50,IF(A40-Premissas!$B$42<=8,Premissas!$B$51,Premissas!$B$52))) -> -35000 | K40: =-IF(A40=1+Premissas!$B$42,Premissas!$B$55,IF(A40=3+Premissas!$B$42,Premissas!$B$56,IF(A40=6+Premissas!$B$42,Premissas!$B$57,0))) -> 0 | L40: =G40+H40+I40+J40+K40 -> 76157.072 | M40: =M39+L40 -> 1302100.7 | N40: =IF(L40>0,A40,9999) -> 36 | O40: =IF(M40>0,A40,9999) -> 36
N42: Colunas auxiliares: 9999 = ainda não aconteceu.

Sheet Resumo
A1: Resumo — os números de decisão
A2: Tudo calculado a partir do Modelo mensal. Nada digitado.
A4: Indicador | B4: Valor | C4: Unidade | D4: Leitura
A6: CAIXA
A7: Capital necessário | B7: =-MIN('Modelo mensal'!M5:M40) -> 191609.42 | C7: R$ | D7: O ponto mais fundo do caixa. É o dinheiro que precisa existir antes de começar.
A8: Mês do pico de caixa negativo | B8: =INDEX('Modelo mensal'!A5:A40,MATCH(MIN('Modelo mensal'!M5:M40),'Modelo mensal'!M5:M40,0)) -> 10 | C8: mês
A9: 1º mês com resultado positivo | B9: =IF(MIN('Modelo mensal'!N5:N40)=9999,0,MIN('Modelo mensal'!N5:N40)) -> 11 | C9: mês | D9: Zero significa que não acontece em 36 meses.
A10: Mês em que o caixa volta a zero | B10: =IF(MIN('Modelo mensal'!O5:O40)=9999,0,MIN('Modelo mensal'!O5:O40)) -> 17 | C10: mês | D10: Zero significa que não volta em 36 meses.
A11: Caixa no mês 36 | B11: ='Modelo mensal'!M40 -> 1302100.7 | C11: R$
A13: RESULTADO POR ANO
A14: Ano | B14: Receita (antes de impostos) | C14: Resultado | D14: Lojas no fim do ano
A15: Ano 1 | B15: =SUM('Modelo mensal'!G5:G16) -> 195713.26 | C15: =SUM('Modelo mensal'!L5:L16) -> -176897.51 | D15: ='Modelo mensal'!C16 -> 231.48333
A16: Ano 2 | B16: =SUM('Modelo mensal'!G17:G28) -> 1275833.9 | C16: =SUM('Modelo mensal'!L17:L28) -> 619604.07 | D16: ='Modelo mensal'!C28 -> 514.16108
A17: Ano 3 | B17: =SUM('Modelo mensal'!G29:G40) -> 1556927.8 | C17: =SUM('Modelo mensal'!L29:L40) -> 859394.1 | D17: ='Modelo mensal'!C40 -> 569.98837
A19: PONTO DE EQUILÍBRIO
A20: Lojas necessárias — só os planos | B20: =IF(Premissas!$B$32=0,0,Premissas!$B$52/Premissas!$B$32) -> 136.18677 | C20: lojas | D20: Custo fixo em regime dividido pela margem de contribuição.
A21: Lojas necessárias — com o Painel da Rede | B21: =IF(Premissas!$B$32=0,0,MAX(0,(Premissas!$B$52-Premissas!$B$45)/Premissas!$B$32)) -> 97.276265 | C21: lojas
A22: % da rede de hoje — só os planos | B22: =IF(Premissas!$B$39=0,0,B20/Premissas!$B$39) -> 0.31597859 | C22: %
A23: % da rede de hoje — com o Painel | B23: =IF(Premissas!$B$39=0,0,B21/Premissas!$B$39) -> 0.22569899 | C23: %
A25: ECONOMIA UNITÁRIA
A26: Ticket médio | B26: =Premissas!$B$9 -> 299 | C26: R$/mês
A27: Custo variável por loja | B27: =Premissas!$B$31 -> 42 | C27: R$/mês
A28: Margem de contribuição | B28: =Premissas!$B$32 -> 257 | C28: R$/mês
A29: Margem de contribuição % | B29: =Premissas!$B$32/Premissas!$B$9 -> 0.85953177 | C29: %
A30: Payback do CAC | B30: =IF(Premissas!$B$32=0,0,Premissas!$B$13/Premissas!$B$32) -> 0.19455253 | C30: meses | D30: Quantos meses uma loja leva para devolver o custo de tê-la conquistado.
A31: LTV | B31: =IF(Premissas!$B$36=0,0,Premissas!$B$32/Premissas!$B$36) -> 17133.333 | C31: R$ | D31: Margem de contribuição dividida pelo churn mensal.
A32: LTV / CAC | B32: =IF(Premissas!$B$13=0,0,B31/Premissas!$B$13) -> 342.66667 | C32: x | D32: Acima de 3x já é saudável. Um número muito alto aqui não é sorte: diz que o risco deste negócio não está em conquistar cliente, está no canal.
A34: Este resumo está antes dos impostos se a alíquota em Premissas estiver zerada (item N3).

Sheet Cenários
A1: Cenários
A2: Cada cenário recalcula os 36 meses com suas próprias premissas. Os valores em branco herdam a aba Premissas.
A4: PREMISSAS DE CADA CENÁRIO
A5: Cenário | B5: Preço por loja | C5: Teto de adoção | D5: Atraso (meses) | E5: Participação franqueadora | F5: Painel da Rede | G5: Custo fixo em regime | H5: CAC por loja | I5: Mês central | J5: Custo variável | K5: Inclinação
A6: 1 · SEM homologação — venda loja a loja | B6: =Premissas!$C$9 -> 319 | C6: =Premissas!$C$10 -> 0.65 | D6: =Premissas!$B$42 -> 0 | E6: =Premissas!$C$15 -> 0 | F6: =Premissas!$B$45 -> 10000 | G6: =Premissas!$B$52 -> 35000 | H6: =Premissas!$C$13 -> 400 | I6: =Premissas!$C$11 -> 16 | J6: =Premissas!$B$66 -> 45 | K6: =Premissas!$C$12 -> 0.32
A7: 2 · COM homologação — obrigatório, participação 25% | B7: =Premissas!$D$9 -> 299 | C7: =Premissas!$D$10 -> 0.95 | D7: =Premissas!$B$42 -> 0 | E7: =Premissas!$D$15 -> 0.25 | F7: =Premissas!$B$45 -> 10000 | G7: =Premissas!$B$52 -> 35000 | H7: =Premissas!$D$13 -> 50 | I7: =Premissas!$D$11 -> 12 | J7: =Premissas!$B$67 -> 42 | K7: =Premissas!$D$12 -> 0.45
A8: Com homologação · sem participação | B8: =Premissas!$D$9 -> 299 | C8: =Premissas!$D$10 -> 0.95 | D8: =Premissas!$B$42 -> 0 | E8: 0 | F8: =Premissas!$B$45 -> 10000 | G8: =Premissas!$B$52 -> 35000 | H8: =Premissas!$D$13 -> 50 | I8: =Premissas!$D$11 -> 12 | J8: =Premissas!$B$67 -> 42 | K8: =Premissas!$D$12 -> 0.45
A9: Com homologação · participação 20% | B9: =Premissas!$D$9 -> 299 | C9: =Premissas!$D$10 -> 0.95 | D9: =Premissas!$B$42 -> 0 | E9: 0.2 | F9: =Premissas!$B$45 -> 10000 | G9: =Premissas!$B$52 -> 35000 | H9: =Premissas!$D$13 -> 50 | I9: =Premissas!$D$11 -> 12 | J9: =Premissas!$B$67 -> 42 | K9: =Premissas!$D$12 -> 0.45
A10: Com homologação · participação 30% | B10: =Premissas!$D$9 -> 299 | C10: =Premissas!$D$10 -> 0.95 | D10: =Premissas!$B$42 -> 0 | E10: 0.3 | F10: =Premissas!$B$45 -> 10000 | G10: =Premissas!$B$52 -> 35000 | H10: =Premissas!$D$13 -> 50 | I10: =Premissas!$D$11 -> 12 | J10: =Premissas!$B$67 -> 42 | K10: =Premissas!$D$12 -> 0.45
A11: Com homologação · participação 40% | B11: =Premissas!$D$9 -> 299 | C11: =Premissas!$D$10 -> 0.95 | D11: =Premissas!$B$42 -> 0 | E11: 0.4 | F11: =Premissas!$B$45 -> 10000 | G11: =Premissas!$B$52 -> 35000 | H11: =Premissas!$D$13 -> 50 | I11: =Premissas!$D$11 -> 12 | J11: =Premissas!$B$67 -> 42 | K11: =Premissas!$D$12 -> 0.45
A12: Com homologação · preço R$ 249 · particip. 25% | B12: 249 | C12: =Premissas!$D$10 -> 0.95 | D12: =Premissas!$B$42 -> 0 | E12: =Premissas!$D$15 -> 0.25 | F12: =Premissas!$B$45 -> 10000 | G12: =Premissas!$B$52 -> 35000 | H12: =Premissas!$D$13 -> 50 | I12: =Premissas!$D$11 -> 12 | J12: =Premissas!$B$67 -> 42 | K12: =Premissas!$D$12 -> 0.45
A13: Com homologação · atraso de 6 meses | B13: =Premissas!$D$9 -> 299 | C13: =Premissas!$D$10 -> 0.95 | D13: 6 | E13: =Premissas!$D$15 -> 0.25 | F13: =Premissas!$B$45 -> 10000 | G13: =Premissas!$B$52 -> 35000 | H13: =Premissas!$D$13 -> 50 | I13: =Premissas!$D$11 -> 12 | J13: =Premissas!$B$67 -> 42 | K13: =Premissas!$D$12 -> 0.45
A14: Com homologação · enxuta, sem pró-labore | B14: =Premissas!$D$9 -> 299 | C14: =Premissas!$D$10 -> 0.95 | D14: =Premissas!$B$42 -> 0 | E14: =Premissas!$D$15 -> 0.25 | F14: =Premissas!$B$45 -> 10000 | G14: 25000 | H14: =Premissas!$D$13 -> 50 | I14: =Premissas!$D$11 -> 12 | J14: =Premissas!$B$67 -> 42 | K14: =Premissas!$D$12 -> 0.45
A15: Sem homologação · adoção metade da rede | B15: =Premissas!$C$9 -> 319 | C15: 0.325 | D15: =Premissas!$B$42 -> 0 | E15: =Premissas!$C$15 -> 0 | F15: =Premissas!$B$45 -> 10000 | G15: =Premissas!$B$52 -> 35000 | H15: =Premissas!$C$13 -> 400 | I15: =Premissas!$C$11 -> 16 | J15: =Premissas!$B$66 -> 45 | K15: =Premissas!$C$12 -> 0.32
A16: Sem homologação · participação de 35% | B16: =Premissas!$C$9 -> 319 | C16: =Premissas!$C$10 -> 0.65 | D16: =Premissas!$B$42 -> 0 | E16: 0.35 | F16: =Premissas!$B$45 -> 10000 | G16: =Premissas!$B$52 -> 35000 | H16: =Premissas!$C$13 -> 400 | I16: =Premissas!$C$11 -> 16 | J16: =Premissas!$B$66 -> 45 | K16: =Premissas!$C$12 -> 0.32
A17: Sem homologação · pior caso combinado | B17: =Premissas!$C$9 -> 319 | C17: 0.325 | D17: 6 | E17: 0.35 | F17: =Premissas!$B$45 -> 10000 | G17: =Premissas!$B$52 -> 35000 | H17: =Premissas!$C$13 -> 400 | I17: =Premissas!$C$11 -> 16 | J17: =Premissas!$B$66 -> 45 | K17: =Premissas!$C$12 -> 0.32
A19: RESULTADO DE CADA CENÁRIO
A20: Cenário | B20: 1º mês positivo | C20: Caixa volta a zero | D20: Capital necessário | E20: Receita ano 3 | F20: Resultado ano 3 | G20: Lojas no mês 36
A21: 1 · SEM homologação — venda loja a loja | B21: =IF(MIN(H42:H77)=9999,0,MIN(H42:H77)) -> 15 | C21: =IF(MIN(I42:I77)=9999,0,MIN(I42:I77)) -> 23 | D21: =-MIN(G42:G77) -> 267088.27 | E21: =SUM(D66:D77) -> 1526137.2 | F21: =SUM(F66:F77) -> 883248.22 | G21: =C77 -> 389.35307
A22: 2 · COM homologação — obrigatório, participação 25% | B22: =IF(MIN(O42:O77)=9999,0,MIN(O42:O77)) -> 11 | C22: =IF(MIN(P42:P77)=9999,0,MIN(P42:P77)) -> 17 | D22: =-MIN(N42:N77) -> 191609.42 | E22: =SUM(K66:K77) -> 1556927.8 | F22: =SUM(M66:M77) -> 859394.1 | G22: =J77 -> 569.98837
A23: Com homologação · sem participação | B23: =IF(MIN(V42:V77)=9999,0,MIN(V42:V77)) -> 10 | C23: =IF(MIN(W42:W77)=9999,0,MIN(W42:W77)) -> 15 | D23: =-MIN(U42:U77) -> 168814.81 | E23: =SUM(R66:R77) -> 2075903.7 | F23: =SUM(T66:T77) -> 1378370 | G23: =Q77 -> 569.98837
A24: Com homologação · participação 20% | B24: =IF(MIN(AC42:AC77)=9999,0,MIN(AC42:AC77)) -> 11 | C24: =IF(MIN(AD42:AD77)=9999,0,MIN(AD42:AD77)) -> 17 | D24: =-MIN(AB42:AB77) -> 185691.49 | E24: =SUM(Y66:Y77) -> 1660723 | F24: =SUM(AA66:AA77) -> 963189.29 | G24: =X77 -> 569.98837
A25: Com homologação · participação 30% | B25: =IF(MIN(AJ42:AJ77)=9999,0,MIN(AJ42:AJ77)) -> 12 | C25: =IF(MIN(AK42:AK77)=9999,0,MIN(AK42:AK77)) -> 18 | D25: =-MIN(AI42:AI77) -> 198024.28 | E25: =SUM(AF66:AF77) -> 1453132.6 | F25: =SUM(AH66:AH77) -> 755598.92 | G25: =AE77 -> 569.98837
A26: Com homologação · participação 40% | B26: =IF(MIN(AQ42:AQ77)=9999,0,MIN(AQ42:AQ77)) -> 12 | C26: =IF(MIN(AR42:AR77)=9999,0,MIN(AR42:AR77)) -> 21 | D26: =-MIN(AP42:AP77) -> 216198.03 | E26: =SUM(AM66:AM77) -> 1245542.2 | F26: =SUM(AO66:AO77) -> 548008.54 | G26: =AL77 -> 569.98837
A27: Com homologação · preço R$ 249 · particip. 25% | B27: =IF(MIN(AX42:AX77)=9999,0,MIN(AX42:AX77)) -> 12 | C27: =IF(MIN(AY42:AY77)=9999,0,MIN(AY42:AY77)) -> 20 | D27: =-MIN(AW42:AW77) -> 207968.03 | E27: =SUM(AT66:AT77) -> 1311622.1 | F27: =SUM(AV66:AV77) -> 614088.45 | G27: =AS77 -> 569.98837
A28: Com homologação · atraso de 6 meses | B28: =IF(MIN(BE42:BE77)=9999,0,MIN(BE42:BE77)) -> 17 | C28: =IF(MIN(BF42:BF77)=9999,0,MIN(BF42:BF77)) -> 23 | D28: =-MIN(BD42:BD77) -> 218425.8 | E28: =SUM(BA66:BA77) -> 1544262.5 | F28: =SUM(BC66:BC77) -> 847598.82 | G28: =AZ77 -> 569.82704
A29: Com homologação · enxuta, sem pró-labore | B29: =IF(MIN(BL42:BL77)=9999,0,MIN(BL42:BL77)) -> 10 | C29: =IF(MIN(BM42:BM77)=9999,0,MIN(BM42:BM77)) -> 16 | D29: =-MIN(BK42:BK77) -> 176094.09 | E29: =SUM(BH66:BH77) -> 1556927.8 | F29: =SUM(BJ66:BJ77) -> 979394.1 | G29: =BG77 -> 569.98837
A30: Sem homologação · adoção metade da rede | B30: =IF(MIN(BS42:BS77)=9999,0,MIN(BS42:BS77)) -> 19 | C30: =IF(MIN(BT42:BT77)=9999,0,MIN(BT42:BT77)) -> 35 | D30: =-MIN(BR42:BR77) -> 327401.78 | E30: =SUM(BO66:BO77) -> 823068.6 | F30: =SUM(BQ66:BQ77) -> 291624.11 | G30: =BN77 -> 194.67653
A31: Sem homologação · participação de 35% | B31: =IF(MIN(BZ42:BZ77)=9999,0,MIN(BZ42:BZ77)) -> 19 | C31: =IF(MIN(CA42:CA77)=9999,0,MIN(CA42:CA77)) -> 35 | D31: =-MIN(BY42:BY77) -> 377326.21 | E31: =SUM(BV66:BV77) -> 991989.18 | F31: =SUM(BX66:BX77) -> 349100.21 | G31: =BU77 -> 389.35307
A32: Sem homologação · pior caso combinado | B32: =IF(MIN(CG42:CG77)=9999,0,MIN(CG42:CG77)) -> 33 | C32: =IF(MIN(CH42:CH77)=9999,0,MIN(CH42:CH77)) -> 0 | D32: =-MIN(CF42:CF77) -> 500221.33 | E32: =SUM(CC66:CC77) -> 499736.42 | F32: =SUM(CE66:CE77) -> -42640.764 | G32: =CB77 -> 192.81475
A34: Zero em "1º mês positivo" ou "caixa volta a zero" significa que não acontece dentro dos 36 meses. A receita já está líquida de participação e de impostos.
A36: AS DUAS LINHAS EM DESTAQUE SÃO A DECISÃO. Sem homologação: você vende loja a loja, a R$ 319, e chega a 65% da rede. Com homologação: a franqueadora torna o produto obrigatório como já fez com Trinks e Sults, cobra das lojas e repassa consolidado — adesão de 95%, preço único de R$ 299, CAC quase nulo, e 25% da receita fica com ela. Todas as outras linhas são sensibilidades em torno dessas duas.
A39: GRADE DE CÁLCULO — 36 meses por cenário (pode ocultar estas linhas)
A40: Mês | C40: 1 · SEM homologação — venda loja a loja | D40: receita | E40: custos | F40: result. | G40: caixa | H40: aux+ | I40: auxcx | J40: 2 · COM homologação — obrigatório, participação 25% | K40: receita | L40: custos | M40: result. | N40: caixa | O40: aux+ | P40: auxcx | Q40: Com homologação · sem participação | R40: receita | S40: custos | T40: result. | U40: caixa | V40: aux+ | W40: auxcx | X40: Com homologação · participação 20% | Y40: receita | Z40: custos | AA40: result. | AB40: caixa | AC40: aux+ | AD40: auxcx | AE40: Com homologação · participação 30% | AF40: receita | AG40: custos | AH40: result. | AI40: caixa | AJ40: aux+ | AK40: auxcx | AL40: Com homologação · participação 40% | AM40: receita | AN40: custos | AO40: result. | AP40: caixa | AQ40: aux+ | AR40: auxcx | AS40: Com homologação · preço R$ 249 · particip. 25% | AT40: receita | AU40: custos | AV40: result. | AW40: caixa | AX40: aux+ | AY40: auxcx | AZ40: Com homologação · atraso de 6 meses | BA40: receita | BB40: custos | BC40: result. | BD40: caixa | BE40: aux+ | BF40: auxcx | BG40: Com homologação · enxuta, sem pró-labore | BH40: receita | BI40: custos | BJ40: result. | BK40: caixa | BL40: aux+ | BM40: auxcx | BN40: Sem homologação · adoção metade da rede | BO40: receita | BP40: custos | BQ40: result. | BR40: caixa | BS40: aux+ | BT40: auxcx | BU40: Sem homologação · participação de 35% | BV40: receita | BW40: custos | BX40: result. | BY40: caixa | BZ40: aux+ | CA40: auxcx | CB40: Sem homologação · pior caso combinado | CC40: receita | CD40: custos | CE40: result. | CF40: caixa | CG40: aux+ | CH40: auxcx
A42: 1 | C42: =IF($A42-$D$6<Premissas!$B$41,0,$C$6*(Premissas!$B$39+(Premissas!$B$40-Premissas!$B$39)*$A42/36)/(1+EXP(-$K$6*($A42-$D$6-$I$6)))) -> 0 | D42: =(C42*$B$6+IF($A42>=Premissas!$B$46+$D$6,$F$6,0))*(1-$E$6)*(1-Premissas!$B$60) -> 0 | E42: =-(C42*$J$6+C42*$H$6+IF($A42-$D$6<=2,Premissas!$B$49,IF($A42-$D$6<=5,Premissas!$B$50,IF($A42-$D$6<=8,Premissas!$B$51,$G$6)))+IF($A42=1+$D$6,Premissas!$B$55,IF($A42=3+$D$6,Premissas!$B$56,IF($A42=6+$D$6,Premissas!$B$57,0)))) -> -13000 | F42: =D42+E42 -> -13000 | G42: =F42 -> -13000 | H42: =IF(F42>0,$A42,9999) -> 9999 | I42: =IF(G42>0,$A42,9999) -> 9999 | J42: =IF($A42-$D$7<Premissas!$B$41,0,$C$7*(Premissas!$B$39+(Premissas!$B$40-Premissas!$B$39)*$A42/36)/(1+EXP(-$K$7*($A42-$D$7-$I$7)))) -> 0 | K42: =(J42*$B$7+IF($A42>=Premissas!$B$46+$D$7,$F$7,0))*(1-$E$7)*(1-Premissas!$B$60) -> 0 | L42: =-(J42*$J$7+J42*$H$7+IF($A42-$D$7<=2,Premissas!$B$49,IF($A42-$D$7<=5,Premissas!$B$50,IF($A42-$D$7<=8,Premissas!$B$51,$G$7)))+IF($A42=1+$D$7,Premissas!$B$55,IF($A42=3+$D$7,Premissas!$B$56,IF($A42=6+$D$7,Premissas!$B$57,0)))) -> -13000 | M42: =K42+L42 -> -13000 | N42: =M42 -> -13000 | O42: =IF(M42>0,$A42,9999) -> 9999 | P42: =IF(N42>0,$A42,9999) -> 9999 | Q42: =IF($A42-$D$8<Premissas!$B$41,0,$C$8*(Premissas!$B$39+(Premissas!$B$40-Premissas!$B$39)*$A42/36)/(1+EXP(-$K$8*($A42-$D$8-$I$8)))) -> 0 | R42: =(Q42*$B$8+IF($A42>=Premissas!$B$46+$D$8,$F$8,0))*(1-$E$8)*(1-Premissas!$B$60) -> 0 | S42: =-(Q42*$J$8+Q42*$H$8+IF($A42-$D$8<=2,Premissas!$B$49,IF($A42-$D$8<=5,Premissas!$B$50,IF($A42-$D$8<=8,Premissas!$B$51,$G$8)))+IF($A42=1+$D$8,Premissas!$B$55,IF($A42=3+$D$8,Premissas!$B$56,IF($A42=6+$D$8,Premissas!$B$57,0)))) -> -13000 | T42: =R42+S42 -> -13000 | U42: =T42 -> -13000 | V42: =IF(T42>0,$A42,9999) -> 9999 | W42: =IF(U42>0,$A42,9999) -> 9999 | X42: =IF($A42-$D$9<Premissas!$B$41,0,$C$9*(Premissas!$B$39+(Premissas!$B$40-Premissas!$B$39)*$A42/36)/(1+EXP(-$K$9*($A42-$D$9-$I$9)))) -> 0 | Y42: =(X42*$B$9+IF($A42>=Premissas!$B$46+$D$9,$F$9,0))*(1-$E$9)*(1-Premissas!$B$60) -> 0 | Z42: =-(X42*$J$9+X42*$H$9+IF($A42-$D$9<=2,Premissas!$B$49,IF($A42-$D$9<=5,Premissas!$B$50,IF($A42-$D$9<=8,Premissas!$B$51,$G$9)))+IF($A42=1+$D$9,Premissas!$B$55,IF($A42=3+$D$9,Premissas!$B$56,IF($A42=6+$D$9,Premissas!$B$57,0)))) -> -13000 | AA42: =Y42+Z42 -> -13000 | AB42: =AA42 -> -13000 | AC42: =IF(AA42>0,$A42,9999) -> 9999 | AD42: =IF(AB42>0,$A42,9999) -> 9999 | AE42: =IF($A42-$D$10<Premissas!$B$41,0,$C$10*(Premissas!$B$39+(Premissas!$B$40-Premissas!$B$39)*$A42/36)/(1+EXP(-$K$10*($A42-$D$10-$I$10)))) -> 0 | AF42: =(AE42*$B$10+IF($A42>=Premissas!$B$46+$D$10,$F$10,0))*(1-$E$10)*(1-Premissas!$B$60) -> 0 | AG42: =-(AE42*$J$10+AE42*$H$10+IF($A42-$D$10<=2,Premissas!$B$49,IF($A42-$D$10<=5,Premissas!$B$50,IF($A42-$D$10<=8,Premissas!$B$51,$G$10)))+IF($A42=1+$D$10,Premissas!$B$55,IF($A42=3+$D$10,Premissas!$B$56,IF($A42=6+$D$10,Premissas!$B$57,0)))) -> -13000 | AH42: =AF42+AG42 -> -13000 | AI42: =AH42 -> -13000 | AJ42: =IF(AH42>0,$A42,9999) -> 9999 | AK42: =IF(AI42>0,$A42,9999) -> 9999 | AL42: =IF($A42-$D$11<Premissas!$B$41,0,$C$11*(Premissas!$B$39+(Premissas!$B$40-Premissas!$B$39)*$A42/36)/(1+EXP(-$K$11*($A42-$D$11-$I$11)))) -> 0 | AM42: =(AL42*$B$11+IF($A42>=Premissas!$B$46+$D$11,$F$11,0))*(1-$E$11)*(1-Premissas!$B$60) -> 0 | AN42: =-(AL42*$J$11+AL42*$H$11+IF($A42-$D$11<=2,Premissas!$B$49,IF($A42-$D$11<=5,Premissas!$B$50,IF($A42-$D$11<=8,Premissas!$B$51,$G$11)))+IF($A42=1+$D$11,Premissas!$B$55,IF($A42=3+$D$11,Premissas!$B$56,IF($A42=6+$D$11,Premissas!$B$57,0)))) -> -13000 | AO42: =AM42+AN42 -> -13000 | AP42: =AO42 -> -13000 | AQ42: =IF(AO42>0,$A42,9999) -> 9999 | AR42: =IF(AP42>0,$A42,9999) -> 9999 | AS42: =IF($A42-$D$12<Premissas!$B$41,0,$C$12*(Premissas!$B$39+(Premissas!$B$40-Premissas!$B$39)*$A42/36)/(1+EXP(-$K$12*($A42-$D$12-$I$12)))) -> 0 | AT42: =(AS42*$B$12+IF($A42>=Premissas!$B$46+$D$12,$F$12,0))*(1-$E$12)*(1-Premissas!$B$60) -> 0 | AU42: =-(AS42*$J$12+AS42*$H$12+IF($A42-$D$12<=2,Premissas!$B$49,IF($A42-$D$12<=5,Premissas!$B$50,IF($A42-$D$12<=8,Premissas!$B$51,$G$12)))+IF($A42=1+$D$12,Premissas!$B$55,IF($A42=3+$D$12,Premissas!$B$56,IF($A42=6+$D$12,Premissas!$B$57,0)))) -> -13000 | AV42: =AT42+AU42 -> -13000 | AW42: =AV42 -> -13000 | AX42: =IF(AV42>0,$A42,9999) -> 9999 | AY42: =IF(AW42>0,$A42,9999) -> 9999 | AZ42: =IF($A42-$D$13<Premissas!$B$41,0,$C$13*(Premissas!$B$39+(Premissas!$B$40-Premissas!$B$39)*$A42/36)/(1+EXP(-$K$13*($A42-$D$13-$I$13)))) -> 0 | BA42: =(AZ42*$B$13+IF($A42>=Premissas!$B$46+$D$13,$F$13,0))*(1-$E$13)*(1-Premissas!$B$60) -> 0 | BB42: =-(AZ42*$J$13+AZ42*$H$13+IF($A42-$D$13<=2,Premissas!$B$49,IF($A42-$D$13<=5,Premissas!$B$50,IF($A42-$D$13<=8,Premissas!$B$51,$G$13)))+IF($A42=1+$D$13,Premissas!$B$55,IF($A42=3+$D$13,Premissas!$B$56,IF($A42=6+$D$13,Premissas!$B$57,0)))) -> -5000 | BC42: =BA42+BB42 -> -5000 | BD42: =BC42 -> -5000 | BE42: =IF(BC42>0,$A42,9999) -> 9999 | BF42: =IF(BD42>0,$A42,9999) -> 9999 | BG42: =IF($A42-$D$14<Premissas!$B$41,0,$C$14*(Premissas!$B$39+(Premissas!$B$40-Premissas!$B$39)*$A42/36)/(1+EXP(-$K$14*($A42-$D$14-$I$14)))) -> 0 | BH42: =(BG42*$B$14+IF($A42>=Premissas!$B$46+$D$14,$F$14,0))*(1-$E$14)*(1-Premissas!$B$60) -> 0 | BI42: =-(BG42*$J$14+BG42*$H$14+IF($A42-$D$14<=2,Premissas!$B$49,IF($A42-$D$14<=5,Premissas!$B$50,IF($A42-$D$14<=8,Premissas!$B$51,$G$14)))+IF($A42=1+$D$14,Premissas!$B$55,IF($A42=3+$D$14,Premissas!$B$56,IF($A42=6+$D$14,Premissas!$B$57,0)))) -> -13000 | BJ42: =BH42+BI42 -> -13000 | BK42: =BJ42 -> -13000 | BL42: =IF(BJ42>0,$A42,9999) -> 9999 | BM42: =IF(BK42>0,$A42,9999) -> 9999 | BN42: =IF($A42-$D$15<Premissas!$B$41,0,$C$15*(Premissas!$B$39+(Premissas!$B$40-Premissas!$B$39)*$A42/36)/(1+EXP(-$K$15*($A42-$D$15-$I$15)))) -> 0 | BO42: =(BN42*$B$15+IF($A42>=Premissas!$B$46+$D$15,$F$15,0))*(1-$E$15)*(1-Premissas!$B$60) -> 0 | BP42: =-(BN42*$J$15+BN42*$H$15+IF($A42-$D$15<=2,Premissas!$B$49,IF($A42-$D$15<=5,Premissas!$B$50,IF($A42-$D$15<=8,Premissas!$B$51,$G$15)))+IF($A42=1+$D$15,Premissas!$B$55,IF($A42=3+$D$15,Premissas!$B$56,IF($A42=6+$D$15,Premissas!$B$57,0)))) -> -13000 | BQ42: =BO42+BP42 -> -13000 | BR42: =BQ42 -> -13000 | BS42: =IF(BQ42>0,$A42,9999) -> 9999 | BT42: =IF(BR42>0,$A42,9999) -> 9999 | BU42: =IF($A42-$D$16<Premissas!$B$41,0,$C$16*(Premissas!$B$39+(Premissas!$B$40-Premissas!$B$39)*$A42/36)/(1+EXP(-$K$16*($A42-$D$16-$I$16)))) -> 0 | BV42: =(BU42*$B$16+IF($A42>=Premissas!$B$46+$D$16,$F$16,0))*(1-$E$16)*(1-Premissas!$B$60) -> 0 | BW42: =-(BU42*$J$16+BU42*$H$16+IF($A42-$D$16<=2,Premissas!$B$49,IF($A42-$D$16<=5,Premissas!$B$50,IF($A42-$D$16<=8,Premissas!$B$51,$G$16)))+IF($A42=1+$D$16,Premissas!$B$55,IF($A42=3+$D$16,Premissas!$B$56,IF($A42=6+$D$16,Premissas!$B$57,0)))) -> -13000 | BX42: =BV42+BW42 -> -13000 | BY42: =BX42 -> -13000 | BZ42: =IF(BX42>0,$A42,9999) -> 9999 | CA42: =IF(BY42>0,$A42,9999) -> 9999 | CB42: =IF($A42-$D$17<Premissas!$B$41,0,$C$17*(Premissas!$B$39+(Premissas!$B$40-Premissas!$B$39)*$A42/36)/(1+EXP(-$K$17*($A42-$D$17-$I$17)))) -> 0 | CC42: =(CB42*$B$17+IF($A42>=Premissas!$B$46+$D$17,$F$17,0))*(1-$E$17)*(1-Premissas!$B$60) -> 0 | CD42: =-(CB42*$J$17+CB42*$H$17+IF($A42-$D$17<=2,Premissas!$B$49,IF($A42-$D$17<=5,Premissas!$B$50,IF($A42-$D$17<=8,Premissas!$B$51,$G$17)))+IF($A42=1+$D$17,Premissas!$B$55,IF($A42=3+$D$17,Premissas!$B$56,IF($A42=6+$D$17,Premissas!$B$57,0)))) -> -5000 | CE42: =CC42+CD42 -> -5000 | CF42: =CE42 -> -5000 | CG42: =IF(CE42>0,$A42,9999) -> 9999 | CH42: =IF(CF42>0,$A42,9999) -> 9999
A43: 2 | C43: =IF($A43-$D$6<Premissas!$B$41,0,$C$6*(Premissas!$B$39+(Premissas!$B$40-Premissas!$B$39)*$A43/36)/(1+EXP(-$K$6*($A43-$D$6-$I$6)))) -> 0 | D43: =(C43*$B$6+IF($A43>=Premissas!$B$46+$D$6,$F$6,0))*(1-$E$6)*(1-Premissas!$B$60) -> 0 | E43: =-(C43*$J$6+MAX(0,C43-C42)*$H$6+IF($A43-$D$6<=2,Premissas!$B$49,IF($A43-$D$6<=5,Premissas!$B$50,IF($A43-$D$6<=8,Premissas!$B$51,$G$6)))+IF($A43=1+$D$6,Premissas!$B$55,IF($A43=3+$D$6,Premissas!$B$56,IF($A43=6+$D$6,Premissas!$B$57,0)))) -> -5000 | F43: =D43+E43 -> -5000 | G43: =G42+F43 -> -18000 | H43: =IF(F43>0,$A43,9999) -> 9999 | I43: =IF(G43>0,$A43,9999) -> 9999 | J43: =IF($A43-$D$7<Premissas!$B$41,0,$C$7*(Premissas!$B$39+(Premissas!$B$40-Premissas!$B$39)*$A43/36)/(1+EXP(-$K$7*($A43-$D$7-$I$7)))) -> 0 | K43: =(J43*$B$7+IF($A43>=Premissas!$B$46+$D$7,$F$7,0))*(1-$E$7)*(1-Premissas!$B$60) -> 0 | L43: =-(J43*$J$7+MAX(0,J43-J42)*$H$7+IF($A43-$D$7<=2,Premissas!$B$49,IF($A43-$D$7<=5,Premissas!$B$50,IF($A43-$D$7<=8,Premissas!$B$51,$G$7)))+IF($A43=1+$D$7,Premissas!$B$55,IF($A43=3+$D$7,Premissas!$B$56,IF($A43=6+$D$7,Premissas!$B$57,0)))) -> -5000 | M43: =K43+L43 -> -5000 | N43: =N42+M43 -> -18000 | O43: =IF(M43>0,$A43,9999) -> 9999 | P43: =IF(N43>0,$A43,9999) -> 9999 | Q43: =IF($A43-$D$8<Premissas!$B$41,0,$C$8*(Premissas!$B$39+(Premissas!$B$40-Premissas!$B$39)*$A43/36)/(1+EXP(-$K$8*($A43-$D$8-$I$8)))) -> 0 | R43: =(Q43*$B$8+IF($A43>=Premissas!$B$46+$D$8,$F$8,0))*(1-$E$8)*(1-Premissas!$B$60) -> 0 | S43: =-(Q43*$J$8+MAX(0,Q43-Q42)*$H$8+IF($A43-$D$8<=2,Premissas!$B$49,IF($A43-$D$8<=5,Premissas!$B$50,IF($A43-$D$8<=8,Premissas!$B$51,$G$8)))+IF($A43=1+$D$8,Premissas!$B$55,IF($A43=3+$D$8,Premissas!$B$56,IF($A43=6+$D$8,Premissas!$B$57,0)))) -> -5000 | T43: =R43+S43 -> -5000 | U43: =U42+T43 -> -18000 | V43: =IF(T43>0,$A43,9999) -> 9999 | W43: =IF(U43>0,$A43,9999) -> 9999 | X43: =IF($A43-$D$9<Premissas!$B$41,0,$C$9*(Premissas!$B$39+(Premissas!$B$40-Premissas!$B$39)*$A43/36)/(1+EXP(-$K$9*($A43-$D$9-$I$9)))) -> 0 | Y43: =(X43*$B$9+IF($A43>=Premissas!$B$46+$D$9,$F$9,0))*(1-$E$9)*(1-Premissas!$B$60) -> 0 | Z43: =-(X43*$J$9+MAX(0,X43-X42)*$H$9+IF($A43-$D$9<=2,Premissas!$B$49,IF($A43-$D$9<=5,Premissas!$B$50,IF($A43-$D$9<=8,Premissas!$B$51,$G$9)))+IF($A43=1+$D$9,Premissas!$B$55,IF($A43=3+$D$9,Premissas!$B$56,IF($A43=6+$D$9,Premissas!$B$57,0)))) -> -5000 | AA43: =Y43+Z43 -> -5000 | AB43: =AB42+AA43 -> -18000 | AC43: =IF(AA43>0,$A43,9999) -> 9999 | AD43: =IF(AB43>0,$A43,9999) -> 9999 | AE43: =IF($A43-$D$10<Premissas!$B$41,0,$C$10*(Premissas!$B$39+(Premissas!$B$40-Premissas!$B$39)*$A43/36)/(1+EXP(-$K$10*($A43-$D$10-$I$10)))) -> 0 | AF43: =(AE43*$B$10+IF($A43>=Premissas!$B$46+$D$10,$F$10,0))*(1-$E$10)*(1-Premissas!$B$60) -> 0 | AG43: =-(AE43*$J$10+MAX(0,AE43-AE42)*$H$10+IF($A43-$D$10<=2,Premissas!$B$49,IF($A43-$D$10<=5,Premissas!$B$50,IF($A43-$D$10<=8,Premissas!$B$51,$G$10)))+IF($A43=1+$D$10,Premissas!$B$55,IF($A43=3+$D$10,Premissas!$B$56,IF($A43=6+$D$10,Premissas!$B$57,0)))) -> -5000 | AH43: =AF43+AG43 -> -5000 | AI43: =AI42+AH43 -> -18000 | AJ43: =IF(AH43>0,$A43,9999) -> 9999 | AK43: =IF(AI43>0,$A43,9999) -> 9999 | AL43: =IF($A43-$D$11<Premissas!$B$41,0,$C$11*(Premissas!$B$39+(Premissas!$B$40-Premissas!$B$39)*$A43/36)/(1+EXP(-$K$11*($A43-$D$11-$I$11)))) -> 0 | AM43: =(AL43*$B$11+IF($A43>=Premissas!$B$46+$D$11,$F$11,0))*(1-$E$11)*(1-Premissas!$B$60) -> 0 | AN43: =-(AL43*$J$11+MAX(0,AL43-AL42)*$H$11+IF($A43-$D$11<=2,Premissas!$B$49,IF($A43-$D$11<=5,Premissas!$B$50,IF($A43-$D$11<=8,Premissas!$B$51,$G$11)))+IF($A43=1+$D$11,Premissas!$B$55,IF($A43=3+$D$11,Premissas!$B$56,IF($A43=6+$D$11,Premissas!$B$57,0)))) -> -5000 | AO43: =AM43+AN43 -> -5000 | AP43: =AP42+AO43 -> -18000 | AQ43: =IF(AO43>0,$A43,9999) -> 9999 | AR43: =IF(AP43>0,$A43,9999) -> 9999 | AS43: =IF($A43-$D$12<Premissas!$B$41,0,$C$12*(Premissas!$B$39+(Premissas!$B$40-Premissas!$B$39)*$A43/36)/(1+EXP(-$K$12*($A43-$D$12-$I$12)))) -> 0 | AT43: =(AS43*$B$12+IF($A43>=Premissas!$B$46+$D$12,$F$12,0))*(1-$E$12)*(1-Premissas!$B$60) -> 0 | AU43: =-(AS43*$J$12+MAX(0,AS43-AS42)*$H$12+IF($A43-$D$12<=2,Premissas!$B$49,IF($A43-$D$12<=5,Premissas!$B$50,IF($A43-$D$12<=8,Premissas!$B$51,$G$12)))+IF($A43=1+$D$12,Premissas!$B$55,IF($A43=3+$D$12,Premissas!$B$56,IF($A43=6+$D$12,Premissas!$B$57,0)))) -> -5000 | AV43: =AT43+AU43 -> -5000 | AW43: =AW42+AV43 -> -18000 | AX43: =IF(AV43>0,$A43,9999) -> 9999 | AY43: =IF(AW43>0,$A43,9999) -> 9999 | AZ43: =IF($A43-$D$13<Premissas!$B$41,0,$C$13*(Premissas!$B$39+(Premissas!$B$40-Premissas!$B$39)*$A43/36)/(1+EXP(-$K$13*($A43-$D$13-$I$13)))) -> 0 | BA43: =(AZ43*$B$13+IF($A43>=Premissas!$B$46+$D$13,$F$13,0))*(1-$E$13)*(1-Premissas!$B$60) -> 0 | BB43: =-(AZ43*$J$13+MAX(0,AZ43-AZ42)*$H$13+IF($A43-$D$13<=2,Premissas!$B$49,IF($A43-$D$13<=5,Premissas!$B$50,IF($A43-$D$13<=8,Premissas!$B$51,$G$13)))+IF($A43=1+$D$13,Premissas!$B$55,IF($A43=3+$D$13,Premissas!$B$56,IF($A43=6+$D$13,Premissas!$B$57,0)))) -> -5000 | BC43: =BA43+BB43 -> -5000 | BD43: =BD42+BC43 -> -10000 | BE43: =IF(BC43>0,$A43,9999) -> 9999 | BF43: =IF(BD43>0,$A43,9999) -> 9999 | BG43: =IF($A43-$D$14<Premissas!$B$41,0,$C$14*(Premissas!$B$39+(Premissas!$B$40-Premissas!$B$39)*$A43/36)/(1+EXP(-$K$14*($A43-$D$14-$I$14)))) -> 0 | BH43: =(BG43*$B$14+IF($A43>=Premissas!$B$46+$D$14,$F$14,0))*(1-$E$14)*(1-Premissas!$B$60) -> 0 | BI43: =-(BG43*$J$14+MAX(0,BG43-BG42)*$H$14+IF($A43-$D$14<=2,Premissas!$B$49,IF($A43-$D$14<=5,Premissas!$B$50,IF($A43-$D$14<=8,Premissas!$B$51,$G$14)))+IF($A43=1+$D$14,Premissas!$B$55,IF($A43=3+$D$14,Premissas!$B$56,IF($A43=6+$D$14,Premissas!$B$57,0)))) -> -5000 | BJ43: =BH43+BI43 -> -5000 | BK43: =BK42+BJ43 -> -18000 | BL43: =IF(BJ43>0,$A43,9999) -> 9999 | BM43: =IF(BK43>0,$A43,9999) -> 9999 | BN43: =IF($A43-$D$15<Premissas!$B$41,0,$C$15*(Premissas!$B$39+(Premissas!$B$40-Premissas!$B$39)*$A43/36)/(1+EXP(-$K$15*($A43-$D$15-$I$15)))) -> 0 | BO43: =(BN43*$B$15+IF($A43>=Premissas!$B$46+$D$15,$F$15,0))*(1-$E$15)*(1-Premissas!$B$60) -> 0 | BP43: =-(BN43*$J$15+MAX(0,BN43-BN42)*$H$15+IF($A43-$D$15<=2,Premissas!$B$49,IF($A43-$D$15<=5,Premissas!$B$50,IF($A43-$D$15<=8,Premissas!$B$51,$G$15)))+IF($A43=1+$D$15,Premissas!$B$55,IF($A43=3+$D$15,Premissas!$B$56,IF($A43=6+$D$15,Premissas!$B$57,0)))) -> -5000 | BQ43: =BO43+BP43 -> -5000 | BR43: =BR42+BQ43 -> -18000 | BS43: =IF(BQ43>0,$A43,9999) -> 9999 | BT43: =IF(BR43>0,$A43,9999) -> 9999 | BU43: =IF($A43-$D$16<Premissas!$B$41,0,$C$16*(Premissas!$B$39+(Premissas!$B$40-Premissas!$B$39)*$A43/36)/(1+EXP(-$K$16*($A43-$D$16-$I$16)))) -> 0 | BV43: =(BU43*$B$16+IF($A43>=Premissas!$B$46+$D$16,$F$16,0))*(1-$E$16)*(1-Premissas!$B$60) -> 0 | BW43: =-(BU43*$J$16+MAX(0,BU43-BU42)*$H$16+IF($A43-$D$16<=2,Premissas!$B$49,IF($A43-$D$16<=5,Premissas!$B$50,IF($A43-$D$16<=8,Premissas!$B$51,$G$16)))+IF($A43=1+$D$16,Premissas!$B$55,IF($A43=3+$D$16,Premissas!$B$56,IF($A43=6+$D$16,Premissas!$B$57,0)))) -> -5000 | BX43: =BV43+BW43 -> -5000 | BY43: =BY42+BX43 -> -18000 | BZ43: =IF(BX43>0,$A43,9999) -> 9999 | CA43: =IF(BY43>0,$A43,9999) -> 9999 | CB43: =IF($A43-$D$17<Premissas!$B$41,0,$C$17*(Premissas!$B$39+(Premissas!$B$40-Premissas!$B$39)*$A43/36)/(1+EXP(-$K$17*($A43-$D$17-$I$17)))) -> 0 | CC43: =(CB43*$B$17+IF($A43>=Premissas!$B$46+$D$17,$F$17,0))*(1-$E$17)*(1-Premissas!$B$60) -> 0 | CD43: =-(CB43*$J$17+MAX(0,CB43-CB42)*$H$17+IF($A43-$D$17<=2,Premissas!$B$49,IF($A43-$D$17<=5,Premissas!$B$50,IF($A43-$D$17<=8,Premissas!$B$51,$G$17)))+IF($A43=1+$D$17,Premissas!$B$55,IF($A43=3+$D$17,Premissas!$B$56,IF($A43=6+$D$17,Premissas!$B$57,0)))) -> -5000 | CE43: =CC43+CD43 -> -5000 | CF43: =CF42+CE43 -> -10000 | CG43: =IF(CE43>0,$A43,9999) -> 9999 | CH43: =IF(CF43>0,$A43,9999) -> 9999
A44: 3 | C44: =IF($A44-$D$6<Premissas!$B$41,0,$C$6*(Premissas!$B$39+(Premissas!$B$40-Premissas!$B$39)*$A44/36)/(1+EXP(-$K$6*($A44-$D$6-$I$6)))) -> 0 | D44: =(C44*$B$6+IF($A44>=Premissas!$B$46+$D$6,$F$6,0))*(1-$E$6)*(1-Premissas!$B$60) -> 0 | E44: =-(C44*$J$6+MAX(0,C44-C43)*$H$6+IF($A44-$D$6<=2,Premissas!$B$49,IF($A44-$D$6<=5,Premissas!$B$50,IF($A44-$D$6<=8,Premissas!$B$51,$G$6)))+IF($A44=1+$D$6,Premissas!$B$55,IF($A44=3+$D$6,Premissas!$B$56,IF($A44=6+$D$6,Premissas!$B$57,0)))) -> -34000 | F44: =D44+E44 -> -34000 | G44: =G43+F44 -> -52000 | H44: =IF(F44>0,$A44,9999) -> 9999 | I44: =IF(G44>0,$A44,9999) -> 9999 | J44: =IF($A44-$D$7<Premissas!$B$41,0,$C$7*(Premissas!$B$39+(Premissas!$B$40-Premissas!$B$39)*$A44/36)/(1+EXP(-$K$7*($A44-$D$7-$I$7)))) -> 0 | K44: =(J44*$B$7+IF($A44>=Premissas!$B$46+$D$7,$F$7,0))*(1-$E$7)*(1-Premissas!$B$60) -> 0 | L44: =-(J44*$J$7+MAX(0,J44-J43)*$H$7+IF($A44-$D$7<=2,Premissas!$B$49,IF($A44-$D$7<=5,Premissas!$B$50,IF($A44-$D$7<=8,Premissas!$B$51,$G$7)))+IF($A44=1+$D$7,Premissas!$B$55,IF($A44=3+$D$7,Premissas!$B$56,IF($A44=6+$D$7,Premissas!$B$57,0)))) -> -34000 | M44: =K44+L44 -> -34000 | N44: =N43+M44 -> -52000 | O44: =IF(M44>0,$A44,9999) -> 9999 | P44: =IF(N44>0,$A44,9999) -> 9999 | Q44: =IF($A44-$D$8<Premissas!$B$41,0,$C$8*(Premissas!$B$39+(Premissas!$B$40-Premissas!$B$39)*$A44/36)/(1+EXP(-$K$8*($A44-$D$8-$I$8)))) -> 0 | R44: =(Q44*$B$8+IF($A44>=Premissas!$B$46+$D$8,$F$8,0))*(1-$E$8)*(1-Premissas!$B$60) -> 0 | S44: =-(Q44*$J$8+MAX(0,Q44-Q43)*$H$8+IF($A44-$D$8<=2,Premissas!$B$49,IF($A44-$D$8<=5,Premissas!$B$50,IF($A44-$D$8<=8,Premissas!$B$51,$G$8)))+IF($A44=1+$D$8,Premissas!$B$55,IF($A44=3+$D$8,Premissas!$B$56,IF($A44=6+$D$8,Premissas!$B$57,0)))) -> -34000 | T44: =R44+S44 -> -34000 | U44: =U43+T44 -> -52000 | V44: =IF(T44>0,$A44,9999) -> 9999 | W44: =IF(U44>0,$A44,9999) -> 9999 | X44: =IF($A44-$D$9<Premissas!$B$41,0,$C$9*(Premissas!$B$39+(Premissas!$B$40-Premissas!$B$39)*$A44/36)/(1+EXP(-$K$9*($A44-$D$9-$I$9)))) -> 0 | Y44: =(X44*$B$9+IF($A44>=Premissas!$B$46+$D$9,$F$9,0))*(1-$E$9)*(1-Premissas!$B$60) -> 0 | Z44: =-(X44*$J$9+MAX(0,X44-X43)*$H$9+IF($A44-$D$9<=2,Premissas!$B$49,IF($A44-$D$9<=5,Premissas!$B$50,IF($A44-$D$9<=8,Premissas!$B$51,$G$9)))+IF($A44=1+$D$9,Premissas!$B$55,IF($A44=3+$D$9,Premissas!$B$56,IF($A44=6+$D$9,Premissas!$B$57,0)))) -> -34000 | AA44: =Y44+Z44 -> -34000 | AB44: =AB43+AA44 -> -52000 | AC44: =IF(AA44>0,$A44,9999) -> 9999 | AD44: =IF(AB44>0,$A44,9999) -> 9999 | AE44: =IF($A44-$D$10<Premissas!$B$41,0,$C$10*(Premissas!$B$39+(Premissas!$B$40-Premissas!$B$39)*$A44/36)/(1+EXP(-$K$10*($A44-$D$10-$I$10)))) -> 0 | AF44: =(AE44*$B$10+IF($A44>=Premissas!$B$46+$D$10,$F$10,0))*(1-$E$10)*(1-Premissas!$B$60) -> 0 | AG44: =-(AE44*$J$10+MAX(0,AE44-AE43)*$H$10+IF($A44-$D$10<=2,Premissas!$B$49,IF($A44-$D$10<=5,Premissas!$B$50,IF($A44-$D$10<=8,Premissas!$B$51,$G$10)))+IF($A44=1+$D$10,Premissas!$B$55,IF($A44=3+$D$10,Premissas!$B$56,IF($A44=6+$D$10,Premissas!$B$57,0)))) -> -34000 | AH44: =AF44+AG44 -> -34000 | AI44: =AI43+AH44 -> -52000 | AJ44: =IF(AH44>0,$A44,9999) -> 9999 | AK44: =IF(AI44>0,$A44,9999) -> 9999 | AL44: =IF($A44-$D$11<Premissas!$B$41,0,$C$11*(Premissas!$B$39+(Premissas!$B$40-Premissas!$B$39)*$A44/36)/(1+EXP(-$K$11*($A44-$D$11-$I$11)))) -> 0 | AM44: =(AL44*$B$11+IF($A44>=Premissas!$B$46+$D$11,$F$11,0))*(1-$E$11)*(1-Premissas!$B$60) -> 0 | AN44: =-(AL44*$J$11+MAX(0,AL44-AL43)*$H$11+IF($A44-$D$11<=2,Premissas!$B$49,IF($A44-$D$11<=5,Premissas!$B$50,IF($A44-$D$11<=8,Premissas!$B$51,$G$11)))+IF($A44=1+$D$11,Premissas!$B$55,IF($A44=3+$D$11,Premissas!$B$56,IF($A44=6+$D$11,Premissas!$B$57,0)))) -> -34000 | AO44: =AM44+AN44 -> -34000 | AP44: =AP43+AO44 -> -52000 | AQ44: =IF(AO44>0,$A44,9999) -> 9999 | AR44: =IF(AP44>0,$A44,9999) -> 9999 | AS44: =IF($A44-$D$12<Premissas!$B$41,0,$C$12*(Premissas!$B$39+(Premissas!$B$40-Premissas!$B$39)*$A44/36)/(1+EXP(-$K$12*($A44-$D$12-$I$12)))) -> 0 | AT44: =(AS44*$B$12+IF($A44>=Premissas!$B$46+$D$12,$F$12,0))*(1-$E$12)*(1-Premissas!$B$60) -> 0 | AU44: =-(AS44*$J$12+MAX(0,AS44-AS43)*$H$12+IF($A44-$D$12<=2,Premissas!$B$49,IF($A44-$D$12<=5,Premissas!$B$50,IF($A44-$D$12<=8,Premissas!$B$51,$G$12)))+IF($A44=1+$D$12,Premissas!$B$55,IF($A44=3+$D$12,Premissas!$B$56,IF($A44=6+$D$12,Premissas!$B$57,0)))) -> -34000 | AV44: =AT44+AU44 -> -34000 | AW44: =AW43+AV44 -> -52000 | AX44: =IF(AV44>0,$A44,9999) -> 9999 | AY44: =IF(AW44>0,$A44,9999) -> 9999 | AZ44: =IF($A44-$D$13<Premissas!$B$41,0,$C$13*(Premissas!$B$39+(Premissas!$B$40-Premissas!$B$39)*$A44/36)/(1+EXP(-$K$13*($A44-$D$13-$I$13)))) -> 0 | BA44: =(AZ44*$B$13+IF($A44>=Premissas!$B$46+$D$13,$F$13,0))*(1-$E$13)*(1-Premissas!$B$60) -> 0 | BB44: =-(AZ44*$J$13+MAX(0,AZ44-AZ43)*$H$13+IF($A44-$D$13<=2,Premissas!$B$49,IF($A44-$D$13<=5,Premissas!$B$50,IF($A44-$D$13<=8,Premissas!$B$51,$G$13)))+IF($A44=1+$D$13,Premissas!$B$55,IF($A44=3+$D$13,Premissas!$B$56,IF($A44=6+$D$13,Premissas!$B$57,0)))) -> -5000 | BC44: =BA44+BB44 -> -5000 | BD44: =BD43+BC44 -> -15000 | BE44: =IF(BC44>0,$A44,9999) -> 9999 | BF44: =IF(BD44>0,$A44,9999) -> 9999 | BG44: =IF($A44-$D$14<Premissas!$B$41,0,$C$14*(Premissas!$B$39+(Premissas!$B$40-Premissas!$B$39)*$A44/36)/(1+EXP(-$K$14*($A44-$D$14-$I$14)))) -> 0 | BH44: =(BG44*$B$14+IF($A44>=Premissas!$B$46+$D$14,$F$14,0))*(1-$E$14)*(1-Premissas!$B$60) -> 0 | BI44: =-(BG44*$J$14+MAX(0,BG44-BG43)*$H$14+IF($A44-$D$14<=2,Premissas!$B$49,IF($A44-$D$14<=5,Premissas!$B$50,IF($A44-$D$14<=8,Premissas!$B$51,$G$14)))+IF($A44=1+$D$14,Premissas!$B$55,IF($A44=3+$D$14,Premissas!$B$56,IF($A44=6+$D$14,Premissas!$B$57,0)))) -> -34000 | BJ44: =BH44+BI44 -> -34000 | BK44: =BK43+BJ44 -> -52000 | BL44: =IF(BJ44>0,$A44,9999) -> 9999 | BM44: =IF(BK44>0,$A44,9999) -> 9999 | BN44: =IF($A44-$D$15<Premissas!$B$41,0,$C$15*(Premissas!$B$39+(Premissas!$B$40-Premissas!$B$39)*$A44/36)/(1+EXP(-$K$15*($A44-$D$15-$I$15)))) -> 0 | BO44: =(BN44*$B$15+IF($A44>=Premissas!$B$46+$D$15,$F$15,0))*(1-$E$15)*(1-Premissas!$B$60) -> 0 | BP44: =-(BN44*$J$15+MAX(0,BN44-BN43)*$H$15+IF($A44-$D$15<=2,Premissas!$B$49,IF($A44-$D$15<=5,Premissas!$B$50,IF($A44-$D$15<=8,Premissas!$B$51,$G$15)))+IF($A44=1+$D$15,Premissas!$B$55,IF($A44=3+$D$15,Premissas!$B$56,IF($A44=6+$D$15,Premissas!$B$57,0)))) -> -34000 | BQ44: =BO44+BP44 -> -34000 | BR44: =BR43+BQ44 -> -52000 | BS44: =IF(BQ44>0,$A44,9999) -> 9999 | BT44: =IF(BR44>0,$A44,9999) -> 9999 | BU44: =IF($A44-$D$16<Premissas!$B$41,0,$C$16*(Premissas!$B$39+(Premissas!$B$40-Premissas!$B$39)*$A44/36)/(1+EXP(-$K$16*($A44-$D$16-$I$16)))) -> 0 | BV44: =(BU44*$B$16+IF($A44>=Premissas!$B$46+$D$16,$F$16,0))*(1-$E$16)*(1-Premissas!$B$60) -> 0 | BW44: =-(BU44*$J$16+MAX(0,BU44-BU43)*$H$16+IF($A44-$D$16<=2,Premissas!$B$49,IF($A44-$D$16<=5,Premissas!$B$50,IF($A44-$D$16<=8,Premissas!$B$51,$G$16)))+IF($A44=1+$D$16,Premissas!$B$55,IF($A44=3+$D$16,Premissas!$B$56,IF($A44=6+$D$16,Premissas!$B$57,0)))) -> -34000 | BX44: =BV44+BW44 -> -34000 | BY44: =BY43+BX44 -> -52000 | BZ44: =IF(BX44>0,$A44,9999) -> 9999 | CA44: =IF(BY44>0,$A44,9999) -> 9999 | CB44: =IF($A44-$D$17<Premissas!$B$41,0,$C$17*(Premissas!$B$39+(Premissas!$B$40-Premissas!$B$39)*$A44/36)/(1+EXP(-$K$17*($A44-$D$17-$I$17)))) -> 0 | CC44: =(CB44*$B$17+IF($A44>=Premissas!$B$46+$D$17,$F$17,0))*(1-$E$17)*(1-Premissas!$B$60) -> 0 | CD44: =-(CB44*$J$17+MAX(0,CB44-CB43)*$H$17+IF($A44-$D$17<=2,Premissas!$B$49,IF($A44-$D$17<=5,Premissas!$B$50,IF($A44-$D$17<=8,Premissas!$B$51,$G$17)))+IF($A44=1+$D$17,Premissas!$B$55,IF($A44=3+$D$17,Premissas!$B$56,IF($A44=6+$D$17,Premissas!$B$57,0)))) -> -5000 | CE44: =CC44+CD44 -> -5000 | CF44: =CF43+CE44 -> -15000 | CG44: =IF(CE44>0,$A44,9999) -> 9999 | CH44: =IF(CF44>0,$A44,9999) -> 9999
A45: 4 | C45: =IF($A45-$D$6<Premissas!$B$41,0,$C$6*(Premissas!$B$39+(Premissas!$B$40-Premissas!$B$39)*$A45/36)/(1+EXP(-$K$6*($A45-$D$6-$I$6)))) -> 0 | D45: =(C45*$B$6+IF($A45>=Premissas!$B$46+$D$6,$F$6,0))*(1-$E$6)*(1-Premissas!$B$60) -> 0 | E45: =-(C45*$J$6+MAX(0,C45-C44)*$H$6+IF($A45-$D$6<=2,Premissas!$B$49,IF($A45-$D$6<=5,Premissas!$B$50,IF($A45-$D$6<=8,Premissas!$B$51,$G$6)))+IF($A45=1+$D$6,Premissas!$B$55,IF($A45=3+$D$6,Premissas!$B$56,IF($A45=6+$D$6,Premissas!$B$57,0)))) -> -22000 | F45: =D45+E45 -> -22000 | G45: =G44+F45 -> -74000 | H45: =IF(F45>0,$A45,9999) -> 9999 | I45: =IF(G45>0,$A45,9999) -> 9999 | J45: =IF($A45-$D$7<Premissas!$B$41,0,$C$7*(Premissas!$B$39+(Premissas!$B$40-Premissas!$B$39)*$A45/36)/(1+EXP(-$K$7*($A45-$D$7-$I$7)))) -> 0 | K45: =(J45*$B$7+IF($A45>=Premissas!$B$46+$D$7,$F$7,0))*(1-$E$7)*(1-Premissas!$B$60) -> 0 | L45: =-(J45*$J$7+MAX(0,J45-J44)*$H$7+IF($A45-$D$7<=2,Premissas!$B$49,IF($A45-$D$7<=5,Premissas!$B$50,IF($A45-$D$7<=8,Premissas!$B$51,$G$7)))+IF($A45=1+$D$7,Premissas!$B$55,IF($A45=3+$D$7,Premissas!$B$56,IF($A45=6+$D$7,Premissas!$B$57,0)))) -> -22000 | M45: =K45+L45 -> -22000 | N45: =N44+M45 -> -74000 | O45: =IF(M45>0,$A45,9999) -> 9999 | P45: =IF(N45>0,$A45,9999) -> 9999 | Q45: =IF($A45-$D$8<Premissas!$B$41,0,$C$8*(Premissas!$B$39+(Premissas!$B$40-Premissas!$B$39)*$A45/36)/(1+EXP(-$K$8*($A45-$D$8-$I$8)))) -> 0 | R45: =(Q45*$B$8+IF($A45>=Premissas!$B$46+$D$8,$F$8,0))*(1-$E$8)*(1-Premissas!$B$60) -> 0 | S45: =-(Q45*$J$8+MAX(0,Q45-Q44)*$H$8+IF($A45-$D$8<=2,Premissas!$B$49,IF($A45-$D$8<=5,Premissas!$B$50,IF($A45-$D$8<=8,Premissas!$B$51,$G$8)))+IF($A45=1+$D$8,Premissas!$B$55,IF($A45=3+$D$8,Premissas!$B$56,IF($A45=6+$D$8,Premissas!$B$57,0)))) -> -22000 | T45: =R45+S45 -> -22000 | U45: =U44+T45 -> -74000 | V45: =IF(T45>0,$A45,9999) -> 9999 | W45: =IF(U45>0,$A45,9999) -> 9999 | X45: =IF($A45-$D$9<Premissas!$B$41,0,$C$9*(Premissas!$B$39+(Premissas!$B$40-Premissas!$B$39)*$A45/36)/(1+EXP(-$K$9*($A45-$D$9-$I$9)))) -> 0 | Y45: =(X45*$B$9+IF($A45>=Premissas!$B$46+$D$9,$F$9,0))*(1-$E$9)*(1-Premissas!$B$60) -> 0 | Z45: =-(X45*$J$9+MAX(0,X45-X44)*$H$9+IF($A45-$D$9<=2,Premissas!$B$49,IF($A45-$D$9<=5,Premissas!$B$50,IF($A45-$D$9<=8,Premissas!$B$51,$G$9)))+IF($A45=1+$D$9,Premissas!$B$55,IF($A45=3+$D$9,Premissas!$B$56,IF($A45=6+$D$9,Premissas!$B$57,0)))) -> -22000 | AA45: =Y45+Z45 -> -22000 | AB45: =AB44+AA45 -> -74000 | AC45: =IF(AA45>0,$A45,9999) -> 9999 | AD45: =IF(AB45>0,$A45,9999) -> 9999 | AE45: =IF($A45-$D$10<Premissas!$B$41,0,$C$10*(Premissas!$B$39+(Premissas!$B$40-Premissas!$B$39)*$A45/36)/(1+EXP(-$K$10*($A45-$D$10-$I$10)))) -> 0 | AF45: =(AE45*$B$10+IF($A45>=Premissas!$B$46+$D$10,$F$10,0))*(1-$E$10)*(1-Premissas!$B$60) -> 0 | AG45: =-(AE45*$J$10+MAX(0,AE45-AE44)*$H$10+IF($A45-$D$10<=2,Premissas!$B$49,IF($A45-$D$10<=5,Premissas!$B$50,IF($A45-$D$10<=8,Premissas!$B$51,$G$10)))+IF($A45=1+$D$10,Premissas!$B$55,IF($A45=3+$D$10,Premissas!$B$56,IF($A45=6+$D$10,Premissas!$B$57,0)))) -> -22000 | AH45: =AF45+AG45 -> -22000 | AI45: =AI44+AH45 -> -74000 | AJ45: =IF(AH45>0,$A45,9999) -> 9999 | AK45: =IF(AI45>0,$A45,9999) -> 9999 | AL45: =IF($A45-$D$11<Premissas!$B$41,0,$C$11*(Premissas!$B$39+(Premissas!$B$40-Premissas!$B$39)*$A45/36)/(1+EXP(-$K$11*($A45-$D$11-$I$11)))) -> 0 | AM45: =(AL45*$B$11+IF($A45>=Premissas!$B$46+$D$11,$F$11,0))*(1-$E$11)*(1-Premissas!$B$60) -> 0 | AN45: =-(AL45*$J$11+MAX(0,AL45-AL44)*$H$11+IF($A45-$D$11<=2,Premissas!$B$49,IF($A45-$D$11<=5,Premissas!$B$50,IF($A45-$D$11<=8,Premissas!$B$51,$G$11)))+IF($A45=1+$D$11,Premissas!$B$55,IF($A45=3+$D$11,Premissas!$B$56,IF($A45=6+$D$11,Premissas!$B$57,0)))) -> -22000 | AO45: =AM45+AN45 -> -22000 | AP45: =AP44+AO45 -> -74000 | AQ45: =IF(AO45>0,$A45,9999) -> 9999 | AR45: =IF(AP45>0,$A45,9999) -> 9999 | AS45: =IF($A45-$D$12<Premissas!$B$41,0,$C$12*(Premissas!$B$39+(Premissas!$B$40-Premissas!$B$39)*$A45/36)/(1+EXP(-$K$12*($A45-$D$12-$I$12)))) -> 0 | AT45: =(AS45*$B$12+IF($A45>=Premissas!$B$46+$D$12,$F$12,0))*(1-$E$12)*(1-Premissas!$B$60) -> 0 | AU45: =-(AS45*$J$12+MAX(0,AS45-AS44)*$H$12+IF($A45-$D$12<=2,Premissas!$B$49,IF($A45-$D$12<=5,Premissas!$B$50,IF($A45-$D$12<=8,Premissas!$B$51,$G$12)))+IF($A45=1+$D$12,Premissas!$B$55,IF($A45=3+$D$12,Premissas!$B$56,IF($A45=6+$D$12,Premissas!$B$57,0)))) -> -22000 | AV45: =AT45+AU45 -> -22000 | AW45: =AW44+AV45 -> -74000 | AX45: =IF(AV45>0,$A45,9999) -> 9999 | AY45: =IF(AW45>0,$A45,9999) -> 9999 | AZ45: =IF($A45-$D$13<Premissas!$B$41,0,$C$13*(Premissas!$B$39+(Premissas!$B$40-Premissas!$B$39)*$A45/36)/(1+EXP(-$K$13*($A45-$D$13-$I$13)))) -> 0 | BA45: =(AZ45*$B$13+IF($A45>=Premissas!$B$46+$D$13,$F$13,0))*(1-$E$13)*(1-Premissas!$B$60) -> 0 | BB45: =-(AZ45*$J$13+MAX(0,AZ45-AZ44)*$H$13+IF($A45-$D$13<=2,Premissas!$B$49,IF($A45-$D$13<=5,Premissas!$B$50,IF($A45-$D$13<=8,Premissas!$B$51,$G$13)))+IF($A45=1+$D$13,Premissas!$B$55,IF($A45=3+$D$13,Premissas!$B$56,IF($A45=6+$D$13,Premissas!$B$57,0)))) -> -5000 | BC45: =BA45+BB45 -> -5000 | BD45: =BD44+BC45 -> -20000 | BE45: =IF(BC45>0,$A45,9999) -> 9999 | BF45: =IF(BD45>0,$A45,9999) -> 9999 | BG45: =IF($A45-$D$14<Premissas!$B$41,0,$C$14*(Premissas!$B$39+(Premissas!$B$40-Premissas!$B$39)*$A45/36)/(1+EXP(-$K$14*($A45-$D$14-$I$14)))) -> 0 | BH45: =(BG45*$B$14+IF($A45>=Premissas!$B$46+$D$14,$F$14,0))*(1-$E$14)*(1-Premissas!$B$60) -> 0 | BI45: =-(BG45*$J$14+MAX(0,BG45-BG44)*$H$14+IF($A45-$D$14<=2,Premissas!$B$49,IF($A45-$D$14<=5,Premissas!$B$50,IF($A45-$D$14<=8,Premissas!$B$51,$G$14)))+IF($A45=1+$D$14,Premissas!$B$55,IF($A45=3+$D$14,Premissas!$B$56,IF($A45=6+$D$14,Premissas!$B$57,0)))) -> -22000 | BJ45: =BH45+BI45 -> -22000 | BK45: =BK44+BJ45 -> -74000 | BL45: =IF(BJ45>0,$A45,9999) -> 9999 | BM45: =IF(BK45>0,$A45,9999) -> 9999 | BN45: =IF($A45-$D$15<Premissas!$B$41,0,$C$15*(Premissas!$B$39+(Premissas!$B$40-Premissas!$B$39)*$A45/36)/(1+EXP(-$K$15*($A45-$D$15-$I$15)))) -> 0 | BO45: =(BN45*$B$15+IF($A45>=Premissas!$B$46+$D$15,$F$15,0))*(1-$E$15)*(1-Premissas!$B$60) -> 0 | BP45: =-(BN45*$J$15+MAX(0,BN45-BN44)*$H$15+IF($A45-$D$15<=2,Premissas!$B$49,IF($A45-$D$15<=5,Premissas!$B$50,IF($A45-$D$15<=8,Premissas!$B$51,$G$15)))+IF($A45=1+$D$15,Premissas!$B$55,IF($A45=3+$D$15,Premissas!$B$56,IF($A45=6+$D$15,Premissas!$B$57,0)))) -> -22000 | BQ45: =BO45+BP45 -> -22000 | BR45: =BR44+BQ45 -> -74000 | BS45: =IF(BQ45>0,$A45,9999) -> 9999 | BT45: =IF(BR45>0,$A45,9999) -> 9999 | BU45: =IF($A45-$D$16<Premissas!$B$41,0,$C$16*(Premissas!$B$39+(Premissas!$B$40-Premissas!$B$39)*$A45/36)/(1+EXP(-$K$16*($A45-$D$16-$I$16)))) -> 0 | BV45: =(BU45*$B$16+IF($A45>=Premissas!$B$46+$D$16,$F$16,0))*(1-$E$16)*(1-Premissas!$B$60) -> 0 | BW45: =-(BU45*$J$16+MAX(0,BU45-BU44)*$H$16+IF($A45-$D$16<=2,Premissas!$B$49,IF($A45-$D$16<=5,Premissas!$B$50,IF($A45-$D$16<=8,Premissas!$B$51,$G$16)))+IF($A45=1+$D$16,Premissas!$B$55,IF($A45=3+$D$16,Premissas!$B$56,IF($A45=6+$D$16,Premissas!$B$57,0)))) -> -22000 | BX45: =BV45+BW45 -> -22000 | BY45: =BY44+BX45 -> -74000 | BZ45: =IF(BX45>0,$A45,9999) -> 9999 | CA45: =IF(BY45>0,$A45,9999) -> 9999 | CB45: =IF($A45-$D$17<Premissas!$B$41,0,$C$17*(Premissas!$B$39+(Premissas!$B$40-Premissas!$B$39)*$A45/36)/(1+EXP(-$K$17*($A45-$D$17-$I$17)))) -> 0 | CC45: =(CB45*$B$17+IF($A45>=Premissas!$B$46+$D$17,$F$17,0))*(1-$E$17)*(1-Premissas!$B$60) -> 0 | CD45: =-(CB45*$J$17+MAX(0,CB45-CB44)*$H$17+IF($A45-$D$17<=2,Premissas!$B$49,IF($A45-$D$17<=5,Premissas!$B$50,IF($A45-$D$17<=8,Premissas!$B$51,$G$17)))+IF($A45=1+$D$17,Premissas!$B$55,IF($A45=3+$D$17,Premissas!$B$56,IF($A45=6+$D$17,Premissas!$B$57,0)))) -> -5000 | CE45: =CC45+CD45 -> -5000 | CF45: =CF44+CE45 -> -20000 | CG45: =IF(CE45>0,$A45,9999) -> 9999 | CH45: =IF(CF45>0,$A45,9999) -> 9999
A46: 5 | C46: =IF($A46-$D$6<Premissas!$B$41,0,$C$6*(Premissas!$B$39+(Premissas!$B$40-Premissas!$B$39)*$A46/36)/(1+EXP(-$K$6*($A46-$D$6-$I$6)))) -> 0 | D46: =(C46*$B$6+IF($A46>=Premissas!$B$46+$D$6,$F$6,0))*(1-$E$6)*(1-Premissas!$B$60) -> 0 | E46: =-(C46*$J$6+MAX(0,C46-C45)*$H$6+IF($A46-$D$6<=2,Premissas!$B$49,IF($A46-$D$6<=5,Premissas!$B$50,IF($A46-$D$6<=8,Premissas!$B$51,$G$6)))+IF($A46=1+$D$6,Premissas!$B$55,IF($A46=3+$D$6,Premissas!$B$56,IF($A46=6+$D$6,Premissas!$B$57,0)))) -> -22000 | F46: =D46+E46 -> -22000 | G46: =G45+F46 -> -96000 | H46: =IF(F46>0,$A46,9999) -> 9999 | I46: =IF(G46>0,$A46,9999) -> 9999 | J46: =IF($A46-$D$7<Premissas!$B$41,0,$C$7*(Premissas!$B$39+(Premissas!$B$40-Premissas!$B$39)*$A46/36)/(1+EXP(-$K$7*($A46-$D$7-$I$7)))) -> 0 | K46: =(J46*$B$7+IF($A46>=Premissas!$B$46+$D$7,$F$7,0))*(1-$E$7)*(1-Premissas!$B$60) -> 0 | L46: =-(J46*$J$7+MAX(0,J46-J45)*$H$7+IF($A46-$D$7<=2,Premissas!$B$49,IF($A46-$D$7<=5,Premissas!$B$50,IF($A46-$D$7<=8,Premissas!$B$51,$G$7)))+IF($A46=1+$D$7,Premissas!$B$55,IF($A46=3+$D$7,Premissas!$B$56,IF($A46=6+$D$7,Premissas!$B$57,0)))) -> -22000 | M46: =K46+L46 -> -22000 | N46: =N45+M46 -> -96000 | O46: =IF(M46>0,$A46,9999) -> 9999 | P46: =IF(N46>0,$A46,9999) -> 9999 | Q46: =IF($A46-$D$8<Premissas!$B$41,0,$C$8*(Premissas!$B$39+(Premissas!$B$40-Premissas!$B$39)*$A46/36)/(1+EXP(-$K$8*($A46-$D$8-$I$8)))) -> 0 | R46: =(Q46*$B$8+IF($A46>=Premissas!$B$46+$D$8,$F$8,0))*(1-$E$8)*(1-Premissas!$B$60) -> 0 | S46: =-(Q46*$J$8+MAX(0,Q46-Q45)*$H$8+IF($A46-$D$8<=2,Premissas!$B$49,IF($A46-$D$8<=5,Premissas!$B$50,IF($A46-$D$8<=8,Premissas!$B$51,$G$8)))+IF($A46=1+$D$8,Premissas!$B$55,IF($A46=3+$D$8,Premissas!$B$56,IF($A46=6+$D$8,Premissas!$B$57,0)))) -> -22000 | T46: =R46+S46 -> -22000 | U46: =U45+T46 -> -96000 | V46: =IF(T46>0,$A46,9999) -> 9999 | W46: =IF(U46>0,$A46,9999) -> 9999 | X46: =IF($A46-$D$9<Premissas!$B$41,0,$C$9*(Premissas!$B$39+(Premissas!$B$40-Premissas!$B$39)*$A46/36)/(1+EXP(-$K$9*($A46-$D$9-$I$9)))) -> 0 | Y46: =(X46*$B$9+IF($A46>=Premissas!$B$46+$D$9,$F$9,0))*(1-$E$9)*(1-Premissas!$B$60) -> 0 | Z46: =-(X46*$J$9+MAX(0,X46-X45)*$H$9+IF($A46-$D$9<=2,Premissas!$B$49,IF($A46-$D$9<=5,Premissas!$B$50,IF($A46-$D$9<=8,Premissas!$B$51,$G$9)))+IF($A46=1+$D$9,Premissas!$B$55,IF($A46=3+$D$9,Premissas!$B$56,IF($A46=6+$D$9,Premissas!$B$57,0)))) -> -22000 | AA46: =Y46+Z46 -> -22000 | AB46: =AB45+AA46 -> -96000 | AC46: =IF(AA46>0,$A46,9999) -> 9999 | AD46: =IF(AB46>0,$A46,9999) -> 9999 | AE46: =IF($A46-$D$10<Premissas!$B$41,0,$C$10*(Premissas!$B$39+(Premissas!$B$40-Premissas!$B$39)*$A46/36)/(1+EXP(-$K$10*($A46-$D$10-$I$10)))) -> 0 | AF46: =(AE46*$B$10+IF($A46>=Premissas!$B$46+$D$10,$F$10,0))*(1-$E$10)*(1-Premissas!$B$60) -> 0 | AG46: =-(AE46*$J$10+MAX(0,AE46-AE45)*$H$10+IF($A46-$D$10<=2,Premissas!$B$49,IF($A46-$D$10<=5,Premissas!$B$50,IF($A46-$D$10<=8,Premissas!$B$51,$G$10)))+IF($A46=1+$D$10,Premissas!$B$55,IF($A46=3+$D$10,Premissas!$B$56,IF($A46=6+$D$10,Premissas!$B$57,0)))) -> -22000 | AH46: =AF46+AG46 -> -22000 | AI46: =AI45+AH46 -> -96000 | AJ46: =IF(AH46>0,$A46,9999) -> 9999 | AK46: =IF(AI46>0,$A46,9999) -> 9999 | AL46: =IF($A46-$D$11<Premissas!$B$41,0,$C$11*(Premissas!$B$39+(Premissas!$B$40-Premissas!$B$39)*$A46/36)/(1+EXP(-$K$11*($A46-$D$11-$I$11)))) -> 0 | AM46: =(AL46*$B$11+IF($A46>=Premissas!$B$46+$D$11,$F$11,0))*(1-$E$11)*(1-Premissas!$B$60) -> 0 | AN46: =-(AL46*$J$11+MAX(0,AL46-AL45)*$H$11+IF($A46-$D$11<=2,Premissas!$B$49,IF($A46-$D$11<=5,Premissas!$B$50,IF($A46-$D$11<=8,Premissas!$B$51,$G$11)))+IF($A46=1+$D$11,Premissas!$B$55,IF($A46=3+$D$11,Premissas!$B$56,IF($A46=6+$D$11,Premissas!$B$57,0)))) -> -22000 | AO46: =AM46+AN46 -> -22000 | AP46: =AP45+AO46 -> -96000 | AQ46: =IF(AO46>0,$A46,9999) -> 9999 | AR46: =IF(AP46>0,$A46,9999) -> 9999 | AS46: =IF($A46-$D$12<Premissas!$B$41,0,$C$12*(Premissas!$B$39+(Premissas!$B$40-Premissas!$B$39)*$A46/36)/(1+EXP(-$K$12*($A46-$D$12-$I$12)))) -> 0 | AT46: =(AS46*$B$12+IF($A46>=Premissas!$B$46+$D$12,$F$12,0))*(1-$E$12)*(1-Premissas!$B$60) -> 0 | AU46: =-(AS46*$J$12+MAX(0,AS46-AS45)*$H$12+IF($A46-$D$12<=2,Premissas!$B$49,IF($A46-$D$12<=5,Premissas!$B$50,IF($A46-$D$12<=8,Premissas!$B$51,$G$12)))+IF($A46=1+$D$12,Premissas!$B$55,IF($A46=3+$D$12,Premissas!$B$56,IF($A46=6+$D$12,Premissas!$B$57,0)))) -> -22000 | AV46: =AT46+AU46 -> -22000 | AW46: =AW45+AV46 -> -96000 | AX46: =IF(AV46>0,$A46,9999) -> 9999 | AY46: =IF(AW46>0,$A46,9999) -> 9999 | AZ46: =IF($A46-$D$13<Premissas!$B$41,0,$C$13*(Premissas!$B$39+(Premissas!$B$40-Premissas!$B$39)*$A46/36)/(1+EXP(-$K$13*($A46-$D$13-$I$13)))) -> 0 | BA46: =(AZ46*$B$13+IF($A46>=Premissas!$B$46+$D$13,$F$13,0))*(1-$E$13)*(1-Premissas!$B$60) -> 0 | BB46: =-(AZ46*$J$13+MAX(0,AZ46-AZ45)*$H$13+IF($A46-$D$13<=2,Premissas!$B$49,IF($A46-$D$13<=5,Premissas!$B$50,IF($A46-$D$13<=8,Premissas!$B$51,$G$13)))+IF($A46=1+$D$13,Premissas!$B$55,IF($A46=3+$D$13,Premissas!$B$56,IF($A46=6+$D$13,Premissas!$B$57,0)))) -> -5000 | BC46: =BA46+BB46 -> -5000 | BD46: =BD45+BC46 -> -25000 | BE46: =IF(BC46>0,$A46,9999) -> 9999 | BF46: =IF(BD46>0,$A46,9999) -> 9999 | BG46: =IF($A46-$D$14<Premissas!$B$41,0,$C$14*(Premissas!$B$39+(Premissas!$B$40-Premissas!$B$39)*$A46/36)/(1+EXP(-$K$14*($A46-$D$14-$I$14)))) -> 0 | BH46: =(BG46*$B$14+IF($A46>=Premissas!$B$46+$D$14,$F$14,0))*(1-$E$14)*(1-Premissas!$B$60) -> 0 | BI46: =-(BG46*$J$14+MAX(0,BG46-BG45)*$H$14+IF($A46-$D$14<=2,Premissas!$B$49,IF($A46-$D$14<=5,Premissas!$B$50,IF($A46-$D$14<=8,Premissas!$B$51,$G$14)))+IF($A46=1+$D$14,Premissas!$B$55,IF($A46=3+$D$14,Premissas!$B$56,IF($A46=6+$D$14,Premissas!$B$57,0)))) -> -22000 | BJ46: =BH46+BI46 -> -22000 | BK46: =BK45+BJ46 -> -96000 | BL46: =IF(BJ46>0,$A46,9999) -> 9999 | BM46: =IF(BK46>0,$A46,9999) -> 9999 | BN46: =IF($A46-$D$15<Premissas!$B$41,0,$C$15*(Premissas!$B$39+(Premissas!$B$40-Premissas!$B$39)*$A46/36)/(1+EXP(-$K$15*($A46-$D$15-$I$15)))) -> 0 | BO46: =(BN46*$B$15+IF($A46>=Premissas!$B$46+$D$15,$F$15,0))*(1-$E$15)*(1-Premissas!$B$60) -> 0 | BP46: =-(BN46*$J$15+MAX(0,BN46-BN45)*$H$15+IF($A46-$D$15<=2,Premissas!$B$49,IF($A46-$D$15<=5,Premissas!$B$50,IF($A46-$D$15<=8,Premissas!$B$51,$G$15)))+IF($A46=1+$D$15,Premissas!$B$55,IF($A46=3+$D$15,Premissas!$B$56,IF($A46=6+$D$15,Premissas!$B$57,0)))) -> -22000 | BQ46: =BO46+BP46 -> -22000 | BR46: =BR45+BQ46 -> -96000 | BS46: =IF(BQ46>0,$A46,9999) -> 9999 | BT46: =IF(BR46>0,$A46,9999) -> 9999 | BU46: =IF($A46-$D$16<Premissas!$B$41,0,$C$16*(Premissas!$B$39+(Premissas!$B$40-Premissas!$B$39)*$A46/36)/(1+EXP(-$K$16*($A46-$D$16-$I$16)))) -> 0 | BV46: =(BU46*$B$16+IF($A46>=Premissas!$B$46+$D$16,$F$16,0))*(1-$E$16)*(1-Premissas!$B$60) -> 0 | BW46: =-(BU46*$J$16+MAX(0,BU46-BU45)*$H$16+IF($A46-$D$16<=2,Premissas!$B$49,IF($A46-$D$16<=5,Premissas!$B$50,IF($A46-$D$16<=8,Premissas!$B$51,$G$16)))+IF($A46=1+$D$16,Premissas!$B$55,IF($A46=3+$D$16,Premissas!$B$56,IF($A46=6+$D$16,Premissas!$B$57,0)))) -> -22000 | BX46: =BV46+BW46 -> -22000 | BY46: =BY45+BX46 -> -96000 | BZ46: =IF(BX46>0,$A46,9999) -> 9999 | CA46: =IF(BY46>0,$A46,9999) -> 9999 | CB46: =IF($A46-$D$17<Premissas!$B$41,0,$C$17*(Premissas!$B$39+(Premissas!$B$40-Premissas!$B$39)*$A46/36)/(1+EXP(-$K$17*($A46-$D$17-$I$17)))) -> 0 | CC46: =(CB46*$B$17+IF($A46>=Premissas!$B$46+$D$17,$F$17,0))*(1-$E$17)*(1-Premissas!$B$60) -> 0 | CD46: =-(CB46*$J$17+MAX(0,CB46-CB45)*$H$17+IF($A46-$D$17<=2,Premissas!$B$49,IF($A46-$D$17<=5,Premissas!$B$50,IF($A46-$D$17<=8,Premissas!$B$51,$G$17)))+IF($A46=1+$D$17,Premissas!$B$55,IF($A46=3+$D$17,Premissas!$B$56,IF($A46=6+$D$17,Premissas!$B$57,0)))) -> -5000 | CE46: =CC46+CD46 -> -5000 | CF46: =CF45+CE46 -> -25000 | CG46: =IF(CE46>0,$A46,9999) -> 9999 | CH46: =IF(CF46>0,$A46,9999) -> 9999
A47: 6 | C47: =IF($A47-$D$6<Premissas!$B$41,0,$C$6*(Premissas!$B$39+(Premissas!$B$40-Premissas!$B$39)*$A47/36)/(1+EXP(-$K$6*($A47-$D$6-$I$6)))) -> 0 | D47: =(C47*$B$6+IF($A47>=Premissas!$B$46+$D$6,$F$6,0))*(1-$E$6)*(1-Premissas!$B$60) -> 0 | E47: =-(C47*$J$6+MAX(0,C47-C46)*$H$6+IF($A47-$D$6<=2,Premissas!$B$49,IF($A47-$D$6<=5,Premissas!$B$50,IF($A47-$D$6<=8,Premissas!$B$51,$G$6)))+IF($A47=1+$D$6,Premissas!$B$55,IF($A47=3+$D$6,Premissas!$B$56,IF($A47=6+$D$6,Premissas!$B$57,0)))) -> -38000 | F47: =D47+E47 -> -38000 | G47: =G46+F47 -> -134000 | H47: =IF(F47>0,$A47,9999) -> 9999 | I47: =IF(G47>0,$A47,9999) -> 9999 | J47: =IF($A47-$D$7<Premissas!$B$41,0,$C$7*(Premissas!$B$39+(Premissas!$B$40-Premissas!$B$39)*$A47/36)/(1+EXP(-$K$7*($A47-$D$7-$I$7)))) -> 0 | K47: =(J47*$B$7+IF($A47>=Premissas!$B$46+$D$7,$F$7,0))*(1-$E$7)*(1-Premissas!$B$60) -> 0 | L47: =-(J47*$J$7+MAX(0,J47-J46)*$H$7+IF($A47-$D$7<=2,Premissas!$B$49,IF($A47-$D$7<=5,Premissas!$B$50,IF($A47-$D$7<=8,Premissas!$B$51,$G$7)))+IF($A47=1+$D$7,Premissas!$B$55,IF($A47=3+$D$7,Premissas!$B$56,IF($A47=6+$D$7,Premissas!$B$57,0)))) -> -38000 | M47: =K47+L47 -> -38000 | N47: =N46+M47 -> -134000 | O47: =IF(M47>0,$A47,9999) -> 9999 | P47: =IF(N47>0,$A47,9999) -> 9999 | Q47: =IF($A47-$D$8<Premissas!$B$41,0,$C$8*(Premissas!$B$39+(Premissas!$B$40-Premissas!$B$39)*$A47/36)/(1+EXP(-$K$8*($A47-$D$8-$I$8)))) -> 0 | R47: =(Q47*$B$8+IF($A47>=Premissas!$B$46+$D$8,$F$8,0))*(1-$E$8)*(1-Premissas!$B$60) -> 0 | S47: =-(Q47*$J$8+MAX(0,Q47-Q46)*$H$8+IF($A47-$D$8<=2,Premissas!$B$49,IF($A47-$D$8<=5,Premissas!$B$50,IF($A47-$D$8<=8,Premissas!$B$51,$G$8)))+IF($A47=1+$D$8,Premissas!$B$55,IF($A47=3+$D$8,Premissas!$B$56,IF($A47=6+$D$8,Premissas!$B$57,0)))) -> -38000 | T47: =R47+S47 -> -38000 | U47: =U46+T47 -> -134000 | V47: =IF(T47>0,$A47,9999) -> 9999 | W47: =IF(U47>0,$A47,9999) -> 9999 | X47: =IF($A47-$D$9<Premissas!$B$41,0,$C$9*(Premissas!$B$39+(Premissas!$B$40-Premissas!$B$39)*$A47/36)/(1+EXP(-$K$9*($A47-$D$9-$I$9)))) -> 0 | Y47: =(X47*$B$9+IF($A47>=Premissas!$B$46+$D$9,$F$9,0))*(1-$E$9)*(1-Premissas!$B$60) -> 0 | Z47: =-(X47*$J$9+MAX(0,X47-X46)*$H$9+IF($A47-$D$9<=2,Premissas!$B$49,IF($A47-$D$9<=5,Premissas!$B$50,IF($A47-$D$9<=8,Premissas!$B$51,$G$9)))+IF($A47=1+$D$9,Premissas!$B$55,IF($A47=3+$D$9,Premissas!$B$56,IF($A47=6+$D$9,Premissas!$B$57,0)))) -> -38000 | AA47: =Y47+Z47 -> -38000 | AB47: =AB46+AA47 -> -134000 | AC47: =IF(AA47>0,$A47,9999) -> 9999 | AD47: =IF(AB47>0,$A47,9999) -> 9999 | AE47: =IF($A47-$D$10<Premissas!$B$41,0,$C$10*(Premissas!$B$39+(Premissas!$B$40-Premissas!$B$39)*$A47/36)/(1+EXP(-$K$10*($A47-$D$10-$I$10)))) -> 0 | AF47: =(AE47*$B$10+IF($A47>=Premissas!$B$46+$D$10,$F$10,0))*(1-$E$10)*(1-Premissas!$B$60) -> 0 | AG47: =-(AE47*$J$10+MAX(0,AE47-AE46)*$H$10+IF($A47-$D$10<=2,Premissas!$B$49,IF($A47-$D$10<=5,Premissas!$B$50,IF($A47-$D$10<=8,Premissas!$B$51,$G$10)))+IF($A47=1+$D$10,Premissas!$B$55,IF($A47=3+$D$10,Premissas!$B$56,IF($A47=6+$D$10,Premissas!$B$57,0)))) -> -38000 | AH47: =AF47+AG47 -> -38000 | AI47: =AI46+AH47 -> -134000 | AJ47: =IF(AH47>0,$A47,9999) -> 9999 | AK47: =IF(AI47>0,$A47,9999) -> 9999 | AL47: =IF($A47-$D$11<Premissas!$B$41,0,$C$11*(Premissas!$B$39+(Premissas!$B$40-Premissas!$B$39)*$A47/36)/(1+EXP(-$K$11*($A47-$D$11-$I$11)))) -> 0 | AM47: =(AL47*$B$11+IF($A47>=Premissas!$B$46+$D$11,$F$11,0))*(1-$E$11)*(1-Premissas!$B$60) -> 0 | AN47: =-(AL47*$J$11+MAX(0,AL47-AL46)*$H$11+IF($A47-$D$11<=2,Premissas!$B$49,IF($A47-$D$11<=5,Premissas!$B$50,IF($A47-$D$11<=8,Premissas!$B$51,$G$11)))+IF($A47=1+$D$11,Premissas!$B$55,IF($A47=3+$D$11,Premissas!$B$56,IF($A47=6+$D$11,Premissas!$B$57,0)))) -> -38000 | AO47: =AM47+AN47 -> -38000 | AP47: =AP46+AO47 -> -134000 | AQ47: =IF(AO47>0,$A47,9999) -> 9999 | AR47: =IF(AP47>0,$A47,9999) -> 9999 | AS47: =IF($A47-$D$12<Premissas!$B$41,0,$C$12*(Premissas!$B$39+(Premissas!$B$40-Premissas!$B$39)*$A47/36)/(1+EXP(-$K$12*($A47-$D$12-$I$12)))) -> 0 | AT47: =(AS47*$B$12+IF($A47>=Premissas!$B$46+$D$12,$F$12,0))*(1-$E$12)*(1-Premissas!$B$60) -> 0 | AU47: =-(AS47*$J$12+MAX(0,AS47-AS46)*$H$12+IF($A47-$D$12<=2,Premissas!$B$49,IF($A47-$D$12<=5,Premissas!$B$50,IF($A47-$D$12<=8,Premissas!$B$51,$G$12)))+IF($A47=1+$D$12,Premissas!$B$55,IF($A47=3+$D$12,Premissas!$B$56,IF($A47=6+$D$12,Premissas!$B$57,0)))) -> -38000 | AV47: =AT47+AU47 -> -38000 | AW47: =AW46+AV47 -> -134000 | AX47: =IF(AV47>0,$A47,9999) -> 9999 | AY47: =IF(AW47>0,$A47,9999) -> 9999 | AZ47: =IF($A47-$D$13<Premissas!$B$41,0,$C$13*(Premissas!$B$39+(Premissas!$B$40-Premissas!$B$39)*$A47/36)/(1+EXP(-$K$13*($A47-$D$13-$I$13)))) -> 0 | BA47: =(AZ47*$B$13+IF($A47>=Premissas!$B$46+$D$13,$F$13,0))*(1-$E$13)*(1-Premissas!$B$60) -> 0 | BB47: =-(AZ47*$J$13+MAX(0,AZ47-AZ46)*$H$13+IF($A47-$D$13<=2,Premissas!$B$49,IF($A47-$D$13<=5,Premissas!$B$50,IF($A47-$D$13<=8,Premissas!$B$51,$G$13)))+IF($A47=1+$D$13,Premissas!$B$55,IF($A47=3+$D$13,Premissas!$B$56,IF($A47=6+$D$13,Premissas!$B$57,0)))) -> -5000 | BC47: =BA47+BB47 -> -5000 | BD47: =BD46+BC47 -> -30000 | BE47: =IF(BC47>0,$A47,9999) -> 9999 | BF47: =IF(BD47>0,$A47,9999) -> 9999 | BG47: =IF($A47-$D$14<Premissas!$B$41,0,$C$14*(Premissas!$B$39+(Premissas!$B$40-Premissas!$B$39)*$A47/36)/(1+EXP(-$K$14*($A47-$D$14-$I$14)))) -> 0 | BH47: =(BG47*$B$14+IF($A47>=Premissas!$B$46+$D$14,$F$14,0))*(1-$E$14)*(1-Premissas!$B$60) -> 0 | BI47: =-(BG47*$J$14+MAX(0,BG47-BG46)*$H$14+IF($A47-$D$14<=2,Premissas!$B$49,IF($A47-$D$14<=5,Premissas!$B$50,IF($A47-$D$14<=8,Premissas!$B$51,$G$14)))+IF($A47=1+$D$14,Premissas!$B$55,IF($A47=3+$D$14,Premissas!$B$56,IF($A47=6+$D$14,Premissas!$B$57,0)))) -> -38000 | BJ47: =BH47+BI47 -> -38000 | BK47: =BK46+BJ47 -> -134000 | BL47: =IF(BJ47>0,$A47,9999) -> 9999 | BM47: =IF(BK47>0,$A47,9999) -> 9999 | BN47: =IF($A47-$D$15<Premissas!$B$41,0,$C$15*(Premissas!$B$39+(Premissas!$B$40-Premissas!$B$39)*$A47/36)/(1+EXP(-$K$15*($A47-$D$15-$I$15)))) -> 0 | BO47: =(BN47*$B$15+IF($A47>=Premissas!$B$46+$D$15,$F$15,0))*(1-$E$15)*(1-Premissas!$B$60) -> 0 | BP47: =-(BN47*$J$15+MAX(0,BN47-BN46)*$H$15+IF($A47-$D$15<=2,Premissas!$B$49,IF($A47-$D$15<=5,Premissas!$B$50,IF($A47-$D$15<=8,Premissas!$B$51,$G$15)))+IF($A47=1+$D$15,Premissas!$B$55,IF($A47=3+$D$15,Premissas!$B$56,IF($A47=6+$D$15,Premissas!$B$57,0)))) -> -38000 | BQ47: =BO47+BP47 -> -38000 | BR47: =BR46+BQ47 -> -134000 | BS47: =IF(BQ47>0,$A47,9999) -> 9999 | BT47: =IF(BR47>0,$A47,9999) -> 9999 | BU47: =IF($A47-$D$16<Premissas!$B$41,0,$C$16*(Premissas!$B$39+(Premissas!$B$40-Premissas!$B$39)*$A47/36)/(1+EXP(-$K$16*($A47-$D$16-$I$16)))) -> 0 | BV47: =(BU47*$B$16+IF($A47>=Premissas!$B$46+$D$16,$F$16,0))*(1-$E$16)*(1-Premissas!$B$60) -> 0 | BW47: =-(BU47*$J$16+MAX(0,BU47-BU46)*$H$16+IF($A47-$D$16<=2,Premissas!$B$49,IF($A47-$D$16<=5,Premissas!$B$50,IF($A47-$D$16<=8,Premissas!$B$51,$G$16)))+IF($A47=1+$D$16,Premissas!$B$55,IF($A47=3+$D$16,Premissas!$B$56,IF($A47=6+$D$16,Premissas!$B$57,0)))) -> -38000 | BX47: =BV47+BW47 -> -38000 | BY47: =BY46+BX47 -> -134000 | BZ47: =IF(BX47>0,$A47,9999) -> 9999 | CA47: =IF(BY47>0,$A47,9999) -> 9999 | CB47: =IF($A47-$D$17<Premissas!$B$41,0,$C$17*(Premissas!$B$39+(Premissas!$B$40-Premissas!$B$39)*$A47/36)/(1+EXP(-$K$17*($A47-$D$17-$I$17)))) -> 0 | CC47: =(CB47*$B$17+IF($A47>=Premissas!$B$46+$D$17,$F$17,0))*(1-$E$17)*(1-Premissas!$B$60) -> 0 | CD47: =-(CB47*$J$17+MAX(0,CB47-CB46)*$H$17+IF($A47-$D$17<=2,Premissas!$B$49,IF($A47-$D$17<=5,Premissas!$B$50,IF($A47-$D$17<=8,Premissas!$B$51,$G$17)))+IF($A47=1+$D$17,Premissas!$B$55,IF($A47=3+$D$17,Premissas!$B$56,IF($A47=6+$D$17,Premissas!$B$57,0)))) -> -5000 | CE47: =CC47+CD47 -> -5000 | CF47: =CF46+CE47 -> -30000 | CG47: =IF(CE47>0,$A47,9999) -> 9999 | CH47: =IF(CF47>0,$A47,9999) -> 9999
A48: 7 | C48: =IF($A48-$D$6<Premissas!$B$41,0,$C$6*(Premissas!$B$39+(Premissas!$B$40-Premissas!$B$39)*$A48/36)/(1+EXP(-$K$6*($A48-$D$6-$I$6)))) -> 16.025584 | D48: =(C48*$B$6+IF($A48>=Premissas!$B$46+$D$6,$F$6,0))*(1-$E$6)*(1-Premissas!$B$60) -> 5112.1614 | E48: =-(C48*$J$6+MAX(0,C48-C47)*$H$6+IF($A48-$D$6<=2,Premissas!$B$49,IF($A48-$D$6<=5,Premissas!$B$50,IF($A48-$D$6<=8,Premissas!$B$51,$G$6)))+IF($A48=1+$D$6,Premissas!$B$55,IF($A48=3+$D$6,Premissas!$B$56,IF($A48=6+$D$6,Premissas!$B$57,0)))) -> -35131.385 | F48: =D48+E48 -> -30019.224 | G48: =G47+F48 -> -164019.22 | H48: =IF(F48>0,$A48,9999) -> 9999 | I48: =IF(G48>0,$A48,9999) -> 9999 | J48: =IF($A48-$D$7<Premissas!$B$41,0,$C$7*(Premissas!$B$39+(Premissas!$B$40-Premissas!$B$39)*$A48/36)/(1+EXP(-$K$7*($A48-$D$7-$I$7)))) -> 42.017463 | K48: =(J48*$B$7+IF($A48>=Premissas!$B$46+$D$7,$F$7,0))*(1-$E$7)*(1-Premissas!$B$60) -> 9422.4161 | L48: =-(J48*$J$7+MAX(0,J48-J47)*$H$7+IF($A48-$D$7<=2,Premissas!$B$49,IF($A48-$D$7<=5,Premissas!$B$50,IF($A48-$D$7<=8,Premissas!$B$51,$G$7)))+IF($A48=1+$D$7,Premissas!$B$55,IF($A48=3+$D$7,Premissas!$B$56,IF($A48=6+$D$7,Premissas!$B$57,0)))) -> -31865.607 | M48: =K48+L48 -> -22443.19 | N48: =N47+M48 -> -156443.19 | O48: =IF(M48>0,$A48,9999) -> 9999 | P48: =IF(N48>0,$A48,9999) -> 9999 | Q48: =IF($A48-$D$8<Premissas!$B$41,0,$C$8*(Premissas!$B$39+(Premissas!$B$40-Premissas!$B$39)*$A48/36)/(1+EXP(-$K$8*($A48-$D$8-$I$8)))) -> 42.017463 | R48: =(Q48*$B$8+IF($A48>=Premissas!$B$46+$D$8,$F$8,0))*(1-$E$8)*(1-Premissas!$B$60) -> 12563.222 | S48: =-(Q48*$J$8+MAX(0,Q48-Q47)*$H$8+IF($A48-$D$8<=2,Premissas!$B$49,IF($A48-$D$8<=5,Premissas!$B$50,IF($A48-$D$8<=8,Premissas!$B$51,$G$8)))+IF($A48=1+$D$8,Premissas!$B$55,IF($A48=3+$D$8,Premissas!$B$56,IF($A48=6+$D$8,Premissas!$B$57,0)))) -> -31865.607 | T48: =R48+S48 -> -19302.385 | U48: =U47+T48 -> -153302.39 | V48: =IF(T48>0,$A48,9999) -> 9999 | W48: =IF(U48>0,$A48,9999) -> 9999 | X48: =IF($A48-$D$9<Premissas!$B$41,0,$C$9*(Premissas!$B$39+(Premissas!$B$40-Premissas!$B$39)*$A48/36)/(1+EXP(-$K$9*($A48-$D$9-$I$9)))) -> 42.017463 | Y48: =(X48*$B$9+IF($A48>=Premissas!$B$46+$D$9,$F$9,0))*(1-$E$9)*(1-Premissas!$B$60) -> 10050.577 | Z48: =-(X48*$J$9+MAX(0,X48-X47)*$H$9+IF($A48-$D$9<=2,Premissas!$B$49,IF($A48-$D$9<=5,Premissas!$B$50,IF($A48-$D$9<=8,Premissas!$B$51,$G$9)))+IF($A48=1+$D$9,Premissas!$B$55,IF($A48=3+$D$9,Premissas!$B$56,IF($A48=6+$D$9,Premissas!$B$57,0)))) -> -31865.607 | AA48: =Y48+Z48 -> -21815.029 | AB48: =AB47+AA48 -> -155815.03 | AC48: =IF(AA48>0,$A48,9999) -> 9999 | AD48: =IF(AB48>0,$A48,9999) -> 9999 | AE48: =IF($A48-$D$10<Premissas!$B$41,0,$C$10*(Premissas!$B$39+(Premissas!$B$40-Premissas!$B$39)*$A48/36)/(1+EXP(-$K$10*($A48-$D$10-$I$10)))) -> 42.017463 | AF48: =(AE48*$B$10+IF($A48>=Premissas!$B$46+$D$10,$F$10,0))*(1-$E$10)*(1-Premissas!$B$60) -> 8794.2551 | AG48: =-(AE48*$J$10+MAX(0,AE48-AE47)*$H$10+IF($A48-$D$10<=2,Premissas!$B$49,IF($A48-$D$10<=5,Premissas!$B$50,IF($A48-$D$10<=8,Premissas!$B$51,$G$10)))+IF($A48=1+$D$10,Premissas!$B$55,IF($A48=3+$D$10,Premissas!$B$56,IF($A48=6+$D$10,Premissas!$B$57,0)))) -> -31865.607 | AH48: =AF48+AG48 -> -23071.352 | AI48: =AI47+AH48 -> -157071.35 | AJ48: =IF(AH48>0,$A48,9999) -> 9999 | AK48: =IF(AI48>0,$A48,9999) -> 9999 | AL48: =IF($A48-$D$11<Premissas!$B$41,0,$C$11*(Premissas!$B$39+(Premissas!$B$40-Premissas!$B$39)*$A48/36)/(1+EXP(-$K$11*($A48-$D$11-$I$11)))) -> 42.017463 | AM48: =(AL48*$B$11+IF($A48>=Premissas!$B$46+$D$11,$F$11,0))*(1-$E$11)*(1-Premissas!$B$60) -> 7537.9329 | AN48: =-(AL48*$J$11+MAX(0,AL48-AL47)*$H$11+IF($A48-$D$11<=2,Premissas!$B$49,IF($A48-$D$11<=5,Premissas!$B$50,IF($A48-$D$11<=8,Premissas!$B$51,$G$11)))+IF($A48=1+$D$11,Premissas!$B$55,IF($A48=3+$D$11,Premissas!$B$56,IF($A48=6+$D$11,Premissas!$B$57,0)))) -> -31865.607 | AO48: =AM48+AN48 -> -24327.674 | AP48: =AP47+AO48 -> -158327.67 | AQ48: =IF(AO48>0,$A48,9999) -> 9999 | AR48: =IF(AP48>0,$A48,9999) -> 9999 | AS48: =IF($A48-$D$12<Premissas!$B$41,0,$C$12*(Premissas!$B$39+(Premissas!$B$40-Premissas!$B$39)*$A48/36)/(1+EXP(-$K$12*($A48-$D$12-$I$12)))) -> 42.017463 | AT48: =(AS48*$B$12+IF($A48>=Premissas!$B$46+$D$12,$F$12,0))*(1-$E$12)*(1-Premissas!$B$60) -> 7846.7613 | AU48: =-(AS48*$J$12+MAX(0,AS48-AS47)*$H$12+IF($A48-$D$12<=2,Premissas!$B$49,IF($A48-$D$12<=5,Premissas!$B$50,IF($A48-$D$12<=8,Premissas!$B$51,$G$12)))+IF($A48=1+$D$12,Premissas!$B$55,IF($A48=3+$D$12,Premissas!$B$56,IF($A48=6+$D$12,Premissas!$B$57,0)))) -> -31865.607 | AV48: =AT48+AU48 -> -24018.845 | AW48: =AW47+AV48 -> -158018.85 | AX48: =IF(AV48>0,$A48,9999) -> 9999 | AY48: =IF(AW48>0,$A48,9999) -> 9999 | AZ48: =IF($A48-$D$13<Premissas!$B$41,0,$C$13*(Premissas!$B$39+(Premissas!$B$40-Premissas!$B$39)*$A48/36)/(1+EXP(-$K$13*($A48-$D$13-$I$13)))) -> 0 | BA48: =(AZ48*$B$13+IF($A48>=Premissas!$B$46+$D$13,$F$13,0))*(1-$E$13)*(1-Premissas!$B$60) -> 0 | BB48: =-(AZ48*$J$13+MAX(0,AZ48-AZ47)*$H$13+IF($A48-$D$13<=2,Premissas!$B$49,IF($A48-$D$13<=5,Premissas!$B$50,IF($A48-$D$13<=8,Premissas!$B$51,$G$13)))+IF($A48=1+$D$13,Premissas!$B$55,IF($A48=3+$D$13,Premissas!$B$56,IF($A48=6+$D$13,Premissas!$B$57,0)))) -> -13000 | BC48: =BA48+BB48 -> -13000 | BD48: =BD47+BC48 -> -43000 | BE48: =IF(BC48>0,$A48,9999) -> 9999 | BF48: =IF(BD48>0,$A48,9999) -> 9999 | BG48: =IF($A48-$D$14<Premissas!$B$41,0,$C$14*(Premissas!$B$39+(Premissas!$B$40-Premissas!$B$39)*$A48/36)/(1+EXP(-$K$14*($A48-$D$14-$I$14)))) -> 42.017463 | BH48: =(BG48*$B$14+IF($A48>=Premissas!$B$46+$D$14,$F$14,0))*(1-$E$14)*(1-Premissas!$B$60) -> 9422.4161 | BI48: =-(BG48*$J$14+MAX(0,BG48-BG47)*$H$14+IF($A48-$D$14<=2,Premissas!$B$49,IF($A48-$D$14<=5,Premissas!$B$50,IF($A48-$D$14<=8,Premissas!$B$51,$G$14)))+IF($A48=1+$D$14,Premissas!$B$55,IF($A48=3+$D$14,Premissas!$B$56,IF($A48=6+$D$14,Premissas!$B$57,0)))) -> -31865.607 | BJ48: =BH48+BI48 -> -22443.19 | BK48: =BK47+BJ48 -> -156443.19 | BL48: =IF(BJ48>0,$A48,9999) -> 9999 | BM48: =IF(BK48>0,$A48,9999) -> 9999 | BN48: =IF($A48-$D$15<Premissas!$B$41,0,$C$15*(Premissas!$B$39+(Premissas!$B$40-Premissas!$B$39)*$A48/36)/(1+EXP(-$K$15*($A48-$D$15-$I$15)))) -> 8.0127922 | BO48: =(BN48*$B$15+IF($A48>=Premissas!$B$46+$D$15,$F$15,0))*(1-$E$15)*(1-Premissas!$B$60) -> 2556.0807 | BP48: =-(BN48*$J$15+MAX(0,BN48-BN47)*$H$15+IF($A48-$D$15<=2,Premissas!$B$49,IF($A48-$D$15<=5,Premissas!$B$50,IF($A48-$D$15<=8,Premissas!$B$51,$G$15)))+IF($A48=1+$D$15,Premissas!$B$55,IF($A48=3+$D$15,Premissas!$B$56,IF($A48=6+$D$15,Premissas!$B$57,0)))) -> -31565.693 | BQ48: =BO48+BP48 -> -29009.612 | BR48: =BR47+BQ48 -> -163009.61 | BS48: =IF(BQ48>0,$A48,9999) -> 9999 | BT48: =IF(BR48>0,$A48,9999) -> 9999 | BU48: =IF($A48-$D$16<Premissas!$B$41,0,$C$16*(Premissas!$B$39+(Premissas!$B$40-Premissas!$B$39)*$A48/36)/(1+EXP(-$K$16*($A48-$D$16-$I$16)))) -> 16.025584 | BV48: =(BU48*$B$16+IF($A48>=Premissas!$B$46+$D$16,$F$16,0))*(1-$E$16)*(1-Premissas!$B$60) -> 3322.9049 | BW48: =-(BU48*$J$16+MAX(0,BU48-BU47)*$H$16+IF($A48-$D$16<=2,Premissas!$B$49,IF($A48-$D$16<=5,Premissas!$B$50,IF($A48-$D$16<=8,Premissas!$B$51,$G$16)))+IF($A48=1+$D$16,Premissas!$B$55,IF($A48=3+$D$16,Premissas!$B$56,IF($A48=6+$D$16,Premissas!$B$57,0)))) -> -35131.385 | BX48: =BV48+BW48 -> -31808.48 | BY48: =BY47+BX48 -> -165808.48 | BZ48: =IF(BX48>0,$A48,9999) -> 9999 | CA48: =IF(BY48>0,$A48,9999) -> 9999 | CB48: =IF($A48-$D$17<Premissas!$B$41,0,$C$17*(Premissas!$B$39+(Premissas!$B$40-Premissas!$B$39)*$A48/36)/(1+EXP(-$K$17*($A48-$D$17-$I$17)))) -> 0 | CC48: =(CB48*$B$17+IF($A48>=Premissas!$B$46+$D$17,$F$17,0))*(1-$E$17)*(1-Premissas!$B$60) -> 0 | CD48: =-(CB48*$J$17+MAX(0,CB48-CB47)*$H$17+IF($A48-$D$17<=2,Premissas!$B$49,IF($A48-$D$17<=5,Premissas!$B$50,IF($A48-$D$17<=8,Premissas!$B$51,$G$17)))+IF($A48=1+$D$17,Premissas!$B$55,IF($A48=3+$D$17,Premissas!$B$56,IF($A48=6+$D$17,Premissas!$B$57,0)))) -> -13000 | CE48: =CC48+CD48 -> -13000 | CF48: =CF47+CE48 -> -43000 | CG48: =IF(CE48>0,$A48,9999) -> 9999 | CH48: =IF(CF48>0,$A48,9999) -> 9999
A49: 8 | C49: =IF($A49-$D$6<Premissas!$B$41,0,$C$6*(Premissas!$B$39+(Premissas!$B$40-Premissas!$B$39)*$A49/36)/(1+EXP(-$K$6*($A49-$D$6-$I$6)))) -> 21.854557 | D49: =(C49*$B$6+IF($A49>=Premissas!$B$46+$D$6,$F$6,0))*(1-$E$6)*(1-Premissas!$B$60) -> 6971.6036 | E49: =-(C49*$J$6+MAX(0,C49-C48)*$H$6+IF($A49-$D$6<=2,Premissas!$B$49,IF($A49-$D$6<=5,Premissas!$B$50,IF($A49-$D$6<=8,Premissas!$B$51,$G$6)))+IF($A49=1+$D$6,Premissas!$B$55,IF($A49=3+$D$6,Premissas!$B$56,IF($A49=6+$D$6,Premissas!$B$57,0)))) -> -31315.044 | F49: =D49+E49 -> -24343.44 | G49: =G48+F49 -> -188362.66 | H49: =IF(F49>0,$A49,9999) -> 9999 | I49: =IF(G49>0,$A49,9999) -> 9999 | J49: =IF($A49-$D$7<Premissas!$B$41,0,$C$7*(Premissas!$B$39+(Premissas!$B$40-Premissas!$B$39)*$A49/36)/(1+EXP(-$K$7*($A49-$D$7-$I$7)))) -> 63.141849 | K49: =(J49*$B$7+IF($A49>=Premissas!$B$46+$D$7,$F$7,0))*(1-$E$7)*(1-Premissas!$B$60) -> 14159.56 | L49: =-(J49*$J$7+MAX(0,J49-J48)*$H$7+IF($A49-$D$7<=2,Premissas!$B$49,IF($A49-$D$7<=5,Premissas!$B$50,IF($A49-$D$7<=8,Premissas!$B$51,$G$7)))+IF($A49=1+$D$7,Premissas!$B$55,IF($A49=3+$D$7,Premissas!$B$56,IF($A49=6+$D$7,Premissas!$B$57,0)))) -> -31708.177 | M49: =K49+L49 -> -17548.617 | N49: =N48+M49 -> -173991.81 | O49: =IF(M49>0,$A49,9999) -> 9999 | P49: =IF(N49>0,$A49,9999) -> 9999 | Q49: =IF($A49-$D$8<Premissas!$B$41,0,$C$8*(Premissas!$B$39+(Premissas!$B$40-Premissas!$B$39)*$A49/36)/(1+EXP(-$K$8*($A49-$D$8-$I$8)))) -> 63.141849 | R49: =(Q49*$B$8+IF($A49>=Premissas!$B$46+$D$8,$F$8,0))*(1-$E$8)*(1-Premissas!$B$60) -> 18879.413 | S49: =-(Q49*$J$8+MAX(0,Q49-Q48)*$H$8+IF($A49-$D$8<=2,Premissas!$B$49,IF($A49-$D$8<=5,Premissas!$B$50,IF($A49-$D$8<=8,Premissas!$B$51,$G$8)))+IF($A49=1+$D$8,Premissas!$B$55,IF($A49=3+$D$8,Premissas!$B$56,IF($A49=6+$D$8,Premissas!$B$57,0)))) -> -31708.177 | T49: =R49+S49 -> -12828.764 | U49: =U48+T49 -> -166131.15 | V49: =IF(T49>0,$A49,9999) -> 9999 | W49: =IF(U49>0,$A49,9999) -> 9999 | X49: =IF($A49-$D$9<Premissas!$B$41,0,$C$9*(Premissas!$B$39+(Premissas!$B$40-Premissas!$B$39)*$A49/36)/(1+EXP(-$K$9*($A49-$D$9-$I$9)))) -> 63.141849 | Y49: =(X49*$B$9+IF($A49>=Premissas!$B$46+$D$9,$F$9,0))*(1-$E$9)*(1-Premissas!$B$60) -> 15103.53 | Z49: =-(X49*$J$9+MAX(0,X49-X48)*$H$9+IF($A49-$D$9<=2,Premissas!$B$49,IF($A49-$D$9<=5,Premissas!$B$50,IF($A49-$D$9<=8,Premissas!$B$51,$G$9)))+IF($A49=1+$D$9,Premissas!$B$55,IF($A49=3+$D$9,Premissas!$B$56,IF($A49=6+$D$9,Premissas!$B$57,0)))) -> -31708.177 | AA49: =Y49+Z49 -> -16604.647 | AB49: =AB48+AA49 -> -172419.68 | AC49: =IF(AA49>0,$A49,9999) -> 9999 | AD49: =IF(AB49>0,$A49,9999) -> 9999 | AE49: =IF($A49-$D$10<Premissas!$B$41,0,$C$10*(Premissas!$B$39+(Premissas!$B$40-Premissas!$B$39)*$A49/36)/(1+EXP(-$K$10*($A49-$D$10-$I$10)))) -> 63.141849 | AF49: =(AE49*$B$10+IF($A49>=Premissas!$B$46+$D$10,$F$10,0))*(1-$E$10)*(1-Premissas!$B$60) -> 13215.589 | AG49: =-(AE49*$J$10+MAX(0,AE49-AE48)*$H$10+IF($A49-$D$10<=2,Premissas!$B$49,IF($A49-$D$10<=5,Premissas!$B$50,IF($A49-$D$10<=8,Premissas!$B$51,$G$10)))+IF($A49=1+$D$10,Premissas!$B$55,IF($A49=3+$D$10,Premissas!$B$56,IF($A49=6+$D$10,Premissas!$B$57,0)))) -> -31708.177 | AH49: =AF49+AG49 -> -18492.588 | AI49: =AI48+AH49 -> -175563.94 | AJ49: =IF(AH49>0,$A49,9999) -> 9999 | AK49: =IF(AI49>0,$A49,9999) -> 9999 | AL49: =IF($A49-$D$11<Premissas!$B$41,0,$C$11*(Premissas!$B$39+(Premissas!$B$40-Premissas!$B$39)*$A49/36)/(1+EXP(-$K$11*($A49-$D$11-$I$11)))) -> 63.141849 | AM49: =(AL49*$B$11+IF($A49>=Premissas!$B$46+$D$11,$F$11,0))*(1-$E$11)*(1-Premissas!$B$60) -> 11327.648 | AN49: =-(AL49*$J$11+MAX(0,AL49-AL48)*$H$11+IF($A49-$D$11<=2,Premissas!$B$49,IF($A49-$D$11<=5,Premissas!$B$50,IF($A49-$D$11<=8,Premissas!$B$51,$G$11)))+IF($A49=1+$D$11,Premissas!$B$55,IF($A49=3+$D$11,Premissas!$B$56,IF($A49=6+$D$11,Premissas!$B$57,0)))) -> -31708.177 | AO49: =AM49+AN49 -> -20380.529 | AP49: =AP48+AO49 -> -178708.2 | AQ49: =IF(AO49>0,$A49,9999) -> 9999 | AR49: =IF(AP49>0,$A49,9999) -> 9999 | AS49: =IF($A49-$D$12<Premissas!$B$41,0,$C$12*(Premissas!$B$39+(Premissas!$B$40-Premissas!$B$39)*$A49/36)/(1+EXP(-$K$12*($A49-$D$12-$I$12)))) -> 63.141849 | AT49: =(AS49*$B$12+IF($A49>=Premissas!$B$46+$D$12,$F$12,0))*(1-$E$12)*(1-Premissas!$B$60) -> 11791.74 | AU49: =-(AS49*$J$12+MAX(0,AS49-AS48)*$H$12+IF($A49-$D$12<=2,Premissas!$B$49,IF($A49-$D$12<=5,Premissas!$B$50,IF($A49-$D$12<=8,Premissas!$B$51,$G$12)))+IF($A49=1+$D$12,Premissas!$B$55,IF($A49=3+$D$12,Premissas!$B$56,IF($A49=6+$D$12,Premissas!$B$57,0)))) -> -31708.177 | AV49: =AT49+AU49 -> -19916.437 | AW49: =AW48+AV49 -> -177935.28 | AX49: =IF(AV49>0,$A49,9999) -> 9999 | AY49: =IF(AW49>0,$A49,9999) -> 9999 | AZ49: =IF($A49-$D$13<Premissas!$B$41,0,$C$13*(Premissas!$B$39+(Premissas!$B$40-Premissas!$B$39)*$A49/36)/(1+EXP(-$K$13*($A49-$D$13-$I$13)))) -> 0 | BA49: =(AZ49*$B$13+IF($A49>=Premissas!$B$46+$D$13,$F$13,0))*(1-$E$13)*(1-Premissas!$B$60) -> 0 | BB49: =-(AZ49*$J$13+MAX(0,AZ49-AZ48)*$H$13+IF($A49-$D$13<=2,Premissas!$B$49,IF($A49-$D$13<=5,Premissas!$B$50,IF($A49-$D$13<=8,Premissas!$B$51,$G$13)))+IF($A49=1+$D$13,Premissas!$B$55,IF($A49=3+$D$13,Premissas!$B$56,IF($A49=6+$D$13,Premissas!$B$57,0)))) -> -5000 | BC49: =BA49+BB49 -> -5000 | BD49: =BD48+BC49 -> -48000 | BE49: =IF(BC49>0,$A49,9999) -> 9999 | BF49: =IF(BD49>0,$A49,9999) -> 9999 | BG49: =IF($A49-$D$14<Premissas!$B$41,0,$C$14*(Premissas!$B$39+(Premissas!$B$40-Premissas!$B$39)*$A49/36)/(1+EXP(-$K$14*($A49-$D$14-$I$14)))) -> 63.141849 | BH49: =(BG49*$B$14+IF($A49>=Premissas!$B$46+$D$14,$F$14,0))*(1-$E$14)*(1-Premissas!$B$60) -> 14159.56 | BI49: =-(BG49*$J$14+MAX(0,BG49-BG48)*$H$14+IF($A49-$D$14<=2,Premissas!$B$49,IF($A49-$D$14<=5,Premissas!$B$50,IF($A49-$D$14<=8,Premissas!$B$51,$G$14)))+IF($A49=1+$D$14,Premissas!$B$55,IF($A49=3+$D$14,Premissas!$B$56,IF($A49=6+$D$14,Premissas!$B$57,0)))) -> -31708.177 | BJ49: =BH49+BI49 -> -17548.617 | BK49: =BK48+BJ49 -> -173991.81 | BL49: =IF(BJ49>0,$A49,9999) -> 9999 | BM49: =IF(BK49>0,$A49,9999) -> 9999 | BN49: =IF($A49-$D$15<Premissas!$B$41,0,$C$15*(Premissas!$B$39+(Premissas!$B$40-Premissas!$B$39)*$A49/36)/(1+EXP(-$K$15*($A49-$D$15-$I$15)))) -> 10.927278 | BO49: =(BN49*$B$15+IF($A49>=Premissas!$B$46+$D$15,$F$15,0))*(1-$E$15)*(1-Premissas!$B$60) -> 3485.8018 | BP49: =-(BN49*$J$15+MAX(0,BN49-BN48)*$H$15+IF($A49-$D$15<=2,Premissas!$B$49,IF($A49-$D$15<=5,Premissas!$B$50,IF($A49-$D$15<=8,Premissas!$B$51,$G$15)))+IF($A49=1+$D$15,Premissas!$B$55,IF($A49=3+$D$15,Premissas!$B$56,IF($A49=6+$D$15,Premissas!$B$57,0)))) -> -29657.522 | BQ49: =BO49+BP49 -> -26171.72 | BR49: =BR48+BQ49 -> -189181.33 | BS49: =IF(BQ49>0,$A49,9999) -> 9999 | BT49: =IF(BR49>0,$A49,9999) -> 9999 | BU49: =IF($A49-$D$16<Premissas!$B$41,0,$C$16*(Premissas!$B$39+(Premissas!$B$40-Premissas!$B$39)*$A49/36)/(1+EXP(-$K$16*($A49-$D$16-$I$16)))) -> 21.854557 | BV49: =(BU49*$B$16+IF($A49>=Premissas!$B$46+$D$16,$F$16,0))*(1-$E$16)*(1-Premissas!$B$60) -> 4531.5424 | BW49: =-(BU49*$J$16+MAX(0,BU49-BU48)*$H$16+IF($A49-$D$16<=2,Premissas!$B$49,IF($A49-$D$16<=5,Premissas!$B$50,IF($A49-$D$16<=8,Premissas!$B$51,$G$16)))+IF($A49=1+$D$16,Premissas!$B$55,IF($A49=3+$D$16,Premissas!$B$56,IF($A49=6+$D$16,Premissas!$B$57,0)))) -> -31315.044 | BX49: =BV49+BW49 -> -26783.502 | BY49: =BY48+BX49 -> -192591.98 | BZ49: =IF(BX49>0,$A49,9999) -> 9999 | CA49: =IF(BY49>0,$A49,9999) -> 9999 | CB49: =IF($A49-$D$17<Premissas!$B$41,0,$C$17*(Premissas!$B$39+(Premissas!$B$40-Premissas!$B$39)*$A49/36)/(1+EXP(-$K$17*($A49-$D$17-$I$17)))) -> 0 | CC49: =(CB49*$B$17+IF($A49>=Premissas!$B$46+$D$17,$F$17,0))*(1-$E$17)*(1-Premissas!$B$60) -> 0 | CD49: =-(CB49*$J$17+MAX(0,CB49-CB48)*$H$17+IF($A49-$D$17<=2,Premissas!$B$49,IF($A49-$D$17<=5,Premissas!$B$50,IF($A49-$D$17<=8,Premissas!$B$51,$G$17)))+IF($A49=1+$D$17,Premissas!$B$55,IF($A49=3+$D$17,Premissas!$B$56,IF($A49=6+$D$17,Premissas!$B$57,0)))) -> -5000 | CE49: =CC49+CD49 -> -5000 | CF49: =CF48+CE49 -> -48000 | CG49: =IF(CE49>0,$A49,9999) -> 9999 | CH49: =IF(CF49>0,$A49,9999) -> 9999
A50: 9 | C50: =IF($A50-$D$6<Premissas!$B$41,0,$C$6*(Premissas!$B$39+(Premissas!$B$40-Premissas!$B$39)*$A50/36)/(1+EXP(-$K$6*($A50-$D$6-$I$6)))) -> 29.597103 | D50: =(C50*$B$6+IF($A50>=Premissas!$B$46+$D$6,$F$6,0))*(1-$E$6)*(1-Premissas!$B$60) -> 19441.476 | E50: =-(C50*$J$6+MAX(0,C50-C49)*$H$6+IF($A50-$D$6<=2,Premissas!$B$49,IF($A50-$D$6<=5,Premissas!$B$50,IF($A50-$D$6<=8,Premissas!$B$51,$G$6)))+IF($A50=1+$D$6,Premissas!$B$55,IF($A50=3+$D$6,Premissas!$B$56,IF($A50=6+$D$6,Premissas!$B$57,0)))) -> -39428.888 | F50: =D50+E50 -> -19987.412 | G50: =G49+F50 -> -208350.08 | H50: =IF(F50>0,$A50,9999) -> 9999 | I50: =IF(G50>0,$A50,9999) -> 9999 | J50: =IF($A50-$D$7<Premissas!$B$41,0,$C$7*(Premissas!$B$39+(Premissas!$B$40-Premissas!$B$39)*$A50/36)/(1+EXP(-$K$7*($A50-$D$7-$I$7)))) -> 92.556746 | K50: =(J50*$B$7+IF($A50>=Premissas!$B$46+$D$7,$F$7,0))*(1-$E$7)*(1-Premissas!$B$60) -> 28255.85 | L50: =-(J50*$J$7+MAX(0,J50-J49)*$H$7+IF($A50-$D$7<=2,Premissas!$B$49,IF($A50-$D$7<=5,Premissas!$B$50,IF($A50-$D$7<=8,Premissas!$B$51,$G$7)))+IF($A50=1+$D$7,Premissas!$B$55,IF($A50=3+$D$7,Premissas!$B$56,IF($A50=6+$D$7,Premissas!$B$57,0)))) -> -40358.128 | M50: =K50+L50 -> -12102.278 | N50: =N49+M50 -> -186094.09 | O50: =IF(M50>0,$A50,9999) -> 9999 | P50: =IF(N50>0,$A50,9999) -> 9999 | Q50: =IF($A50-$D$8<Premissas!$B$41,0,$C$8*(Premissas!$B$39+(Premissas!$B$40-Premissas!$B$39)*$A50/36)/(1+EXP(-$K$8*($A50-$D$8-$I$8)))) -> 92.556746 | R50: =(Q50*$B$8+IF($A50>=Premissas!$B$46+$D$8,$F$8,0))*(1-$E$8)*(1-Premissas!$B$60) -> 37674.467 | S50: =-(Q50*$J$8+MAX(0,Q50-Q49)*$H$8+IF($A50-$D$8<=2,Premissas!$B$49,IF($A50-$D$8<=5,Premissas!$B$50,IF($A50-$D$8<=8,Premissas!$B$51,$G$8)))+IF($A50=1+$D$8,Premissas!$B$55,IF($A50=3+$D$8,Premissas!$B$56,IF($A50=6+$D$8,Premissas!$B$57,0)))) -> -40358.128 | T50: =R50+S50 -> -2683.6612 | U50: =U49+T50 -> -168814.81 | V50: =IF(T50>0,$A50,9999) -> 9999 | W50: =IF(U50>0,$A50,9999) -> 9999 | X50: =IF($A50-$D$9<Premissas!$B$41,0,$C$9*(Premissas!$B$39+(Premissas!$B$40-Premissas!$B$39)*$A50/36)/(1+EXP(-$K$9*($A50-$D$9-$I$9)))) -> 92.556746 | Y50: =(X50*$B$9+IF($A50>=Premissas!$B$46+$D$9,$F$9,0))*(1-$E$9)*(1-Premissas!$B$60) -> 30139.574 | Z50: =-(X50*$J$9+MAX(0,X50-X49)*$H$9+IF($A50-$D$9<=2,Premissas!$B$49,IF($A50-$D$9<=5,Premissas!$B$50,IF($A50-$D$9<=8,Premissas!$B$51,$G$9)))+IF($A50=1+$D$9,Premissas!$B$55,IF($A50=3+$D$9,Premissas!$B$56,IF($A50=6+$D$9,Premissas!$B$57,0)))) -> -40358.128 | AA50: =Y50+Z50 -> -10218.555 | AB50: =AB49+AA50 -> -182638.23 | AC50: =IF(AA50>0,$A50,9999) -> 9999 | AD50: =IF(AB50>0,$A50,9999) -> 9999 | AE50: =IF($A50-$D$10<Premissas!$B$41,0,$C$10*(Premissas!$B$39+(Premissas!$B$40-Premissas!$B$39)*$A50/36)/(1+EXP(-$K$10*($A50-$D$10-$I$10)))) -> 92.556746 | AF50: =(AE50*$B$10+IF($A50>=Premissas!$B$46+$D$10,$F$10,0))*(1-$E$10)*(1-Premissas!$B$60) -> 26372.127 | AG50: =-(AE50*$J$10+MAX(0,AE50-AE49)*$H$10+IF($A50-$D$10<=2,Premissas!$B$49,IF($A50-$D$10<=5,Premissas!$B$50,IF($A50-$D$10<=8,Premissas!$B$51,$G$10)))+IF($A50=1+$D$10,Premissas!$B$55,IF($A50=3+$D$10,Premissas!$B$56,IF($A50=6+$D$10,Premissas!$B$57,0)))) -> -40358.128 | AH50: =AF50+AG50 -> -13986.001 | AI50: =AI49+AH50 -> -189549.94 | AJ50: =IF(AH50>0,$A50,9999) -> 9999 | AK50: =IF(AI50>0,$A50,9999) -> 9999 | AL50: =IF($A50-$D$11<Premissas!$B$41,0,$C$11*(Premissas!$B$39+(Premissas!$B$40-Premissas!$B$39)*$A50/36)/(1+EXP(-$K$11*($A50-$D$11-$I$11)))) -> 92.556746 | AM50: =(AL50*$B$11+IF($A50>=Premissas!$B$46+$D$11,$F$11,0))*(1-$E$11)*(1-Premissas!$B$60) -> 22604.68 | AN50: =-(AL50*$J$11+MAX(0,AL50-AL49)*$H$11+IF($A50-$D$11<=2,Premissas!$B$49,IF($A50-$D$11<=5,Premissas!$B$50,IF($A50-$D$11<=8,Premissas!$B$51,$G$11)))+IF($A50=1+$D$11,Premissas!$B$55,IF($A50=3+$D$11,Premissas!$B$56,IF($A50=6+$D$11,Premissas!$B$57,0)))) -> -40358.128 | AO50: =AM50+AN50 -> -17753.448 | AP50: =AP49+AO50 -> -196461.65 | AQ50: =IF(AO50>0,$A50,9999) -> 9999 | AR50: =IF(AP50>0,$A50,9999) -> 9999 | AS50: =IF($A50-$D$12<Premissas!$B$41,0,$C$12*(Premissas!$B$39+(Premissas!$B$40-Premissas!$B$39)*$A50/36)/(1+EXP(-$K$12*($A50-$D$12-$I$12)))) -> 92.556746 | AT50: =(AS50*$B$12+IF($A50>=Premissas!$B$46+$D$12,$F$12,0))*(1-$E$12)*(1-Premissas!$B$60) -> 24784.972 | AU50: =-(AS50*$J$12+MAX(0,AS50-AS49)*$H$12+IF($A50-$D$12<=2,Premissas!$B$49,IF($A50-$D$12<=5,Premissas!$B$50,IF($A50-$D$12<=8,Premissas!$B$51,$G$12)))+IF($A50=1+$D$12,Premissas!$B$55,IF($A50=3+$D$12,Premissas!$B$56,IF($A50=6+$D$12,Premissas!$B$57,0)))) -> -40358.128 | AV50: =AT50+AU50 -> -15573.156 | AW50: =AW49+AV50 -> -193508.44 | AX50: =IF(AV50>0,$A50,9999) -> 9999 | AY50: =IF(AW50>0,$A50,9999) -> 9999 | AZ50: =IF($A50-$D$13<Premissas!$B$41,0,$C$13*(Premissas!$B$39+(Premissas!$B$40-Premissas!$B$39)*$A50/36)/(1+EXP(-$K$13*($A50-$D$13-$I$13)))) -> 0 | BA50: =(AZ50*$B$13+IF($A50>=Premissas!$B$46+$D$13,$F$13,0))*(1-$E$13)*(1-Premissas!$B$60) -> 0 | BB50: =-(AZ50*$J$13+MAX(0,AZ50-AZ49)*$H$13+IF($A50-$D$13<=2,Premissas!$B$49,IF($A50-$D$13<=5,Premissas!$B$50,IF($A50-$D$13<=8,Premissas!$B$51,$G$13)))+IF($A50=1+$D$13,Premissas!$B$55,IF($A50=3+$D$13,Premissas!$B$56,IF($A50=6+$D$13,Premissas!$B$57,0)))) -> -34000 | BC50: =BA50+BB50 -> -34000 | BD50: =BD49+BC50 -> -82000 | BE50: =IF(BC50>0,$A50,9999) -> 9999 | BF50: =IF(BD50>0,$A50,9999) -> 9999 | BG50: =IF($A50-$D$14<Premissas!$B$41,0,$C$14*(Premissas!$B$39+(Premissas!$B$40-Premissas!$B$39)*$A50/36)/(1+EXP(-$K$14*($A50-$D$14-$I$14)))) -> 92.556746 | BH50: =(BG50*$B$14+IF($A50>=Premissas!$B$46+$D$14,$F$14,0))*(1-$E$14)*(1-Premissas!$B$60) -> 28255.85 | BI50: =-(BG50*$J$14+MAX(0,BG50-BG49)*$H$14+IF($A50-$D$14<=2,Premissas!$B$49,IF($A50-$D$14<=5,Premissas!$B$50,IF($A50-$D$14<=8,Premissas!$B$51,$G$14)))+IF($A50=1+$D$14,Premissas!$B$55,IF($A50=3+$D$14,Premissas!$B$56,IF($A50=6+$D$14,Premissas!$B$57,0)))) -> -30358.128 | BJ50: =BH50+BI50 -> -2102.2779 | BK50: =BK49+BJ50 -> -176094.09 | BL50: =IF(BJ50>0,$A50,9999) -> 9999 | BM50: =IF(BK50>0,$A50,9999) -> 9999 | BN50: =IF($A50-$D$15<Premissas!$B$41,0,$C$15*(Premissas!$B$39+(Premissas!$B$40-Premissas!$B$39)*$A50/36)/(1+EXP(-$K$15*($A50-$D$15-$I$15)))) -> 14.798552 | BO50: =(BN50*$B$15+IF($A50>=Premissas!$B$46+$D$15,$F$15,0))*(1-$E$15)*(1-Premissas!$B$60) -> 14720.738 | BP50: =-(BN50*$J$15+MAX(0,BN50-BN49)*$H$15+IF($A50-$D$15<=2,Premissas!$B$49,IF($A50-$D$15<=5,Premissas!$B$50,IF($A50-$D$15<=8,Premissas!$B$51,$G$15)))+IF($A50=1+$D$15,Premissas!$B$55,IF($A50=3+$D$15,Premissas!$B$56,IF($A50=6+$D$15,Premissas!$B$57,0)))) -> -37214.444 | BQ50: =BO50+BP50 -> -22493.706 | BR50: =BR49+BQ50 -> -211675.04 | BS50: =IF(BQ50>0,$A50,9999) -> 9999 | BT50: =IF(BR50>0,$A50,9999) -> 9999 | BU50: =IF($A50-$D$16<Premissas!$B$41,0,$C$16*(Premissas!$B$39+(Premissas!$B$40-Premissas!$B$39)*$A50/36)/(1+EXP(-$K$16*($A50-$D$16-$I$16)))) -> 29.597103 | BV50: =(BU50*$B$16+IF($A50>=Premissas!$B$46+$D$16,$F$16,0))*(1-$E$16)*(1-Premissas!$B$60) -> 12636.959 | BW50: =-(BU50*$J$16+MAX(0,BU50-BU49)*$H$16+IF($A50-$D$16<=2,Premissas!$B$49,IF($A50-$D$16<=5,Premissas!$B$50,IF($A50-$D$16<=8,Premissas!$B$51,$G$16)))+IF($A50=1+$D$16,Premissas!$B$55,IF($A50=3+$D$16,Premissas!$B$56,IF($A50=6+$D$16,Premissas!$B$57,0)))) -> -39428.888 | BX50: =BV50+BW50 -> -26791.929 | BY50: =BY49+BX50 -> -219383.91 | BZ50: =IF(BX50>0,$A50,9999) -> 9999 | CA50: =IF(BY50>0,$A50,9999) -> 9999 | CB50: =IF($A50-$D$17<Premissas!$B$41,0,$C$17*(Premissas!$B$39+(Premissas!$B$40-Premissas!$B$39)*$A50/36)/(1+EXP(-$K$17*($A50-$D$17-$I$17)))) -> 0 | CC50: =(CB50*$B$17+IF($A50>=Premissas!$B$46+$D$17,$F$17,0))*(1-$E$17)*(1-Premissas!$B$60) -> 0 | CD50: =-(CB50*$J$17+MAX(0,CB50-CB49)*$H$17+IF($A50-$D$17<=2,Premissas!$B$49,IF($A50-$D$17<=5,Premissas!$B$50,IF($A50-$D$17<=8,Premissas!$B$51,$G$17)))+IF($A50=1+$D$17,Premissas!$B$55,IF($A50=3+$D$17,Premissas!$B$56,IF($A50=6+$D$17,Premissas!$B$57,0)))) -> -34000 | CE50: =CC50+CD50 -> -34000 | CF50: =CF49+CE50 -> -82000 | CG50: =IF(CE50>0,$A50,9999) -> 9999 | CH50: =IF(CF50>0,$A50,9999) -> 9999
A51: 10 | C51: =IF($A51-$D$6<Premissas!$B$41,0,$C$6*(Premissas!$B$39+(Premissas!$B$40-Premissas!$B$39)*$A51/36)/(1+EXP(-$K$6*($A51-$D$6-$I$6)))) -> 39.721971 | D51: =(C51*$B$6+IF($A51>=Premissas!$B$46+$D$6,$F$6,0))*(1-$E$6)*(1-Premissas!$B$60) -> 22671.309 | E51: =-(C51*$J$6+MAX(0,C51-C50)*$H$6+IF($A51-$D$6<=2,Premissas!$B$49,IF($A51-$D$6<=5,Premissas!$B$50,IF($A51-$D$6<=8,Premissas!$B$51,$G$6)))+IF($A51=1+$D$6,Premissas!$B$55,IF($A51=3+$D$6,Premissas!$B$56,IF($A51=6+$D$6,Premissas!$B$57,0)))) -> -40837.436 | F51: =D51+E51 -> -18166.127 | G51: =G50+F51 -> -226516.2 | H51: =IF(F51>0,$A51,9999) -> 9999 | I51: =IF(G51>0,$A51,9999) -> 9999 | J51: =IF($A51-$D$7<Premissas!$B$41,0,$C$7*(Premissas!$B$39+(Premissas!$B$40-Premissas!$B$39)*$A51/36)/(1+EXP(-$K$7*($A51-$D$7-$I$7)))) -> 131.24258 | K51: =(J51*$B$7+IF($A51>=Premissas!$B$46+$D$7,$F$7,0))*(1-$E$7)*(1-Premissas!$B$60) -> 36931.148 | L51: =-(J51*$J$7+MAX(0,J51-J50)*$H$7+IF($A51-$D$7<=2,Premissas!$B$49,IF($A51-$D$7<=5,Premissas!$B$50,IF($A51-$D$7<=8,Premissas!$B$51,$G$7)))+IF($A51=1+$D$7,Premissas!$B$55,IF($A51=3+$D$7,Premissas!$B$56,IF($A51=6+$D$7,Premissas!$B$57,0)))) -> -42446.48 | M51: =K51+L51 -> -5515.3321 | N51: =N50+M51 -> -191609.42 | O51: =IF(M51>0,$A51,9999) -> 9999 | P51: =IF(N51>0,$A51,9999) -> 9999 | Q51: =IF($A51-$D$8<Premissas!$B$41,0,$C$8*(Premissas!$B$39+(Premissas!$B$40-Premissas!$B$39)*$A51/36)/(1+EXP(-$K$8*($A51-$D$8-$I$8)))) -> 131.24258 | R51: =(Q51*$B$8+IF($A51>=Premissas!$B$46+$D$8,$F$8,0))*(1-$E$8)*(1-Premissas!$B$60) -> 49241.53 | S51: =-(Q51*$J$8+MAX(0,Q51-Q50)*$H$8+IF($A51-$D$8<=2,Premissas!$B$49,IF($A51-$D$8<=5,Premissas!$B$50,IF($A51-$D$8<=8,Premissas!$B$51,$G$8)))+IF($A51=1+$D$8,Premissas!$B$55,IF($A51=3+$D$8,Premissas!$B$56,IF($A51=6+$D$8,Premissas!$B$57,0)))) -> -42446.48 | T51: =R51+S51 -> 6795.0504 | U51: =U50+T51 -> -162019.76 | V51: =IF(T51>0,$A51,9999) -> 10 | W51: =IF(U51>0,$A51,9999) -> 9999 | X51: =IF($A51-$D$9<Premissas!$B$41,0,$C$9*(Premissas!$B$39+(Premissas!$B$40-Premissas!$B$39)*$A51/36)/(1+EXP(-$K$9*($A51-$D$9-$I$9)))) -> 131.24258 | Y51: =(X51*$B$9+IF($A51>=Premissas!$B$46+$D$9,$F$9,0))*(1-$E$9)*(1-Premissas!$B$60) -> 39393.224 | Z51: =-(X51*$J$9+MAX(0,X51-X50)*$H$9+IF($A51-$D$9<=2,Premissas!$B$49,IF($A51-$D$9<=5,Premissas!$B$50,IF($A51-$D$9<=8,Premissas!$B$51,$G$9)))+IF($A51=1+$D$9,Premissas!$B$55,IF($A51=3+$D$9,Premissas!$B$56,IF($A51=6+$D$9,Premissas!$B$57,0)))) -> -42446.48 | AA51: =Y51+Z51 -> -3053.2556 | AB51: =AB50+AA51 -> -185691.49 | AC51: =IF(AA51>0,$A51,9999) -> 9999 | AD51: =IF(AB51>0,$A51,9999) -> 9999 | AE51: =IF($A51-$D$10<Premissas!$B$41,0,$C$10*(Premissas!$B$39+(Premissas!$B$40-Premissas!$B$39)*$A51/36)/(1+EXP(-$K$10*($A51-$D$10-$I$10)))) -> 131.24258 | AF51: =(AE51*$B$10+IF($A51>=Premissas!$B$46+$D$10,$F$10,0))*(1-$E$10)*(1-Premissas!$B$60) -> 34469.071 | AG51: =-(AE51*$J$10+MAX(0,AE51-AE50)*$H$10+IF($A51-$D$10<=2,Premissas!$B$49,IF($A51-$D$10<=5,Premissas!$B$50,IF($A51-$D$10<=8,Premissas!$B$51,$G$10)))+IF($A51=1+$D$10,Premissas!$B$55,IF($A51=3+$D$10,Premissas!$B$56,IF($A51=6+$D$10,Premissas!$B$57,0)))) -> -42446.48 | AH51: =AF51+AG51 -> -7977.4086 | AI51: =AI50+AH51 -> -197527.35 | AJ51: =IF(AH51>0,$A51,9999) -> 9999 | AK51: =IF(AI51>0,$A51,9999) -> 9999 | AL51: =IF($A51-$D$11<Premissas!$B$41,0,$C$11*(Premissas!$B$39+(Premissas!$B$40-Premissas!$B$39)*$A51/36)/(1+EXP(-$K$11*($A51-$D$11-$I$11)))) -> 131.24258 | AM51: =(AL51*$B$11+IF($A51>=Premissas!$B$46+$D$11,$F$11,0))*(1-$E$11)*(1-Premissas!$B$60) -> 29544.918 | AN51: =-(AL51*$J$11+MAX(0,AL51-AL50)*$H$11+IF($A51-$D$11<=2,Premissas!$B$49,IF($A51-$D$11<=5,Premissas!$B$50,IF($A51-$D$11<=8,Premissas!$B$51,$G$11)))+IF($A51=1+$D$11,Premissas!$B$55,IF($A51=3+$D$11,Premissas!$B$56,IF($A51=6+$D$11,Premissas!$B$57,0)))) -> -42446.48 | AO51: =AM51+AN51 -> -12901.562 | AP51: =AP50+AO51 -> -209363.21 | AQ51: =IF(AO51>0,$A51,9999) -> 9999 | AR51: =IF(AP51>0,$A51,9999) -> 9999 | AS51: =IF($A51-$D$12<Premissas!$B$41,0,$C$12*(Premissas!$B$39+(Premissas!$B$40-Premissas!$B$39)*$A51/36)/(1+EXP(-$K$12*($A51-$D$12-$I$12)))) -> 131.24258 | AT51: =(AS51*$B$12+IF($A51>=Premissas!$B$46+$D$12,$F$12,0))*(1-$E$12)*(1-Premissas!$B$60) -> 32009.551 | AU51: =-(AS51*$J$12+MAX(0,AS51-AS50)*$H$12+IF($A51-$D$12<=2,Premissas!$B$49,IF($A51-$D$12<=5,Premissas!$B$50,IF($A51-$D$12<=8,Premissas!$B$51,$G$12)))+IF($A51=1+$D$12,Premissas!$B$55,IF($A51=3+$D$12,Premissas!$B$56,IF($A51=6+$D$12,Premissas!$B$57,0)))) -> -42446.48 | AV51: =AT51+AU51 -> -10436.929 | AW51: =AW50+AV51 -> -203945.37 | AX51: =IF(AV51>0,$A51,9999) -> 9999 | AY51: =IF(AW51>0,$A51,9999) -> 9999 | AZ51: =IF($A51-$D$13<Premissas!$B$41,0,$C$13*(Premissas!$B$39+(Premissas!$B$40-Premissas!$B$39)*$A51/36)/(1+EXP(-$K$13*($A51-$D$13-$I$13)))) -> 0 | BA51: =(AZ51*$B$13+IF($A51>=Premissas!$B$46+$D$13,$F$13,0))*(1-$E$13)*(1-Premissas!$B$60) -> 0 | BB51: =-(AZ51*$J$13+MAX(0,AZ51-AZ50)*$H$13+IF($A51-$D$13<=2,Premissas!$B$49,IF($A51-$D$13<=5,Premissas!$B$50,IF($A51-$D$13<=8,Premissas!$B$51,$G$13)))+IF($A51=1+$D$13,Premissas!$B$55,IF($A51=3+$D$13,Premissas!$B$56,IF($A51=6+$D$13,Premissas!$B$57,0)))) -> -22000 | BC51: =BA51+BB51 -> -22000 | BD51: =BD50+BC51 -> -104000 | BE51: =IF(BC51>0,$A51,9999) -> 9999 | BF51: =IF(BD51>0,$A51,9999) -> 9999 | BG51: =IF($A51-$D$14<Premissas!$B$41,0,$C$14*(Premissas!$B$39+(Premissas!$B$40-Premissas!$B$39)*$A51/36)/(1+EXP(-$K$14*($A51-$D$14-$I$14)))) -> 131.24258 | BH51: =(BG51*$B$14+IF($A51>=Premissas!$B$46+$D$14,$F$14,0))*(1-$E$14)*(1-Premissas!$B$60) -> 36931.148 | BI51: =-(BG51*$J$14+MAX(0,BG51-BG50)*$H$14+IF($A51-$D$14<=2,Premissas!$B$49,IF($A51-$D$14<=5,Premissas!$B$50,IF($A51-$D$14<=8,Premissas!$B$51,$G$14)))+IF($A51=1+$D$14,Premissas!$B$55,IF($A51=3+$D$14,Premissas!$B$56,IF($A51=6+$D$14,Premissas!$B$57,0)))) -> -32446.48 | BJ51: =BH51+BI51 -> 4484.6679 | BK51: =BK50+BJ51 -> -171609.42 | BL51: =IF(BJ51>0,$A51,9999) -> 10 | BM51: =IF(BK51>0,$A51,9999) -> 9999 | BN51: =IF($A51-$D$15<Premissas!$B$41,0,$C$15*(Premissas!$B$39+(Premissas!$B$40-Premissas!$B$39)*$A51/36)/(1+EXP(-$K$15*($A51-$D$15-$I$15)))) -> 19.860986 | BO51: =(BN51*$B$15+IF($A51>=Premissas!$B$46+$D$15,$F$15,0))*(1-$E$15)*(1-Premissas!$B$60) -> 16335.654 | BP51: =-(BN51*$J$15+MAX(0,BN51-BN50)*$H$15+IF($A51-$D$15<=2,Premissas!$B$49,IF($A51-$D$15<=5,Premissas!$B$50,IF($A51-$D$15<=8,Premissas!$B$51,$G$15)))+IF($A51=1+$D$15,Premissas!$B$55,IF($A51=3+$D$15,Premissas!$B$56,IF($A51=6+$D$15,Premissas!$B$57,0)))) -> -37918.718 | BQ51: =BO51+BP51 -> -21583.064 | BR51: =BR50+BQ51 -> -233258.1 | BS51: =IF(BQ51>0,$A51,9999) -> 9999 | BT51: =IF(BR51>0,$A51,9999) -> 9999 | BU51: =IF($A51-$D$16<Premissas!$B$41,0,$C$16*(Premissas!$B$39+(Premissas!$B$40-Premissas!$B$39)*$A51/36)/(1+EXP(-$K$16*($A51-$D$16-$I$16)))) -> 39.721971 | BV51: =(BU51*$B$16+IF($A51>=Premissas!$B$46+$D$16,$F$16,0))*(1-$E$16)*(1-Premissas!$B$60) -> 14736.351 | BW51: =-(BU51*$J$16+MAX(0,BU51-BU50)*$H$16+IF($A51-$D$16<=2,Premissas!$B$49,IF($A51-$D$16<=5,Premissas!$B$50,IF($A51-$D$16<=8,Premissas!$B$51,$G$16)))+IF($A51=1+$D$16,Premissas!$B$55,IF($A51=3+$D$16,Premissas!$B$56,IF($A51=6+$D$16,Premissas!$B$57,0)))) -> -40837.436 | BX51: =BV51+BW51 -> -26101.085 | BY51: =BY50+BX51 -> -245485 | BZ51: =IF(BX51>0,$A51,9999) -> 9999 | CA51: =IF(BY51>0,$A51,9999) -> 9999 | CB51: =IF($A51-$D$17<Premissas!$B$41,0,$C$17*(Premissas!$B$39+(Premissas!$B$40-Premissas!$B$39)*$A51/36)/(1+EXP(-$K$17*($A51-$D$17-$I$17)))) -> 0 | CC51: =(CB51*$B$17+IF($A51>=Premissas!$B$46+$D$17,$F$17,0))*(1-$E$17)*(1-Premissas!$B$60) -> 0 | CD51: =-(CB51*$J$17+MAX(0,CB51-CB50)*$H$17+IF($A51-$D$17<=2,Premissas!$B$49,IF($A51-$D$17<=5,Premissas!$B$50,IF($A51-$D$17<=8,Premissas!$B$51,$G$17)))+IF($A51=1+$D$17,Premissas!$B$55,IF($A51=3+$D$17,Premissas!$B$56,IF($A51=6+$D$17,Premissas!$B$57,0)))) -> -22000 | CE51: =CC51+CD51 -> -22000 | CF51: =CF50+CE51 -> -104000 | CG51: =IF(CE51>0,$A51,9999) -> 9999 | CH51: =IF(CF51>0,$A51,9999) -> 9999
A52: 11 | C52: =IF($A52-$D$6<Premissas!$B$41,0,$C$6*(Premissas!$B$39+(Premissas!$B$40-Premissas!$B$39)*$A52/36)/(1+EXP(-$K$6*($A52-$D$6-$I$6)))) -> 52.698399 | D52: =(C52*$B$6+IF($A52>=Premissas!$B$46+$D$6,$F$6,0))*(1-$E$6)*(1-Premissas!$B$60) -> 26810.789 | E52: =-(C52*$J$6+MAX(0,C52-C51)*$H$6+IF($A52-$D$6<=2,Premissas!$B$49,IF($A52-$D$6<=5,Premissas!$B$50,IF($A52-$D$6<=8,Premissas!$B$51,$G$6)))+IF($A52=1+$D$6,Premissas!$B$55,IF($A52=3+$D$6,Premissas!$B$56,IF($A52=6+$D$6,Premissas!$B$57,0)))) -> -42561.999 | F52: =D52+E52 -> -15751.21 | G52: =G51+F52 -> -242267.41 | H52: =IF(F52>0,$A52,9999) -> 9999 | I52: =IF(G52>0,$A52,9999) -> 9999 | J52: =IF($A52-$D$7<Premissas!$B$41,0,$C$7*(Premissas!$B$39+(Premissas!$B$40-Premissas!$B$39)*$A52/36)/(1+EXP(-$K$7*($A52-$D$7-$I$7)))) -> 178.52462 | K52: =(J52*$B$7+IF($A52>=Premissas!$B$46+$D$7,$F$7,0))*(1-$E$7)*(1-Premissas!$B$60) -> 47534.145 | L52: =-(J52*$J$7+MAX(0,J52-J51)*$H$7+IF($A52-$D$7<=2,Premissas!$B$49,IF($A52-$D$7<=5,Premissas!$B$50,IF($A52-$D$7<=8,Premissas!$B$51,$G$7)))+IF($A52=1+$D$7,Premissas!$B$55,IF($A52=3+$D$7,Premissas!$B$56,IF($A52=6+$D$7,Premissas!$B$57,0)))) -> -44862.136 | M52: =K52+L52 -> 2672.0091 | N52: =N51+M52 -> -188937.41 | O52: =IF(M52>0,$A52,9999) -> 11 | P52: =IF(N52>0,$A52,9999) -> 9999 | Q52: =IF($A52-$D$8<Premissas!$B$41,0,$C$8*(Premissas!$B$39+(Premissas!$B$40-Premissas!$B$39)*$A52/36)/(1+EXP(-$K$8*($A52-$D$8-$I$8)))) -> 178.52462 | R52: =(Q52*$B$8+IF($A52>=Premissas!$B$46+$D$8,$F$8,0))*(1-$E$8)*(1-Premissas!$B$60) -> 63378.86 | S52: =-(Q52*$J$8+MAX(0,Q52-Q51)*$H$8+IF($A52-$D$8<=2,Premissas!$B$49,IF($A52-$D$8<=5,Premissas!$B$50,IF($A52-$D$8<=8,Premissas!$B$51,$G$8)))+IF($A52=1+$D$8,Premissas!$B$55,IF($A52=3+$D$8,Premissas!$B$56,IF($A52=6+$D$8,Premissas!$B$57,0)))) -> -44862.136 | T52: =R52+S52 -> 18516.724 | U52: =U51+T52 -> -143503.04 | V52: =IF(T52>0,$A52,9999) -> 11 | W52: =IF(U52>0,$A52,9999) -> 9999 | X52: =IF($A52-$D$9<Premissas!$B$41,0,$C$9*(Premissas!$B$39+(Premissas!$B$40-Premissas!$B$39)*$A52/36)/(1+EXP(-$K$9*($A52-$D$9-$I$9)))) -> 178.52462 | Y52: =(X52*$B$9+IF($A52>=Premissas!$B$46+$D$9,$F$9,0))*(1-$E$9)*(1-Premissas!$B$60) -> 50703.088 | Z52: =-(X52*$J$9+MAX(0,X52-X51)*$H$9+IF($A52-$D$9<=2,Premissas!$B$49,IF($A52-$D$9<=5,Premissas!$B$50,IF($A52-$D$9<=8,Premissas!$B$51,$G$9)))+IF($A52=1+$D$9,Premissas!$B$55,IF($A52=3+$D$9,Premissas!$B$56,IF($A52=6+$D$9,Premissas!$B$57,0)))) -> -44862.136 | AA52: =Y52+Z52 -> 5840.9521 | AB52: =AB51+AA52 -> -179850.53 | AC52: =IF(AA52>0,$A52,9999) -> 11 | AD52: =IF(AB52>0,$A52,9999) -> 9999 | AE52: =IF($A52-$D$10<Premissas!$B$41,0,$C$10*(Premissas!$B$39+(Premissas!$B$40-Premissas!$B$39)*$A52/36)/(1+EXP(-$K$10*($A52-$D$10-$I$10)))) -> 178.52462 | AF52: =(AE52*$B$10+IF($A52>=Premissas!$B$46+$D$10,$F$10,0))*(1-$E$10)*(1-Premissas!$B$60) -> 44365.202 | AG52: =-(AE52*$J$10+MAX(0,AE52-AE51)*$H$10+IF($A52-$D$10<=2,Premissas!$B$49,IF($A52-$D$10<=5,Premissas!$B$50,IF($A52-$D$10<=8,Premissas!$B$51,$G$10)))+IF($A52=1+$D$10,Premissas!$B$55,IF($A52=3+$D$10,Premissas!$B$56,IF($A52=6+$D$10,Premissas!$B$57,0)))) -> -44862.136 | AH52: =AF52+AG52 -> -496.93387 | AI52: =AI51+AH52 -> -198024.28 | AJ52: =IF(AH52>0,$A52,9999) -> 9999 | AK52: =IF(AI52>0,$A52,9999) -> 9999 | AL52: =IF($A52-$D$11<Premissas!$B$41,0,$C$11*(Premissas!$B$39+(Premissas!$B$40-Premissas!$B$39)*$A52/36)/(1+EXP(-$K$11*($A52-$D$11-$I$11)))) -> 178.52462 | AM52: =(AL52*$B$11+IF($A52>=Premissas!$B$46+$D$11,$F$11,0))*(1-$E$11)*(1-Premissas!$B$60) -> 38027.316 | AN52: =-(AL52*$J$11+MAX(0,AL52-AL51)*$H$11+IF($A52-$D$11<=2,Premissas!$B$49,IF($A52-$D$11<=5,Premissas!$B$50,IF($A52-$D$11<=8,Premissas!$B$51,$G$11)))+IF($A52=1+$D$11,Premissas!$B$55,IF($A52=3+$D$11,Premissas!$B$56,IF($A52=6+$D$11,Premissas!$B$57,0)))) -> -44862.136 | AO52: =AM52+AN52 -> -6834.8199 | AP52: =AP51+AO52 -> -216198.03 | AQ52: =IF(AO52>0,$A52,9999) -> 9999 | AR52: =IF(AP52>0,$A52,9999) -> 9999 | AS52: =IF($A52-$D$12<Premissas!$B$41,0,$C$12*(Premissas!$B$39+(Premissas!$B$40-Premissas!$B$39)*$A52/36)/(1+EXP(-$K$12*($A52-$D$12-$I$12)))) -> 178.52462 | AT52: =(AS52*$B$12+IF($A52>=Premissas!$B$46+$D$12,$F$12,0))*(1-$E$12)*(1-Premissas!$B$60) -> 40839.472 | AU52: =-(AS52*$J$12+MAX(0,AS52-AS51)*$H$12+IF($A52-$D$12<=2,Premissas!$B$49,IF($A52-$D$12<=5,Premissas!$B$50,IF($A52-$D$12<=8,Premissas!$B$51,$G$12)))+IF($A52=1+$D$12,Premissas!$B$55,IF($A52=3+$D$12,Premissas!$B$56,IF($A52=6+$D$12,Premissas!$B$57,0)))) -> -44862.136 | AV52: =AT52+AU52 -> -4022.6639 | AW52: =AW51+AV52 -> -207968.03 | AX52: =IF(AV52>0,$A52,9999) -> 9999 | AY52: =IF(AW52>0,$A52,9999) -> 9999 | AZ52: =IF($A52-$D$13<Premissas!$B$41,0,$C$13*(Premissas!$B$39+(Premissas!$B$40-Premissas!$B$39)*$A52/36)/(1+EXP(-$K$13*($A52-$D$13-$I$13)))) -> 0 | BA52: =(AZ52*$B$13+IF($A52>=Premissas!$B$46+$D$13,$F$13,0))*(1-$E$13)*(1-Premissas!$B$60) -> 0 | BB52: =-(AZ52*$J$13+MAX(0,AZ52-AZ51)*$H$13+IF($A52-$D$13<=2,Premissas!$B$49,IF($A52-$D$13<=5,Premissas!$B$50,IF($A52-$D$13<=8,Premissas!$B$51,$G$13)))+IF($A52=1+$D$13,Premissas!$B$55,IF($A52=3+$D$13,Premissas!$B$56,IF($A52=6+$D$13,Premissas!$B$57,0)))) -> -22000 | BC52: =BA52+BB52 -> -22000 | BD52: =BD51+BC52 -> -126000 | BE52: =IF(BC52>0,$A52,9999) -> 9999 | BF52: =IF(BD52>0,$A52,9999) -> 9999 | BG52: =IF($A52-$D$14<Premissas!$B$41,0,$C$14*(Premissas!$B$39+(Premissas!$B$40-Premissas!$B$39)*$A52/36)/(1+EXP(-$K$14*($A52-$D$14-$I$14)))) -> 178.52462 | BH52: =(BG52*$B$14+IF($A52>=Premissas!$B$46+$D$14,$F$14,0))*(1-$E$14)*(1-Premissas!$B$60) -> 47534.145 | BI52: =-(BG52*$J$14+MAX(0,BG52-BG51)*$H$14+IF($A52-$D$14<=2,Premissas!$B$49,IF($A52-$D$14<=5,Premissas!$B$50,IF($A52-$D$14<=8,Premissas!$B$51,$G$14)))+IF($A52=1+$D$14,Premissas!$B$55,IF($A52=3+$D$14,Premissas!$B$56,IF($A52=6+$D$14,Premissas!$B$57,0)))) -> -34862.136 | BJ52: =BH52+BI52 -> 12672.009 | BK52: =BK51+BJ52 -> -158937.41 | BL52: =IF(BJ52>0,$A52,9999) -> 11 | BM52: =IF(BK52>0,$A52,9999) -> 9999 | BN52: =IF($A52-$D$15<Premissas!$B$41,0,$C$15*(Premissas!$B$39+(Premissas!$B$40-Premissas!$B$39)*$A52/36)/(1+EXP(-$K$15*($A52-$D$15-$I$15)))) -> 26.349199 | BO52: =(BN52*$B$15+IF($A52>=Premissas!$B$46+$D$15,$F$15,0))*(1-$E$15)*(1-Premissas!$B$60) -> 18405.395 | BP52: =-(BN52*$J$15+MAX(0,BN52-BN51)*$H$15+IF($A52-$D$15<=2,Premissas!$B$49,IF($A52-$D$15<=5,Premissas!$B$50,IF($A52-$D$15<=8,Premissas!$B$51,$G$15)))+IF($A52=1+$D$15,Premissas!$B$55,IF($A52=3+$D$15,Premissas!$B$56,IF($A52=6+$D$15,Premissas!$B$57,0)))) -> -38780.999 | BQ52: =BO52+BP52 -> -20375.605 | BR52: =BR51+BQ52 -> -253633.71 | BS52: =IF(BQ52>0,$A52,9999) -> 9999 | BT52: =IF(BR52>0,$A52,9999) -> 9999 | BU52: =IF($A52-$D$16<Premissas!$B$41,0,$C$16*(Premissas!$B$39+(Premissas!$B$40-Premissas!$B$39)*$A52/36)/(1+EXP(-$K$16*($A52-$D$16-$I$16)))) -> 52.698399 | BV52: =(BU52*$B$16+IF($A52>=Premissas!$B$46+$D$16,$F$16,0))*(1-$E$16)*(1-Premissas!$B$60) -> 17427.013 | BW52: =-(BU52*$J$16+MAX(0,BU52-BU51)*$H$16+IF($A52-$D$16<=2,Premissas!$B$49,IF($A52-$D$16<=5,Premissas!$B$50,IF($A52-$D$16<=8,Premissas!$B$51,$G$16)))+IF($A52=1+$D$16,Premissas!$B$55,IF($A52=3+$D$16,Premissas!$B$56,IF($A52=6+$D$16,Premissas!$B$57,0)))) -> -42561.999 | BX52: =BV52+BW52 -> -25134.986 | BY52: =BY51+BX52 -> -270619.98 | BZ52: =IF(BX52>0,$A52,9999) -> 9999 | CA52: =IF(BY52>0,$A52,9999) -> 9999 | CB52: =IF($A52-$D$17<Premissas!$B$41,0,$C$17*(Premissas!$B$39+(Premissas!$B$40-Premissas!$B$39)*$A52/36)/(1+EXP(-$K$17*($A52-$D$17-$I$17)))) -> 0 | CC52: =(CB52*$B$17+IF($A52>=Premissas!$B$46+$D$17,$F$17,0))*(1-$E$17)*(1-Premissas!$B$60) -> 0 | CD52: =-(CB52*$J$17+MAX(0,CB52-CB51)*$H$17+IF($A52-$D$17<=2,Premissas!$B$49,IF($A52-$D$17<=5,Premissas!$B$50,IF($A52-$D$17<=8,Premissas!$B$51,$G$17)))+IF($A52=1+$D$17,Premissas!$B$55,IF($A52=3+$D$17,Premissas!$B$56,IF($A52=6+$D$17,Premissas!$B$57,0)))) -> -22000 | CE52: =CC52+CD52 -> -22000 | CF52: =CF51+CE52 -> -126000 | CG52: =IF(CE52>0,$A52,9999) -> 9999 | CH52: =IF(CF52>0,$A52,9999) -> 9999
A53: 12 | C53: =IF($A53-$D$6<Premissas!$B$41,0,$C$6*(Premissas!$B$39+(Premissas!$B$40-Premissas!$B$39)*$A53/36)/(1+EXP(-$K$6*($A53-$D$6-$I$6)))) -> 68.912659 | D53: =(C53*$B$6+IF($A53>=Premissas!$B$46+$D$6,$F$6,0))*(1-$E$6)*(1-Premissas!$B$60) -> 31983.138 | E53: =-(C53*$J$6+MAX(0,C53-C52)*$H$6+IF($A53-$D$6<=2,Premissas!$B$49,IF($A53-$D$6<=5,Premissas!$B$50,IF($A53-$D$6<=8,Premissas!$B$51,$G$6)))+IF($A53=1+$D$6,Premissas!$B$55,IF($A53=3+$D$6,Premissas!$B$56,IF($A53=6+$D$6,Premissas!$B$57,0)))) -> -44586.774 | F53: =D53+E53 -> -12603.635 | G53: =G52+F53 -> -254871.05 | H53: =IF(F53>0,$A53,9999) -> 9999 | I53: =IF(G53>0,$A53,9999) -> 9999 | J53: =IF($A53-$D$7<Premissas!$B$41,0,$C$7*(Premissas!$B$39+(Premissas!$B$40-Premissas!$B$39)*$A53/36)/(1+EXP(-$K$7*($A53-$D$7-$I$7)))) -> 231.48333 | K53: =(J53*$B$7+IF($A53>=Premissas!$B$46+$D$7,$F$7,0))*(1-$E$7)*(1-Premissas!$B$60) -> 59410.137 | L53: =-(J53*$J$7+MAX(0,J53-J52)*$H$7+IF($A53-$D$7<=2,Premissas!$B$49,IF($A53-$D$7<=5,Premissas!$B$50,IF($A53-$D$7<=8,Premissas!$B$51,$G$7)))+IF($A53=1+$D$7,Premissas!$B$55,IF($A53=3+$D$7,Premissas!$B$56,IF($A53=6+$D$7,Premissas!$B$57,0)))) -> -47370.236 | M53: =K53+L53 -> 12039.902 | N53: =N52+M53 -> -176897.51 | O53: =IF(M53>0,$A53,9999) -> 12 | P53: =IF(N53>0,$A53,9999) -> 9999 | Q53: =IF($A53-$D$8<Premissas!$B$41,0,$C$8*(Premissas!$B$39+(Premissas!$B$40-Premissas!$B$39)*$A53/36)/(1+EXP(-$K$8*($A53-$D$8-$I$8)))) -> 231.48333 | R53: =(Q53*$B$8+IF($A53>=Premissas!$B$46+$D$8,$F$8,0))*(1-$E$8)*(1-Premissas!$B$60) -> 79213.517 | S53: =-(Q53*$J$8+MAX(0,Q53-Q52)*$H$8+IF($A53-$D$8<=2,Premissas!$B$49,IF($A53-$D$8<=5,Premissas!$B$50,IF($A53-$D$8<=8,Premissas!$B$51,$G$8)))+IF($A53=1+$D$8,Premissas!$B$55,IF($A53=3+$D$8,Premissas!$B$56,IF($A53=6+$D$8,Premissas!$B$57,0)))) -> -47370.236 | T53: =R53+S53 -> 31843.281 | U53: =U52+T53 -> -111659.76 | V53: =IF(T53>0,$A53,9999) -> 12 | W53: =IF(U53>0,$A53,9999) -> 9999 | X53: =IF($A53-$D$9<Premissas!$B$41,0,$C$9*(Premissas!$B$39+(Premissas!$B$40-Premissas!$B$39)*$A53/36)/(1+EXP(-$K$9*($A53-$D$9-$I$9)))) -> 231.48333 | Y53: =(X53*$B$9+IF($A53>=Premissas!$B$46+$D$9,$F$9,0))*(1-$E$9)*(1-Premissas!$B$60) -> 63370.813 | Z53: =-(X53*$J$9+MAX(0,X53-X52)*$H$9+IF($A53-$D$9<=2,Premissas!$B$49,IF($A53-$D$9<=5,Premissas!$B$50,IF($A53-$D$9<=8,Premissas!$B$51,$G$9)))+IF($A53=1+$D$9,Premissas!$B$55,IF($A53=3+$D$9,Premissas!$B$56,IF($A53=6+$D$9,Premissas!$B$57,0)))) -> -47370.236 | AA53: =Y53+Z53 -> 16000.577 | AB53: =AB52+AA53 -> -163849.96 | AC53: =IF(AA53>0,$A53,9999) -> 12 | AD53: =IF(AB53>0,$A53,9999) -> 9999 | AE53: =IF($A53-$D$10<Premissas!$B$41,0,$C$10*(Premissas!$B$39+(Premissas!$B$40-Premissas!$B$39)*$A53/36)/(1+EXP(-$K$10*($A53-$D$10-$I$10)))) -> 231.48333 | AF53: =(AE53*$B$10+IF($A53>=Premissas!$B$46+$D$10,$F$10,0))*(1-$E$10)*(1-Premissas!$B$60) -> 55449.462 | AG53: =-(AE53*$J$10+MAX(0,AE53-AE52)*$H$10+IF($A53-$D$10<=2,Premissas!$B$49,IF($A53-$D$10<=5,Premissas!$B$50,IF($A53-$D$10<=8,Premissas!$B$51,$G$10)))+IF($A53=1+$D$10,Premissas!$B$55,IF($A53=3+$D$10,Premissas!$B$56,IF($A53=6+$D$10,Premissas!$B$57,0)))) -> -47370.236 | AH53: =AF53+AG53 -> 8079.2258 | AI53: =AI52+AH53 -> -189945.06 | AJ53: =IF(AH53>0,$A53,9999) -> 12 | AK53: =IF(AI53>0,$A53,9999) -> 9999 | AL53: =IF($A53-$D$11<Premissas!$B$41,0,$C$11*(Premissas!$B$39+(Premissas!$B$40-Premissas!$B$39)*$A53/36)/(1+EXP(-$K$11*($A53-$D$11-$I$11)))) -> 231.48333 | AM53: =(AL53*$B$11+IF($A53>=Premissas!$B$46+$D$11,$F$11,0))*(1-$E$11)*(1-Premissas!$B$60) -> 47528.11 | AN53: =-(AL53*$J$11+MAX(0,AL53-AL52)*$H$11+IF($A53-$D$11<=2,Premissas!$B$49,IF($A53-$D$11<=5,Premissas!$B$50,IF($A53-$D$11<=8,Premissas!$B$51,$G$11)))+IF($A53=1+$D$11,Premissas!$B$55,IF($A53=3+$D$11,Premissas!$B$56,IF($A53=6+$D$11,Premissas!$B$57,0)))) -> -47370.236 | AO53: =AM53+AN53 -> 157.87409 | AP53: =AP52+AO53 -> -216040.16 | AQ53: =IF(AO53>0,$A53,9999) -> 12 | AR53: =IF(AP53>0,$A53,9999) -> 9999 | AS53: =IF($A53-$D$12<Premissas!$B$41,0,$C$12*(Premissas!$B$39+(Premissas!$B$40-Premissas!$B$39)*$A53/36)/(1+EXP(-$K$12*($A53-$D$12-$I$12)))) -> 231.48333 | AT53: =(AS53*$B$12+IF($A53>=Premissas!$B$46+$D$12,$F$12,0))*(1-$E$12)*(1-Premissas!$B$60) -> 50729.513 | AU53: =-(AS53*$J$12+MAX(0,AS53-AS52)*$H$12+IF($A53-$D$12<=2,Premissas!$B$49,IF($A53-$D$12<=5,Premissas!$B$50,IF($A53-$D$12<=8,Premissas!$B$51,$G$12)))+IF($A53=1+$D$12,Premissas!$B$55,IF($A53=3+$D$12,Premissas!$B$56,IF($A53=6+$D$12,Premissas!$B$57,0)))) -> -47370.236 | AV53: =AT53+AU53 -> 3359.2766 | AW53: =AW52+AV53 -> -204608.75 | AX53: =IF(AV53>0,$A53,9999) -> 12 | AY53: =IF(AW53>0,$A53,9999) -> 9999 | AZ53: =IF($A53-$D$13<Premissas!$B$41,0,$C$13*(Premissas!$B$39+(Premissas!$B$40-Premissas!$B$39)*$A53/36)/(1+EXP(-$K$13*($A53-$D$13-$I$13)))) -> 0 | BA53: =(AZ53*$B$13+IF($A53>=Premissas!$B$46+$D$13,$F$13,0))*(1-$E$13)*(1-Premissas!$B$60) -> 0 | BB53: =-(AZ53*$J$13+MAX(0,AZ53-AZ52)*$H$13+IF($A53-$D$13<=2,Premissas!$B$49,IF($A53-$D$13<=5,Premissas!$B$50,IF($A53-$D$13<=8,Premissas!$B$51,$G$13)))+IF($A53=1+$D$13,Premissas!$B$55,IF($A53=3+$D$13,Premissas!$B$56,IF($A53=6+$D$13,Premissas!$B$57,0)))) -> -38000 | BC53: =BA53+BB53 -> -38000 | BD53: =BD52+BC53 -> -164000 | BE53: =IF(BC53>0,$A53,9999) -> 9999 | BF53: =IF(BD53>0,$A53,9999) -> 9999 | BG53: =IF($A53-$D$14<Premissas!$B$41,0,$C$14*(Premissas!$B$39+(Premissas!$B$40-Premissas!$B$39)*$A53/36)/(1+EXP(-$K$14*($A53-$D$14-$I$14)))) -> 231.48333 | BH53: =(BG53*$B$14+IF($A53>=Premissas!$B$46+$D$14,$F$14,0))*(1-$E$14)*(1-Premissas!$B$60) -> 59410.137 | BI53: =-(BG53*$J$14+MAX(0,BG53-BG52)*$H$14+IF($A53-$D$14<=2,Premissas!$B$49,IF($A53-$D$14<=5,Premissas!$B$50,IF($A53-$D$14<=8,Premissas!$B$51,$G$14)))+IF($A53=1+$D$14,Premissas!$B$55,IF($A53=3+$D$14,Premissas!$B$56,IF($A53=6+$D$14,Premissas!$B$57,0)))) -> -37370.236 | BJ53: =BH53+BI53 -> 22039.902 | BK53: =BK52+BJ53 -> -136897.51 | BL53: =IF(BJ53>0,$A53,9999) -> 12 | BM53: =IF(BK53>0,$A53,9999) -> 9999 | BN53: =IF($A53-$D$15<Premissas!$B$41,0,$C$15*(Premissas!$B$39+(Premissas!$B$40-Premissas!$B$39)*$A53/36)/(1+EXP(-$K$15*($A53-$D$15-$I$15)))) -> 34.45633 | BO53: =(BN53*$B$15+IF($A53>=Premissas!$B$46+$D$15,$F$15,0))*(1-$E$15)*(1-Premissas!$B$60) -> 20991.569 | BP53: =-(BN53*$J$15+MAX(0,BN53-BN52)*$H$15+IF($A53-$D$15<=2,Premissas!$B$49,IF($A53-$D$15<=5,Premissas!$B$50,IF($A53-$D$15<=8,Premissas!$B$51,$G$15)))+IF($A53=1+$D$15,Premissas!$B$55,IF($A53=3+$D$15,Premissas!$B$56,IF($A53=6+$D$15,Premissas!$B$57,0)))) -> -39793.387 | BQ53: =BO53+BP53 -> -18801.818 | BR53: =BR52+BQ53 -> -272435.52 | BS53: =IF(BQ53>0,$A53,9999) -> 9999 | BT53: =IF(BR53>0,$A53,9999) -> 9999 | BU53: =IF($A53-$D$16<Premissas!$B$41,0,$C$16*(Premissas!$B$39+(Premissas!$B$40-Premissas!$B$39)*$A53/36)/(1+EXP(-$K$16*($A53-$D$16-$I$16)))) -> 68.912659 | BV53: =(BU53*$B$16+IF($A53>=Premissas!$B$46+$D$16,$F$16,0))*(1-$E$16)*(1-Premissas!$B$60) -> 20789.04 | BW53: =-(BU53*$J$16+MAX(0,BU53-BU52)*$H$16+IF($A53-$D$16<=2,Premissas!$B$49,IF($A53-$D$16<=5,Premissas!$B$50,IF($A53-$D$16<=8,Premissas!$B$51,$G$16)))+IF($A53=1+$D$16,Premissas!$B$55,IF($A53=3+$D$16,Premissas!$B$56,IF($A53=6+$D$16,Premissas!$B$57,0)))) -> -44586.774 | BX53: =BV53+BW53 -> -23797.734 | BY53: =BY52+BX53 -> -294417.72 | BZ53: =IF(BX53>0,$A53,9999) -> 9999 | CA53: =IF(BY53>0,$A53,9999) -> 9999 | CB53: =IF($A53-$D$17<Premissas!$B$41,0,$C$17*(Premissas!$B$39+(Premissas!$B$40-Premissas!$B$39)*$A53/36)/(1+EXP(-$K$17*($A53-$D$17-$I$17)))) -> 0 | CC53: =(CB53*$B$17+IF($A53>=Premissas!$B$46+$D$17,$F$17,0))*(1-$E$17)*(1-Premissas!$B$60) -> 0 | CD53: =-(CB53*$J$17+MAX(0,CB53-CB52)*$H$17+IF($A53-$D$17<=2,Premissas!$B$49,IF($A53-$D$17<=5,Premissas!$B$50,IF($A53-$D$17<=8,Premissas!$B$51,$G$17)))+IF($A53=1+$D$17,Premissas!$B$55,IF($A53=3+$D$17,Premissas!$B$56,IF($A53=6+$D$17,Premissas!$B$57,0)))) -> -38000 | CE53: =CC53+CD53 -> -38000 | CF53: =CF52+CE53 -> -164000 | CG53: =IF(CE53>0,$A53,9999) -> 9999 | CH53: =IF(CF53>0,$A53,9999) -> 9999
A54: 13 | C54: =IF($A54-$D$6<Premissas!$B$41,0,$C$6*(Premissas!$B$39+(Premissas!$B$40-Premissas!$B$39)*$A54/36)/(1+EXP(-$K$6*($A54-$D$6-$I$6)))) -> 88.550646 | D54: =(C54*$B$6+IF($A54>=Premissas!$B$46+$D$6,$F$6,0))*(1-$E$6)*(1-Premissas!$B$60) -> 38247.656 | E54: =-(C54*$J$6+MAX(0,C54-C53)*$H$6+IF($A54-$D$6<=2,Premissas!$B$49,IF($A54-$D$6<=5,Premissas!$B$50,IF($A54-$D$6<=8,Premissas!$B$51,$G$6)))+IF($A54=1+$D$6,Premissas!$B$55,IF($A54=3+$D$6,Premissas!$B$56,IF($A54=6+$D$6,Premissas!$B$57,0)))) -> -46839.974 | F54: =D54+E54 -> -8592.3177 | G54: =G53+F54 -> -263463.37 | H54: =IF(F54>0,$A54,9999) -> 9999 | I54: =IF(G54>0,$A54,9999) -> 9999 | J54: =IF($A54-$D$7<Premissas!$B$41,0,$C$7*(Premissas!$B$39+(Premissas!$B$40-Premissas!$B$39)*$A54/36)/(1+EXP(-$K$7*($A54-$D$7-$I$7)))) -> 285.42889 | K54: =(J54*$B$7+IF($A54>=Premissas!$B$46+$D$7,$F$7,0))*(1-$E$7)*(1-Premissas!$B$60) -> 71507.429 | L54: =-(J54*$J$7+MAX(0,J54-J53)*$H$7+IF($A54-$D$7<=2,Premissas!$B$49,IF($A54-$D$7<=5,Premissas!$B$50,IF($A54-$D$7<=8,Premissas!$B$51,$G$7)))+IF($A54=1+$D$7,Premissas!$B$55,IF($A54=3+$D$7,Premissas!$B$56,IF($A54=6+$D$7,Premissas!$B$57,0)))) -> -49685.291 | M54: =K54+L54 -> 21822.138 | N54: =N53+M54 -> -155075.37 | O54: =IF(M54>0,$A54,9999) -> 13 | P54: =IF(N54>0,$A54,9999) -> 9999 | Q54: =IF($A54-$D$8<Premissas!$B$41,0,$C$8*(Premissas!$B$39+(Premissas!$B$40-Premissas!$B$39)*$A54/36)/(1+EXP(-$K$8*($A54-$D$8-$I$8)))) -> 285.42889 | R54: =(Q54*$B$8+IF($A54>=Premissas!$B$46+$D$8,$F$8,0))*(1-$E$8)*(1-Premissas!$B$60) -> 95343.239 | S54: =-(Q54*$J$8+MAX(0,Q54-Q53)*$H$8+IF($A54-$D$8<=2,Premissas!$B$49,IF($A54-$D$8<=5,Premissas!$B$50,IF($A54-$D$8<=8,Premissas!$B$51,$G$8)))+IF($A54=1+$D$8,Premissas!$B$55,IF($A54=3+$D$8,Premissas!$B$56,IF($A54=6+$D$8,Premissas!$B$57,0)))) -> -49685.291 | T54: =R54+S54 -> 45657.947 | U54: =U53+T54 -> -66001.808 | V54: =IF(T54>0,$A54,9999) -> 13 | W54: =IF(U54>0,$A54,9999) -> 9999 | X54: =IF($A54-$D$9<Premissas!$B$41,0,$C$9*(Premissas!$B$39+(Premissas!$B$40-Premissas!$B$39)*$A54/36)/(1+EXP(-$K$9*($A54-$D$9-$I$9)))) -> 285.42889 | Y54: =(X54*$B$9+IF($A54>=Premissas!$B$46+$D$9,$F$9,0))*(1-$E$9)*(1-Premissas!$B$60) -> 76274.591 | Z54: =-(X54*$J$9+MAX(0,X54-X53)*$H$9+IF($A54-$D$9<=2,Premissas!$B$49,IF($A54-$D$9<=5,Premissas!$B$50,IF($A54-$D$9<=8,Premissas!$B$51,$G$9)))+IF($A54=1+$D$9,Premissas!$B$55,IF($A54=3+$D$9,Premissas!$B$56,IF($A54=6+$D$9,Premissas!$B$57,0)))) -> -49685.291 | AA54: =Y54+Z54 -> 26589.3 | AB54: =AB53+AA54 -> -137260.66 | AC54: =IF(AA54>0,$A54,9999) -> 13 | AD54: =IF(AB54>0,$A54,9999) -> 9999 | AE54: =IF($A54-$D$10<Premissas!$B$41,0,$C$10*(Premissas!$B$39+(Premissas!$B$40-Premissas!$B$39)*$A54/36)/(1+EXP(-$K$10*($A54-$D$10-$I$10)))) -> 285.42889 | AF54: =(AE54*$B$10+IF($A54>=Premissas!$B$46+$D$10,$F$10,0))*(1-$E$10)*(1-Premissas!$B$60) -> 66740.267 | AG54: =-(AE54*$J$10+MAX(0,AE54-AE53)*$H$10+IF($A54-$D$10<=2,Premissas!$B$49,IF($A54-$D$10<=5,Premissas!$B$50,IF($A54-$D$10<=8,Premissas!$B$51,$G$10)))+IF($A54=1+$D$10,Premissas!$B$55,IF($A54=3+$D$10,Premissas!$B$56,IF($A54=6+$D$10,Premissas!$B$57,0)))) -> -49685.291 | AH54: =AF54+AG54 -> 17054.976 | AI54: =AI53+AH54 -> -172890.08 | AJ54: =IF(AH54>0,$A54,9999) -> 13 | AK54: =IF(AI54>0,$A54,9999) -> 9999 | AL54: =IF($A54-$D$11<Premissas!$B$41,0,$C$11*(Premissas!$B$39+(Premissas!$B$40-Premissas!$B$39)*$A54/36)/(1+EXP(-$K$11*($A54-$D$11-$I$11)))) -> 285.42889 | AM54: =(AL54*$B$11+IF($A54>=Premissas!$B$46+$D$11,$F$11,0))*(1-$E$11)*(1-Premissas!$B$60) -> 57205.943 | AN54: =-(AL54*$J$11+MAX(0,AL54-AL53)*$H$11+IF($A54-$D$11<=2,Premissas!$B$49,IF($A54-$D$11<=5,Premissas!$B$50,IF($A54-$D$11<=8,Premissas!$B$51,$G$11)))+IF($A54=1+$D$11,Premissas!$B$55,IF($A54=3+$D$11,Premissas!$B$56,IF($A54=6+$D$11,Premissas!$B$57,0)))) -> -49685.291 | AO54: =AM54+AN54 -> 7520.6518 | AP54: =AP53+AO54 -> -208519.51 | AQ54: =IF(AO54>0,$A54,9999) -> 13 | AR54: =IF(AP54>0,$A54,9999) -> 9999 | AS54: =IF($A54-$D$12<Premissas!$B$41,0,$C$12*(Premissas!$B$39+(Premissas!$B$40-Premissas!$B$39)*$A54/36)/(1+EXP(-$K$12*($A54-$D$12-$I$12)))) -> 285.42889 | AT54: =(AS54*$B$12+IF($A54>=Premissas!$B$46+$D$12,$F$12,0))*(1-$E$12)*(1-Premissas!$B$60) -> 60803.846 | AU54: =-(AS54*$J$12+MAX(0,AS54-AS53)*$H$12+IF($A54-$D$12<=2,Premissas!$B$49,IF($A54-$D$12<=5,Premissas!$B$50,IF($A54-$D$12<=8,Premissas!$B$51,$G$12)))+IF($A54=1+$D$12,Premissas!$B$55,IF($A54=3+$D$12,Premissas!$B$56,IF($A54=6+$D$12,Premissas!$B$57,0)))) -> -49685.291 | AV54: =AT54+AU54 -> 11118.554 | AW54: =AW53+AV54 -> -193490.2 | AX54: =IF(AV54>0,$A54,9999) -> 13 | AY54: =IF(AW54>0,$A54,9999) -> 9999 | AZ54: =IF($A54-$D$13<Premissas!$B$41,0,$C$13*(Premissas!$B$39+(Premissas!$B$40-Premissas!$B$39)*$A54/36)/(1+EXP(-$K$13*($A54-$D$13-$I$13)))) -> 44.568856 | BA54: =(AZ54*$B$13+IF($A54>=Premissas!$B$46+$D$13,$F$13,0))*(1-$E$13)*(1-Premissas!$B$60) -> 9994.566 | BB54: =-(AZ54*$J$13+MAX(0,AZ54-AZ53)*$H$13+IF($A54-$D$13<=2,Premissas!$B$49,IF($A54-$D$13<=5,Premissas!$B$50,IF($A54-$D$13<=8,Premissas!$B$51,$G$13)))+IF($A54=1+$D$13,Premissas!$B$55,IF($A54=3+$D$13,Premissas!$B$56,IF($A54=6+$D$13,Premissas!$B$57,0)))) -> -32100.335 | BC54: =BA54+BB54 -> -22105.769 | BD54: =BD53+BC54 -> -186105.77 | BE54: =IF(BC54>0,$A54,9999) -> 9999 | BF54: =IF(BD54>0,$A54,9999) -> 9999 | BG54: =IF($A54-$D$14<Premissas!$B$41,0,$C$14*(Premissas!$B$39+(Premissas!$B$40-Premissas!$B$39)*$A54/36)/(1+EXP(-$K$14*($A54-$D$14-$I$14)))) -> 285.42889 | BH54: =(BG54*$B$14+IF($A54>=Premissas!$B$46+$D$14,$F$14,0))*(1-$E$14)*(1-Premissas!$B$60) -> 71507.429 | BI54: =-(BG54*$J$14+MAX(0,BG54-BG53)*$H$14+IF($A54-$D$14<=2,Premissas!$B$49,IF($A54-$D$14<=5,Premissas!$B$50,IF($A54-$D$14<=8,Premissas!$B$51,$G$14)))+IF($A54=1+$D$14,Premissas!$B$55,IF($A54=3+$D$14,Premissas!$B$56,IF($A54=6+$D$14,Premissas!$B$57,0)))) -> -39685.291 | BJ54: =BH54+BI54 -> 31822.138 | BK54: =BK53+BJ54 -> -105075.37 | BL54: =IF(BJ54>0,$A54,9999) -> 13 | BM54: =IF(BK54>0,$A54,9999) -> 9999 | BN54: =IF($A54-$D$15<Premissas!$B$41,0,$C$15*(Premissas!$B$39+(Premissas!$B$40-Premissas!$B$39)*$A54/36)/(1+EXP(-$K$15*($A54-$D$15-$I$15)))) -> 44.275323 | BO54: =(BN54*$B$15+IF($A54>=Premissas!$B$46+$D$15,$F$15,0))*(1-$E$15)*(1-Premissas!$B$60) -> 24123.828 | BP54: =-(BN54*$J$15+MAX(0,BN54-BN53)*$H$15+IF($A54-$D$15<=2,Premissas!$B$49,IF($A54-$D$15<=5,Premissas!$B$50,IF($A54-$D$15<=8,Premissas!$B$51,$G$15)))+IF($A54=1+$D$15,Premissas!$B$55,IF($A54=3+$D$15,Premissas!$B$56,IF($A54=6+$D$15,Premissas!$B$57,0)))) -> -40919.987 | BQ54: =BO54+BP54 -> -16796.159 | BR54: =BR53+BQ54 -> -289231.68 | BS54: =IF(BQ54>0,$A54,9999) -> 9999 | BT54: =IF(BR54>0,$A54,9999) -> 9999 | BU54: =IF($A54-$D$16<Premissas!$B$41,0,$C$16*(Premissas!$B$39+(Premissas!$B$40-Premissas!$B$39)*$A54/36)/(1+EXP(-$K$16*($A54-$D$16-$I$16)))) -> 88.550646 | BV54: =(BU54*$B$16+IF($A54>=Premissas!$B$46+$D$16,$F$16,0))*(1-$E$16)*(1-Premissas!$B$60) -> 24860.976 | BW54: =-(BU54*$J$16+MAX(0,BU54-BU53)*$H$16+IF($A54-$D$16<=2,Premissas!$B$49,IF($A54-$D$16<=5,Premissas!$B$50,IF($A54-$D$16<=8,Premissas!$B$51,$G$16)))+IF($A54=1+$D$16,Premissas!$B$55,IF($A54=3+$D$16,Premissas!$B$56,IF($A54=6+$D$16,Premissas!$B$57,0)))) -> -46839.974 | BX54: =BV54+BW54 -> -21978.997 | BY54: =BY53+BX54 -> -316396.71 | BZ54: =IF(BX54>0,$A54,9999) -> 9999 | CA54: =IF(BY54>0,$A54,9999) -> 9999 | CB54: =IF($A54-$D$17<Premissas!$B$41,0,$C$17*(Premissas!$B$39+(Premissas!$B$40-Premissas!$B$39)*$A54/36)/(1+EXP(-$K$17*($A54-$D$17-$I$17)))) -> 8.4993465 | CC54: =(CB54*$B$17+IF($A54>=Premissas!$B$46+$D$17,$F$17,0))*(1-$E$17)*(1-Premissas!$B$60) -> 1762.3395 | CD54: =-(CB54*$J$17+MAX(0,CB54-CB53)*$H$17+IF($A54-$D$17<=2,Premissas!$B$49,IF($A54-$D$17<=5,Premissas!$B$50,IF($A54-$D$17<=8,Premissas!$B$51,$G$17)))+IF($A54=1+$D$17,Premissas!$B$55,IF($A54=3+$D$17,Premissas!$B$56,IF($A54=6+$D$17,Premissas!$B$57,0)))) -> -31782.209 | CE54: =CC54+CD54 -> -30019.87 | CF54: =CF53+CE54 -> -194019.87 | CG54: =IF(CE54>0,$A54,9999) -> 9999 | CH54: =IF(CF54>0,$A54,9999) -> 9999
... A77: 36 | C77: =IF($A77-$D$6<Premissas!$B$41,0,$C$6*(Premissas!$B$39+(Premissas!$B$40-Premissas!$B$39)*$A77/36)/(1+EXP(-$K$6*($A77-$D$6-$I$6)))) -> 389.35307 | D77: =(C77*$B$6+IF($A77>=Premissas!$B$46+$D$6,$F$6,0))*(1-$E$6)*(1-Premissas!$B$60) -> 134203.63 | E77: =-(C77*$J$6+MAX(0,C77-C76)*$H$6+IF($A77-$D$6<=2,Premissas!$B$49,IF($A77-$D$6<=5,Premissas!$B$50,IF($A77-$D$6<=8,Premissas!$B$51,$G$6)))+IF($A77=1+$D$6,Premissas!$B$55,IF($A77=3+$D$6,Premissas!$B$56,IF($A77=6+$D$6,Premissas!$B$57,0)))) -> -53836.025 | F77: =D77+E77 -> 80367.604 | G77: =G76+F77 -> 953228.72 | H77: =IF(F77>0,$A77,9999) -> 36 | I77: =IF(G77>0,$A77,9999) -> 36 | J77: =IF($A77-$D$7<Premissas!$B$41,0,$C$7*(Premissas!$B$39+(Premissas!$B$40-Premissas!$B$39)*$A77/36)/(1+EXP(-$K$7*($A77-$D$7-$I$7)))) -> 569.98837 | K77: =(J77*$B$7+IF($A77>=Premissas!$B$46+$D$7,$F$7,0))*(1-$E$7)*(1-Premissas!$B$60) -> 135319.89 | L77: =-(J77*$J$7+MAX(0,J77-J76)*$H$7+IF($A77-$D$7<=2,Premissas!$B$49,IF($A77-$D$7<=5,Premissas!$B$50,IF($A77-$D$7<=8,Premissas!$B$51,$G$7)))+IF($A77=1+$D$7,Premissas!$B$55,IF($A77=3+$D$7,Premissas!$B$56,IF($A77=6+$D$7,Premissas!$B$57,0)))) -> -59162.821 | M77: =K77+L77 -> 76157.072 | N77: =N76+M77 -> 1302100.7 | O77: =IF(M77>0,$A77,9999) -> 36 | P77: =IF(N77>0,$A77,9999) -> 36 | Q77: =IF($A77-$D$8<Premissas!$B$41,0,$C$8*(Premissas!$B$39+(Premissas!$B$40-Premissas!$B$39)*$A77/36)/(1+EXP(-$K$8*($A77-$D$8-$I$8)))) -> 569.98837 | R77: =(Q77*$B$8+IF($A77>=Premissas!$B$46+$D$8,$F$8,0))*(1-$E$8)*(1-Premissas!$B$60) -> 180426.52 | S77: =-(Q77*$J$8+MAX(0,Q77-Q76)*$H$8+IF($A77-$D$8<=2,Premissas!$B$49,IF($A77-$D$8<=5,Premissas!$B$50,IF($A77-$D$8<=8,Premissas!$B$51,$G$8)))+IF($A77=1+$D$8,Premissas!$B$55,IF($A77=3+$D$8,Premissas!$B$56,IF($A77=6+$D$8,Premissas!$B$57,0)))) -> -59162.821 | T77: =R77+S77 -> 121263.7 | U77: =U76+T77 -> 2311592.3 | V77: =IF(T77>0,$A77,9999) -> 36 | W77: =IF(U77>0,$A77,9999) -> 36 | X77: =IF($A77-$D$9<Premissas!$B$41,0,$C$9*(Premissas!$B$39+(Premissas!$B$40-Premissas!$B$39)*$A77/36)/(1+EXP(-$K$9*($A77-$D$9-$I$9)))) -> 569.98837 | Y77: =(X77*$B$9+IF($A77>=Premissas!$B$46+$D$9,$F$9,0))*(1-$E$9)*(1-Premissas!$B$60) -> 144341.22 | Z77: =-(X77*$J$9+MAX(0,X77-X76)*$H$9+IF($A77-$D$9<=2,Premissas!$B$49,IF($A77-$D$9<=5,Premissas!$B$50,IF($A77-$D$9<=8,Premissas!$B$51,$G$9)))+IF($A77=1+$D$9,Premissas!$B$55,IF($A77=3+$D$9,Premissas!$B$56,IF($A77=6+$D$9,Premissas!$B$57,0)))) -> -59162.821 | AA77: =Y77+Z77 -> 85178.398 | AB77: =AB76+AA77 -> 1503999 | AC77: =IF(AA77>0,$A77,9999) -> 36 | AD77: =IF(AB77>0,$A77,9999) -> 36 | AE77: =IF($A77-$D$10<Premissas!$B$41,0,$C$10*(Premissas!$B$39+(Premissas!$B$40-Premissas!$B$39)*$A77/36)/(1+EXP(-$K$10*($A77-$D$10-$I$10)))) -> 569.98837 | AF77: =(AE77*$B$10+IF($A77>=Premissas!$B$46+$D$10,$F$10,0))*(1-$E$10)*(1-Premissas!$B$60) -> 126298.57 | AG77: =-(AE77*$J$10+MAX(0,AE77-AE76)*$H$10+IF($A77-$D$10<=2,Premissas!$B$49,IF($A77-$D$10<=5,Premissas!$B$50,IF($A77-$D$10<=8,Premissas!$B$51,$G$10)))+IF($A77=1+$D$10,Premissas!$B$55,IF($A77=3+$D$10,Premissas!$B$56,IF($A77=6+$D$10,Premissas!$B$57,0)))) -> -59162.821 | AH77: =AF77+AG77 -> 67135.745 | AI77: =AI76+AH77 -> 1100202.3 | AJ77: =IF(AH77>0,$A77,9999) -> 36 | AK77: =IF(AI77>0,$A77,9999) -> 36 | AL77: =IF($A77-$D$11<Premissas!$B$41,0,$C$11*(Premissas!$B$39+(Premissas!$B$40-Premissas!$B$39)*$A77/36)/(1+EXP(-$K$11*($A77-$D$11-$I$11)))) -> 569.98837 | AM77: =(AL77*$B$11+IF($A77>=Premissas!$B$46+$D$11,$F$11,0))*(1-$E$11)*(1-Premissas!$B$60) -> 108255.91 | AN77: =-(AL77*$J$11+MAX(0,AL77-AL76)*$H$11+IF($A77-$D$11<=2,Premissas!$B$49,IF($A77-$D$11<=5,Premissas!$B$50,IF($A77-$D$11<=8,Premissas!$B$51,$G$11)))+IF($A77=1+$D$11,Premissas!$B$55,IF($A77=3+$D$11,Premissas!$B$56,IF($A77=6+$D$11,Premissas!$B$57,0)))) -> -59162.821 | AO77: =AM77+AN77 -> 49093.093 | AP77: =AP76+AO77 -> 696405.66 | AQ77: =IF(AO77>0,$A77,9999) -> 36 | AR77: =IF(AP77>0,$A77,9999) -> 36 | AS77: =IF($A77-$D$12<Premissas!$B$41,0,$C$12*(Premissas!$B$39+(Premissas!$B$40-Premissas!$B$39)*$A77/36)/(1+EXP(-$K$12*($A77-$D$12-$I$12)))) -> 569.98837 | AT77: =(AS77*$B$12+IF($A77>=Premissas!$B$46+$D$12,$F$12,0))*(1-$E$12)*(1-Premissas!$B$60) -> 113945.33 | AU77: =-(AS77*$J$12+MAX(0,AS77-AS76)*$H$12+IF($A77-$D$12<=2,Premissas!$B$49,IF($A77-$D$12<=5,Premissas!$B$50,IF($A77-$D$12<=8,Premissas!$B$51,$G$12)))+IF($A77=1+$D$12,Premissas!$B$55,IF($A77=3+$D$12,Premissas!$B$56,IF($A77=6+$D$12,Premissas!$B$57,0)))) -> -59162.821 | AV77: =AT77+AU77 -> 54782.508 | AW77: =AW76+AV77 -> 830783.77 | AX77: =IF(AV77>0,$A77,9999) -> 36 | AY77: =IF(AW77>0,$A77,9999) -> 36 | AZ77: =IF($A77-$D$13<Premissas!$B$41,0,$C$13*(Premissas!$B$39+(Premissas!$B$40-Premissas!$B$39)*$A77/36)/(1+EXP(-$K$13*($A77-$D$13-$I$13)))) -> 569.82704 | BA77: =(AZ77*$B$13+IF($A77>=Premissas!$B$46+$D$13,$F$13,0))*(1-$E$13)*(1-Premissas!$B$60) -> 135283.71 | BB77: =-(AZ77*$J$13+MAX(0,AZ77-AZ76)*$H$13+IF($A77-$D$13<=2,Premissas!$B$49,IF($A77-$D$13<=5,Premissas!$B$50,IF($A77-$D$13<=8,Premissas!$B$51,$G$13)))+IF($A77=1+$D$13,Premissas!$B$55,IF($A77=3+$D$13,Premissas!$B$56,IF($A77=6+$D$13,Premissas!$B$57,0)))) -> -59160.528 | BC77: =BA77+BB77 -> 76123.185 | BD77: =BD76+BC77 -> 915408.22 | BE77: =IF(BC77>0,$A77,9999) -> 36 | BF77: =IF(BD77>0,$A77,9999) -> 36 | BG77: =IF($A77-$D$14<Premissas!$B$41,0,$C$14*(Premissas!$B$39+(Premissas!$B$40-Premissas!$B$39)*$A77/36)/(1+EXP(-$K$14*($A77-$D$14-$I$14)))) -> 569.98837 | BH77: =(BG77*$B$14+IF($A77>=Premissas!$B$46+$D$14,$F$14,0))*(1-$E$14)*(1-Premissas!$B$60) -> 135319.89 | BI77: =-(BG77*$J$14+MAX(0,BG77-BG76)*$H$14+IF($A77-$D$14<=2,Premissas!$B$49,IF($A77-$D$14<=5,Premissas!$B$50,IF($A77-$D$14<=8,Premissas!$B$51,$G$14)))+IF($A77=1+$D$14,Premissas!$B$55,IF($A77=3+$D$14,Premissas!$B$56,IF($A77=6+$D$14,Premissas!$B$57,0)))) -> -49162.821 | BJ77: =BH77+BI77 -> 86157.072 | BK77: =BK76+BJ77 -> 1582100.7 | BL77: =IF(BJ77>0,$A77,9999) -> 36 | BM77: =IF(BK77>0,$A77,9999) -> 36 | BN77: =IF($A77-$D$15<Premissas!$B$41,0,$C$15*(Premissas!$B$39+(Premissas!$B$40-Premissas!$B$39)*$A77/36)/(1+EXP(-$K$15*($A77-$D$15-$I$15)))) -> 194.67653 | BO77: =(BN77*$B$15+IF($A77>=Premissas!$B$46+$D$15,$F$15,0))*(1-$E$15)*(1-Premissas!$B$60) -> 72101.814 | BP77: =-(BN77*$J$15+MAX(0,BN77-BN76)*$H$15+IF($A77-$D$15<=2,Premissas!$B$49,IF($A77-$D$15<=5,Premissas!$B$50,IF($A77-$D$15<=8,Premissas!$B$51,$G$15)))+IF($A77=1+$D$15,Premissas!$B$55,IF($A77=3+$D$15,Premissas!$B$56,IF($A77=6+$D$15,Premissas!$B$57,0)))) -> -44418.012 | BQ77: =BO77+BP77 -> 27683.802 | BR77: =BR76+BQ77 -> 31614.361 | BS77: =IF(BQ77>0,$A77,9999) -> 36 | BT77: =IF(BR77>0,$A77,9999) -> 36 | BU77: =IF($A77-$D$16<Premissas!$B$41,0,$C$16*(Premissas!$B$39+(Premissas!$B$40-Premissas!$B$39)*$A77/36)/(1+EXP(-$K$16*($A77-$D$16-$I$16)))) -> 389.35307 | BV77: =(BU77*$B$16+IF($A77>=Premissas!$B$46+$D$16,$F$16,0))*(1-$E$16)*(1-Premissas!$B$60) -> 87232.359 | BW77: =-(BU77*$J$16+MAX(0,BU77-BU76)*$H$16+IF($A77-$D$16<=2,Premissas!$B$49,IF($A77-$D$16<=5,Premissas!$B$50,IF($A77-$D$16<=8,Premissas!$B$51,$G$16)))+IF($A77=1+$D$16,Premissas!$B$55,IF($A77=3+$D$16,Premissas!$B$56,IF($A77=6+$D$16,Premissas!$B$57,0)))) -> -53836.025 | BX77: =BV77+BW77 -> 33396.334 | BY77: =BY76+BX77 -> 40684.945 | BZ77: =IF(BX77>0,$A77,9999) -> 36 | CA77: =IF(BY77>0,$A77,9999) -> 36 | CB77: =IF($A77-$D$17<Premissas!$B$41,0,$C$17*(Premissas!$B$39+(Premissas!$B$40-Premissas!$B$39)*$A77/36)/(1+EXP(-$K$17*($A77-$D$17-$I$17)))) -> 192.81475 | CC77: =(CB77*$B$17+IF($A77>=Premissas!$B$46+$D$17,$F$17,0))*(1-$E$17)*(1-Premissas!$B$60) -> 46480.139 | CD77: =-(CB77*$J$17+MAX(0,CB77-CB76)*$H$17+IF($A77-$D$17<=2,Premissas!$B$49,IF($A77-$D$17<=5,Premissas!$B$50,IF($A77-$D$17<=8,Premissas!$B$51,$G$17)))+IF($A77=1+$D$17,Premissas!$B$55,IF($A77=3+$D$17,Premissas!$B$56,IF($A77=6+$D$17,Premissas!$B$57,0)))) -> -44602.144 | CE77: =CC77+CD77 -> 1877.9942 | CF77: =CF76+CE77 -> -495982.8 | CG77: =IF(CE77>0,$A77,9999) -> 36 | CH77: =IF(CF77>0,$A77,9999) -> 9999

Sheet Descoberta
A1: Plano de descoberta — 34 itens
A2: Marque o status e anote a resposta. Os seis bloqueantes vêm primeiro.
A4: Código | B4: Categoria | C4: Prioridade | D4: Onda | E4: Pergunta | F4: O que muda | G4: Quem responde | H4: Status | I4: Resposta / anotação | J4: Data
A5: J1 | B5: Jurídico | C5: Bloqueante | D5: 1 | E5: A cláusula 13.13 alcança um software que eu escrevi? Cessão universal e gratuita é exigível ou abusiva num contrato de adesão? | F5: Tudo. Se alcança, o único caminho é negociar. | G5: Advogado de franquias | H5: Não iniciado
A6: J2 | B6: Jurídico | C6: Bloqueante | D6: 1 | E6: A Lei de Software (9.609/98) muda algo, sendo o autor pessoa física fora de vínculo empregatício? | F6: Define a força do argumento de titularidade. | G6: Advogado de franquias | H6: Não iniciado
A7: J3 | B7: Jurídico | C7: Bloqueante | D7: 1 | E7: Qual o risco das três exposições atuais — painel público, sync do HubSpot, campanhas — e em que ordem corrigir? | F7: Define o que fazer nesta semana. | G7: Advogado de franquias | H7: Não iniciado
A8: T1 | B8: Trinks | C8: Bloqueante | D8: 1 | E8: Existe autorização para uso comercial da API? Qual o processo para o contrato específico que os Termos exigem? | F8: Se não existe caminho, não há produto sobre a API. | G8: Comercial Trinks | H8: Não iniciado
A9: T2 | B9: Trinks | C9: Bloqueante | D9: 1 | E9: A cota de 10.000 requisições/mês é por estabelecimento ou por conta? | F9: Se for por conta, o custo unitário muda e o modelo é refeito. | G9: Suporte técnico Trinks | H9: Não iniciado
A10: T3 | B10: Trinks | C10: Bloqueante | D10: 1 | E10: Existe programa formal de parceiro ou integrador? Contrato-tipo, requisitos, prazo? | F10: Define o prazo da Onda 1 e se há atalho. | G10: Parcerias Trinks | H10: Não iniciado
A11: J4 | B11: Jurídico | C11: Estrutural | D11: 2 | E11: Como demonstrar o produto sem entregar o ativo? Existe NDA ou memorando que preserve minha posição? | F11: Define se a reunião da semana 4 pode acontecer. | G11: Advogado de franquias | H11: Não iniciado
A12: J5 | B12: Jurídico | C12: Estrutural | D12: 2 | E12: Qual estrutura usar: PJ separada, sociedade com a franqueadora, ou licenciamento? | F12: Define qual das três estruturas é viável. | G12: Advogado de franquias | H12: Não iniciado
A13: J6 | B13: Jurídico | C13: Estrutural | D13: 2 | E13: Sendo franqueado e fornecedor homologado ao mesmo tempo, há conflito a tratar no contrato? | F13: Define cláusulas do contrato de homologação. | G13: Advogado de franquias | H13: Não iniciado
A14: J7 | B14: Jurídico | C14: Estrutural | D14: 2 | E14: Um produto genérico feito do zero, fora do horário e sem material dos MANUAIS, escapa da 13.13? Que provas de segregação preciso desde já? | F14: Define se o plano B existe — e as provas começam antes. | G14: Advogado de franquias | H14: Não iniciado
A15: T4 | B15: Trinks | C15: Estrutural | D15: 2 | E15: A parceria envolve taxa, participação na receita, ou é gratuita? | F15: Entra direto no custo variável por loja. | G15: Comercial Trinks | H15: Não iniciado
A16: T5 | B16: Trinks | C16: Estrutural | D16: 2 | E16: A API tem endpoints incrementais (updated_since, delta, webhooks) ou só paginação completa? | F16: Define o custo da Fase 3 e a economia de 70% de requisições. | G16: Documentação e suporte Trinks | H16: Não iniciado
... A38: N2 | B38: Números | C38: Refinamento | D38: 3 | E38: Custo real de suporte por loja, medido no piloto. | F38: Modelado em R$ 34. É o maior componente do custo variável. | G38: Você, medindo | H38: Não iniciado
A40: Progresso | E40: =COUNTIF(H5:H38,"Respondido")&" de 34 respondidos" -> 0 de 34 respondidos
E41: =COUNTIFS(C5:C38,"Bloqueante",H5:H38,"Respondido")&" de 6 bloqueantes respondidos" -> 0 de 6 bloqueantes respondidos
A43: Seis itens bloqueantes. Um advogado e três telefonemas — é todo o custo de descobrir se este projeto existe.
